Workbook
Name LP: #REF!

Sheet Sheet1
A1: EXPO | B1: Not Finish

Sheet Valuation Sheet
B1: Ticker | C1: Price | D1: Earnings | E1: Sales | F1: EPS | G1: NAVPS | H1: RoE | I1: Normalized P/E | J1: P/B | K1: Dividend Yield | L1: P/E | O1: Sales | R1: Earnings | U1: EPS | X1: DPS | AA1: FY+1
D2: TTM | E2: TTM | F2: TTM - EPS | H2: Avg | L2: FY24E | M2: FY25E | N2: FY26E | O2: FY24E | P2: FY25E | Q2: FY26E | R2: FY24E | S2: FY25E | T2: FY26E | U2: FY24E | V2: FY25E | W2: FY26E | X2: FY24E | Y2: FY25E | Z2: FY26E | AA2: Sales growth | AB2: EPS Growth | AC2: No of Shares
A3: 1 | B3: MGT | C3: 46.9 | D3: =+SUM(MGT!AI26:AL26)/1000 -> 2544.412 | E3: =+SUM(MGT!AI3:AL3)/1000 -> 50252.886 | F3: =+SUM(MGT!AI29:AL29) -> 6.1240039 | G3: =+MGT!AL46 -> 24.110887 | H3: =+MGT!AO33 -> 0.22511269 | I3: =+MGT!AO35 -> 8.0028419 | J3: =+C3/G3 -> 1.9451794 | K3: =+Y3/C3 -> 0.056289979 | L3: =+C3/U3 -> 6.3228851 | M3: =+C3/V3 -> 6.1852951 | N3: =+C3/W3 -> 5.6285629 | O3: =+MGT!AQ11 -> 62655.5 | P3: =+MGT!AV11 -> 55904 | Q3: =+MGT!BA11 -> 62636 | R3: =+MGT!AS11 -> 3075 | S3: =+MGT!AX11 -> 3550 | T3: =+MGT!BC11 -> 3902.5 | U3: =+MGT!AT11 -> 7.4175 | V3: =+MGT!AY11 -> 7.5825 | W3: =+MGT!BD11 -> 8.3325 | X3: =+MGT!AU11 -> 2.575 | Y3: =+MGT!AZ11 -> 2.64 | Z3: =+MGT!BE11 -> 2.84 | AA3: =+P3/O3-1 -> -0.1077559 | AB3: =+S3/R3-1 -> 0.15447154 | AC3: =+MGT!AK44 -> 415481.78
A4: 2 | B4: TJL | C4: 40 | D4: =+SUM(TJL!C24:F24)/1000 -> 1116.479 | E4: =+SUM(TJL!C2:F2)/1000 -> 60698.88 | F4: =+SUM(TJL!C27:F27) -> 1.5577183 | G4: =+TJL!F45 -> 42.011675 | H4: =+TJL!#REF! -> #REF! | I4: =+TJL!#REF! -> #REF! | J4: =+C4/G4 -> 0.95211628 | K4: =+Y4/C4 -> #REF! | L4: =+C4/U4 -> #REF! | M4: =+C4/V4 -> #REF! | N4: =+C4/W4 -> #REF! | O4: =+TJL!#REF! -> #REF! | P4: =+TJL!#REF! -> #REF! | Q4: =+TJL!#REF! -> #REF! | R4: =+TJL!#REF! -> #REF! | S4: =+TJL!#REF! -> #REF! | T4: =+TJL!#REF! -> #REF! | U4: =+TJL!#REF! -> #REF! | V4: =+TJL!#REF! -> #REF! | ... Z4: =+TJL!#REF! -> #REF! | AA4: =+P4/O4-1 -> #REF! | AB4: =+S4/R4-1 -> #REF! | AC4: =+TJL!E43 -> 716739.97
A5: 3 | B5: BPPL | C5: 18.4 | D5: =+SUM(BPPL!AJ26:AM26)/1000 -> 422.00336 | E5: =+SUM(BPPL!AJ3:AM3)/1000 -> 5933.416 | F5: =+SUM(BPPL!AJ29:AM29) -> 1.3753055 | G5: =+BPPL!AM46 -> 13.086935 | H5: =+BPPL!AO33 -> 0.15382125 | I5: =+BPPL!AO35 -> 9.1403653 | J5: =+C5/G5 -> 1.4059824 | AC5: =+BPPL!AK44 -> 306843.36
A6: 4 | B6: HAYL | C6: 95.6 | D6: =+SUM(HAYL!AI28:AL28)/1000 -> 6888.77 | E6: =+SUM(HAYL!AI3:AL3)/1000 -> 436833.27 | F6: =+SUM(HAYL!AI31:AL31) -> 9.1850267 | G6: =+HAYL!AL48 -> 106.88399 | H6: =+HAYL!AN35 -> 0.20139277 | I6: =+HAYL!AN37 -> 4.4412104 | J6: =+C6/G6 -> 0.89442768 | L6: =+C6/U6 -> 10.402612 | M6: =+C6/V6 -> 5.3259053 | O6: =+HAYL!AP11 -> 416563 | P6: =+HAYL!AU11 -> 448372 | R6: =+HAYL!AR11 -> 6892 | S6: =+HAYL!AW11 -> 13460 | U6: =+HAYL!AS11 -> 9.19 | V6: =+HAYL!AX11 -> 17.95 | AA6: =+P6/O6-1 -> 0.076360599 | AB6: =+S6/R6-1 -> 0.95298897 | AC6: =+HAYL!AK46 -> 750000
A7: 5 | B7: HAYC | C7: 79 | D7: =+SUM(HAYC!AI29:AL29)/1000 -> 3743.929 | E7: =+SUM(HAYC!AI3:AL3)/1000 -> 43179.205 | F7: =+SUM(HAYC!AI32:AL32) -> 12.600571 | G7: =+HAYC!AL49 -> 77.089304 | H7: =+HAYC!AN36 -> 0.21881837 | I7: =+HAYC!AN38 -> 4.6832699 | J7: =+C7/G7 -> 1.0247855 | AC7: =+HAYC!AK47 -> 297123.75
A8: 6 | B8: HELA | C8: 5.2 | D8: =+SUM(HELA!AI28:AL28)/1000 -> -1852.217 | E8: =+SUM(HELA!AI3:AL3)/1000 -> 70180.266 | F8: =+SUM(HELA!AI31:AL31) -> -1.4338827 | G8: =+HELA!AL48 -> 6.3843371 | J8: =+C8/G8 -> 0.81449333 | AC8: =+HELA!AK46 -> 1309955.9
A9: 7 | B9: EXPO | C9: 151 | E9: =+SUM(EXPO!AH3:AK3)/1000 -> 239094.62 | F9: =+SUM(EXPO!AH32:AK32) -> -6.9347098 | G9: =+EXPO!AK49 -> 66.043483 | H9: =+EXPO!AO33 -> 0.50793182 | I9: =+EXPO!AO35 -> 4.5013373 | J9: =+C9/G9 -> 2.2863724 | AC9: =+EXPO!AK47 -> 1954915
A10: 8 | B10: GLAS | C10: 27.7 | D10: =+SUM(GLAS!AI26:AL26)/1000 -> 2938.83 | E10: =+SUM(GLAS!AI3:AL3)/1000 -> 17823.509 | F10: =+SUM(GLAS!AI29:AL29) -> 3.093225 | G10: =+GLAS!AL46 -> 11.649883 | H10: =+GLAS!AO33 -> 0.31506446 | I10: =+GLAS!AO35 -> 7.1048548 | J10: =+C10/G10 -> 2.3777062 | K10: =+Y10/C10 -> 0.068592058 | L10: =+C10/U10 -> 9.3581081 | M10: =+C10/V10 -> 7.5271739 | O10: =+GLAS!AQ11 -> 17866 | P10: =+GLAS!AV11 -> 22199 | R10: =+GLAS!AS11 -> 2814 | S10: =+GLAS!AX11 -> 3492 | U10: =+GLAS!AT11 -> 2.96 | V10: =+GLAS!AY11 -> 3.68 | X10: =+GLAS!AU11 -> 1.5 | Y10: =+GLAS!AZ11 -> 1.9 | AA10: =+P10/O10-1 -> 0.24252771 | AB10: =+S10/R10-1 -> 0.24093817 | AC10: =+GLAS!AL44 -> 950086.08
A11: 9 | B11: TKYO | C11: 48.8 | D11: =+SUM(TKYO!AI28:AL28)/1000 -> 2418.725 | E11: =+SUM(TKYO!AI3:AL3)/1000 -> 49823.793 | F11: =+SUM(TKYO!AI31:AL31) -> 5.4840776 | G11: =+TKYO!AL49 -> 62.391858 | H11: =+TKYO!AN35 -> 0.13288721 | I11: =+TKYO!AN37 -> 5.8858436 | J11: =+C11/G11 -> 0.78215334 | K11: =+Y11/C11 -> 0.029713115 | L11: =+C11/U11 -> 4.9317837 | M11: =+C11/V11 -> 6 | O11: =+TKYO!AP11 -> 55247.5 | P11: =+TKYO!AU11 -> 57164.873 | R11: =+TKYO!AR11 -> 4371.5 | S11: =+TKYO!AW11 -> 3581.8067 | U11: =+TKYO!AS11 -> 9.895 | V11: =+TKYO!AX11 -> 8.1333333 | X11: =+TKYO!AT11 -> 1.8 | Y11: =+TKYO!AY11 -> 1.45 | AA11: =+P11/O11-1 -> 0.03470516 | AB11: =+S11/R11-1 -> -0.18064585 | AC11: =+TKYO!AK47 -> 441045
A12: 10 | B12: TILE | C12: 48.9 | D12: =+SUM(TILE!AI28:AL28)/1000 -> 2912.278 | E12: =+SUM(TILE!AI3:AL3)/1000 -> 16131.536 | F12: =+SUM(TILE!AI31:AL31) -> 10.979286 | G12: =+TILE!AL49 -> 56.305925 | H12: =+TILE!AN35 -> 0.21536605 | I12: =+TILE!AN37 -> 4.0325293 | J12: =+C12/G12 -> 0.86846988 | AC12: =+TILE!AK47 -> 265252.05
A13: 11 | B13: JAT | C13: 17.9 | D13: =+SUM(JAT!AI28:AL28)/1000 -> 1021.2017 | E13: =+SUM(JAT!AI3:AL3)/1000 -> 11560.476 | F13: =+SUM(JAT!AI31:AL31) -> 2.0007565 | G13: =+JAT!AL49 -> 17.916 | H13: =+JAT!AN35 -> 0.12066455 | I13: =+JAT!AN37 -> 8.2800373 | J13: =+C13/G13 -> 0.99910697 | AC13: =+JAT!AK47 -> 510407.77
A14: 12 | B14: CARG | C14: 371 | D14: =+SUM(CARG!AI28:AL28)/1000 -> 5886.785 | E14: =+SUM(CARG!AI3:AL3)/1000 -> 223440.48 | F14: =+SUM(CARG!AI31:AL31) -> 22.845533 | G14: =+CARG!AL49 -> 125.86176 | H14: =+CARG!AN35 -> 0.21500723 | I14: =+CARG!AN37 -> 13.709671 | J14: =+C14/G14 -> 2.9476784 | K14: =+Y14/C14 -> 0.039254268 | L14: =+C14/U14 -> 12.079444 | M14: =+C14/V14 -> 8.4812924 | O14: =+CARG!AP11 -> 229901.67 | P14: =+CARG!AU11 -> 264689.33 | R14: =+CARG!AR11 -> 7917 | S14: =+CARG!AW11 -> 11268.333 | U14: =+CARG!AS11 -> 30.713333 | V14: =+CARG!AX11 -> 43.743333 | X14: =+CARG!AT11 -> 10.433333 | Y14: =+CARG!AY11 -> 14.563333 | AA14: =+P14/O14-1 -> 0.15131542 | AB14: =+S14/R14-1 -> 0.42330849 | AC14: =+CARG!AK47 -> 257677.73
A15: 13 | B15: CCS | C15: 55.5 | D15: =+SUM(CCS!AH28:AK28)/1000 -> 3282.209 | E15: =+SUM(CCS!AH3:AK3)/1000 -> 135634.06 | F15: =+SUM(CCS!AH31:AK31) -> 3.4535027 | G15: =+CCS!AK49 -> 21.382158 | H15: =+CCS!AM35 -> 0.15354589 | I15: =+CCS!AM37 -> 16.904535 | J15: =+C15/G15 -> 2.595622 | K15: =+Y15/C15 -> 0.04977942 | L15: =+C15/U15 -> 18.512269 | M15: =+C15/V15 -> 11.302513 | O15: =+CCS!AO11 -> 139919.8 | P15: =+CCS!AT11 -> 155475.6 | R15: =+CCS!AQ11 -> 2848.6 | S15: =+CCS!AV11 -> 4669.2 | U15: =+CCS!AR11 -> 2.9980118 | V15: =+CCS!AW11 -> 4.9104125 | X15: =+CCS!AS11 -> 1.6637574 | Y15: =+CCS!AX11 -> 2.7627578 | AA15: =+P15/O15-1 -> 0.11117655 | AB15: =+S15/R15-1 -> 0.63912097 | AC15: =+CCS!AK47 -> 950400
A16: 14 | B16: LMF | C16: 25.7 | D16: =+SUM(LMF!AI28:AL28)/1000 -> 2273.67 | E16: =+SUM(LMF!AI3:AL3)/1000 -> 16763.349 | F16: =+SUM(LMF!AI31:AL31) -> 5.6844592 | G16: =+LMF!AL49 -> 54.661416 | H16: =+LMF!AN35 -> 0.089831254 | I16: =+LMF!AN37 -> 5.2338923 | J16: =+C16/G16 -> 0.47016711 | AC16: =+LMF!AK47 -> 399980
A17: 15 | B17: LLUB | C17: 121.75 | D17: =+SUM(LLUB!AJ28:AM28)/1000 -> 3832.086 | E17: =+SUM(LLUB!AJ3:AM3)/1000 -> 24063.247 | F17: =+SUM(LLUB!AI31:AL31) -> 14.979983 | G17: =+LLUB!AM49 -> 32.584017 | H17: =+LLUB!AO35 -> 0.60032755 | I17: =+LLUB!AO37 -> 6.2240931 | J17: =+C17/G17 -> 3.7364945 | K17: =+Y17/C17 -> 0.11830801 | M17: =+C17/V17 -> 6.8383509 | N17: =+C17/W17 -> 5.9842713 | P17: =+LLUB!AV9 -> 25710.4 | Q17: =+LLUB!BA9 -> 28683.25 | S17: =+LLUB!AX9 -> 4271.2 | T17: =+LLUB!BC9 -> 4882.5 | V17: =+LLUB!AY9 -> 17.804 | W17: =+LLUB!BD9 -> 20.345 | Y17: =+LLUB!AZ9 -> 14.404 | Z17: =+LLUB!BE9 -> 16.6 | AA17: =+Q17/P17-1 -> 0.11562831 | AB17: =+T17/S17-1 -> 0.14312137 | AC17: =+LLUB!AL47 -> 240000
A18: 16 | B18: LIOC | C18: 114.5 | D18: =+SUM(LIOC!AI28:AL28)/1000 -> 13944.994 | E18: =+SUM(LIOC!AI3:AL3)/1000 -> 263568.72 | F18: =+SUM(LIOC!AH31:AK31) -> 33.242321 | G18: =+LIOC!AL49 -> 137.98101 | H18: =+LIOC!AO35 -> 0.34565378 | I18: =+LIOC!AO37 -> 2.1421055 | J18: =+C18/G18 -> 0.82982432 | K18: =+Y18/C18 -> 0.080393013 | L18: =+C18/U18 -> 3.1544872 | M18: =+C18/V18 -> 2.9081212 | O18: =+LIOC!AQ9 -> 265956.75 | P18: =+LIOC!AV9 -> 304364.5 | R18: =+LIOC!AS9 -> 19320 | S18: =+LIOC!AX9 -> 20953.75 | U18: =+LIOC!AT9 -> 36.2975 | V18: =+LIOC!AY9 -> 39.3725 | X18: =+LIOC!AU9 -> 8.785 | Y18: =+LIOC!AZ9 -> 9.205 | AA18: =+P18/O18-1 -> 0.14441352 | AB18: =+S18/R18-1 -> 0.084562629 | AC18: =+LIOC!AK47 -> 532465.7
A19: 17 | B19: CTC | C19: 1226.25 | D19: =+SUM(CTC!AH32:AK32) -> 25477 | E19: =+SUM(CTC!AH7:AK7) -> 52182 | F19: =+SUM(CTC!AH35:AK35) -> 136.00518 | G19: =+CTC!AK51 -> 53.255393 | H19: =+CTC!AM39 -> 2.1295579 | I19: =+CTC!AM41 -> 10.812496 | J19: =+C19/G19 -> 23.025837 | K19: =+Y19/C19 -> 0.1151315 | M19: =+C19/V19 -> 8.6329796 | P19: =+CTC!AT9 -> 56967.5 | S19: =+CTC!AV9 -> 26606.75 | V19: =+CTC!AW9 -> 142.0425 | Y19: =+CTC!AX9 -> 141.18 | AC19: =+CTC!AK49*1000 -> 187323.75
A20: 18 | B20: DIST | C20: 25.5 | D20: =+SUM(DIST!AH32:AK32)/1000 -> 15115.08 | E20: =+SUM(DIST!AH7:AK7)/1000 -> 49388.349 | F20: =+SUM(DIST!AH35:AK35) -> 3.285887 | G20: =+DIST!AK53 -> 1.9186289 | H20: =+DIST!AM39 -> 1.885936 | I20: =+DIST!AM41 -> 7.0472917 | J20: =+C20/G20 -> 13.290741 | K20: =+Y20/C20 -> 0.10196078 | L20: =+C20/U20 -> 7.6119403 | M20: =+C20/V20 -> 5.9942766 | N20: =+C20/W20 -> 5.704698 | O20: =+DIST!AO11 -> 52966 | P20: =+DIST!AT11 -> 65394.667 | Q20: =+DIST!AY11 -> 71380.5 | R20: =+DIST!AQ11 -> 15381.667 | S20: =+DIST!AV11 -> 19525.333 | T20: =+DIST!BA11 -> 20567.5 | U20: =+DIST!AR11 -> 3.35 | V20: =+DIST!AW11 -> 4.254058 | W20: =+DIST!BB11 -> 4.47 | X20: =+DIST!AS11 -> 2.15 | Y20: =+DIST!AX11 -> 2.6 | Z20: =+DIST!BC11 -> 3.1 | AA20: =+P20/O20-1 -> 0.23465368 | AB20: =+S20/R20-1 -> 0.26938997 | AC20: =+DIST!AK51 -> 4600000
A21: 19 | B21: HHL | C21: 77.9 | D21: =+SUM(HHL!AI28:AL28)/1000 -> 6108.52 | E21: =+SUM(HHL!AI3:AL3)/1000 -> 121613.77 | F21: =+SUM(HHL!AI31:AL31) -> 10.239728 | G21: =+HHL!AL49 -> 72.804785 | H21: =+HHL!AN35 -> 0.1312404 | I21: =+HHL!AN37 -> 8.1528601 | J21: =+C21/G21 -> 1.0699846 | K21: =+Y21/C21 -> 0.049743261 | L21: =+C21/U21 -> 7.5338491 | M21: =+C21/V21 -> 5.8553818 | O21: =+HHL!AP11 -> 124057.4 | P21: =+HHL!AU11 -> 140094.4 | R21: =+HHL!AR11 -> 6204.4 | S21: =+HHL!AW11 -> 7975.6 | U21: =+HHL!AS11 -> 10.34 | V21: =+HHL!AX11 -> 13.304 | X21: =+HHL!AT11 -> 2.95 | Y21: =+HHL!AY11 -> 3.875 | AA21: =+P21/O21-1 -> 0.12927081 | AB21: =+S21/R21-1 -> 0.28547482 | AC21: =+HHL!AK47 -> 596551.03
A22: 20 | B22: SUN | C22: 58.1 | D22: =+SUM(SUN!AH28:AK28)/1000 -> 4019.7229 | E22: =+SUM(SUN!AH3:AK3)/1000 -> 55711.077 | F22: =+SUM(SUN!AH31:AK31) -> 8.1706065 | G22: =+SUN!AK49 -> 37.156922 | H22: =+SUN!AM35 -> 0.19809302 | I22: =+SUN!AM37 -> 7.8934565 | J22: =+C22/G22 -> 1.5636386 | K22: =+Y22/C22 -> 0.050344234 | L22: =+C22/U22 -> 5.7906977 | M22: =+C22/V22 -> 5.1129363 | O22: =+SUN!AO11 -> 57142.333 | P22: =+SUN!AT11 -> 65798 | R22: =+SUN!AQ11 -> 4939 | S22: =+SUN!AV11 -> 5595.6667 | U22: =+SUN!AR11 -> 10.033333 | V22: =+SUN!AW11 -> 11.363333 | X22: =+SUN!AS11 -> 2.25 | Y22: =+SUN!AX11 -> 2.925 | AA22: =+P22/O22-1 -> 0.15147556 | AB22: =+S22/R22-1 -> 0.13295539 | AC22: =+SUN!AK47 -> 491973.63
A23: 21 | B23: DIAL | C23: 9.4 | D23: =+SUM(DIAL!AJ28:AM28)/1000 -> 14190.296 | E23: =+SUM(DIAL!AJ3:AM3)/1000 -> 180914.26 | F23: =+SUM(DIAL!AI31:AL31) -> 2.4386197 | G23: =+DIAL!AL49 -> 8.0431202 | H23: =+DIAL!AO35 -> -0.078553248 | J23: =+C23/G23 -> 1.1687007 | K23: =+Y23/C23 -> 0.069680851 | L23: =+C23/U23 -> 4 | M23: =+C23/V23 -> 7.43083 | N23: =+C23/W23 -> 4.4976077 | O23: =+DIAL!AQ11 -> 192901 | P23: =+DIAL!AV11 -> 180360.5 | Q23: =+DIAL!BA11 -> 194372.5 | R23: =+DIAL!AS11 -> 19373 | S23: =+DIAL!AX11 -> 10827 | T23: =+DIAL!BC11 -> 18197.5 | U23: =+DIAL!AT11 -> 2.35 | V23: =+DIAL!AY11 -> 1.265 | W23: =+DIAL!BD11 -> 2.09 | X23: =+DIAL!AU11 -> 0.94 | Y23: =+DIAL!AZ11 -> 0.655 | Z23: =+DIAL!BE11 -> 1.045 | AA23: =+P23/O23-1 -> -0.065010031 | AB23: =+S23/R23-1 -> -0.44112941 | AC23: =+DIAL!AL47 -> 8247640.3
A24: 22 | B24: PLR | C24: 7.6 | D24: =+SUM(PLR!AI29:AL29)/1000 -> 1129.0017 | E24: =+SUM(PLR!AI3:AL3)/1000 -> 8090.3791 | F24: =+SUM(PLR!AI32:AL32) -> 1.2042685 | G24: =+PLR!AL49 -> 10.213058 | H24: =+PLR!AN36 -> 0.27339238 | I24: =+PLR!AN38 -> 2.7218952 | J24: =+C24/G24 -> 0.74414542 | AC24: =+PLR!AK47 -> 937500
A25: 23 | B25: SAMP | C25: 73.8
A26: 24 | B26: NTB | C26: 120
A27: 25 | B27: HNB | C27: 181.5
A28: 26 | B28: COMB | C28: 89
A29: 27 | B29: PABC | C29: 19.8
A30: 28 | B30: SEYB | C30: 43.6
A31: 29 | B31: AAIC | C31: 64.5 | D31: =+SUM(AAIC!AJ48:AM48)/1000 -> 3190.381 | E31: =+SUM(AAIC!AJ16:AM16)/1000 -> 32959.621 | F31: =+SUM(AAIC!AI51:AL51) -> 7.5690773 | G31: =+AAIC!AL83 -> 35.555589 | H31: =+AAIC!AO55 -> 0.2458523 | I31: =+AAIC!AO57 -> 7.7061726 | J31: =+C31/G31 -> 1.8140608 | AC31: =+AAIC!AM81 -> 375000
A32: 30 | B32: KHL | C32: 15.6
A33: 31 | B33: AHUN | C33: 63.6
A34: 32 | B34: WATA | C34: 85.5 | D34: =+SUM(WATA!AI28:AL28)/1000 -> 2358.77 | E34: =+SUM(WATA!AI3:AL3)/1000 -> 8320.903 | F34: =+SUM(WATA!AH31:AK31) -> 9.6700123 | G34: =+WATA!AK49 -> 29.72584 | H34: =+WATA!AN35 -> 0.37047571 | I34: =+WATA!AN37 -> 7.581621 | J34: =+C34/G34 -> 2.8762854 | AC34: =+WATA!AK47 -> 203308.63
A35: 33 | B35: ACL | C35: 82.5
A36: 34 | B36: PACK | C36: 13.2
A37: 35 | B37: ASIR | C37: 23.8
A38: 36 | B38: DIPD | C38: 33.5
A39: 37 | B39: JKH | C39: 177.75
A40: 38 | B40: AEL | C40: 21
A41: 39 | B41: LFIN | C41: 65
A42: 40 | B42: CINS-X | C42: 922
C46: Harmonic Mean | F46: Weight | G46: P/E
C47: Stock A | F47: 0.4 | G47: 50
C48: Stock B | F48: 0.6 | G48: 4
C50: Harmonic Mean | F50: =+(F47+F48)/(F47/G47+F48/G48) -> 6.3291139

Sheet MGT
W1: Stock Price | X1: =+'Valuation Sheet'!C3 -> 46.9
B2: MGT - Rs mn | C2: FY16 | D2: FY17 | E2: FY18 | F2: FY19 | G2: FY20 | H2: FY21 | I2: FY22 | J2: CAGR/AVG | M2: MPS | N2: ='[1]LT Portfolio'!I294 -> SELL | P2: AVG | Q2: =J14*J21 -> 21.034273 | W2: MGT | X2: 2Q21 | Y2: 3Q21 | Z2: 4Q21 | AA2: 1Q22 | AB2: 2Q22 | AC2: 3Q22 | AD2: 4Q22 | AE2: 1Q23 | AF2: 2Q23 | AG2: 3Q23 | AH2: 4Q23 | AI2: 1Q24 | AJ2: 2Q24 | AK2: 3Q24 | AL2: 4Q24 | AM2: 1Q25 | AP2: =+W2 -> MGT | AQ2: FY24E | AV2: FY25E | BA2: FY26E
B3: Net Revenue | C3: 8494.841 | D3: 8332.832 | E3: 8964.529 | F3: 11982.988 | G3: 12225.353 | H3: 14769.114 | I3: 31652.58 | M3: P/E | N3: ='[1]LT Portfolio'!W294 -> 0 | W3: Revenue (LKR 000) | X3: 4205828 | Y3: 3844988 | Z3: 3723204 | AA3: 5813709 | AB3: 8155862 | AC3: 8490686 | AD3: 9200419 | AE3: 15038517 | AF3: 16795679 | AG3: 14956175 | AH3: 14158418 | AI3: 14276671 | AJ3: 15877062 | AK3: 10686568 | AL3: 9412585 | AM3: 12912687 | AQ3: Revenue | AR3: EBIT | AS3: NP | AT3: EPS | AU3: DPS | AV3: Revenue | AW3: EBIT | AX3: NP | AY3: EPS | AZ3: DPS | BA3: Revenue | BB3: EBIT | BC3: NP | BD3: EPS | BE3: DPS
B4: Revenue Growth | D4: =(D3/C3-1)*100 -> -1.9071458 | E4: =(E3/D3-1)*100 -> 7.5808201 | F4: =(F3/E3-1)*100 -> 33.671139 | G4: =(G3/F3-1)*100 -> 2.0225757 | H4: =(H3/G3-1)*100 -> 20.80726 | I4: =(I3/H3-1)*100 -> 114.31604 | J4: =((I3/D3)^(1/5)-1)*100 -> 30.594022 | W4: YoY% | AB4: =+AB3/X3-1 -> 0.93918106 | AC4: =+AC3/Y3-1 -> 1.2082477 | AD4: =+AD3/Z3-1 -> 1.4711026 | AE4: =+AE3/AA3-1 -> 1.5867337 | AF4: =+AF3/AB3-1 -> 1.0593383 | AG4: =+AG3/AC3-1 -> 0.76148017 | AH4: =+AH3/AD3-1 -> 0.53888839 | AI4: =+AI3/AE3-1 -> -0.050659649 | ... AM4: =+AM3/AI3-1 -> -0.095539359 | AP4: CT CLSA
B5: Gross Profit | C5: 1070.806 | D5: 974.244 | E5: 944.457 | F5: 1428.694 | G5: 1584.661 | H5: 2019.458 | I5: 4121.563 | M5: 2Q21 | N5: =202.575/415.481776 -> 0.48756651 | W5: QoQ% | Y5: =+Y3/X3-1 -> -0.085795235 | Z5: =+Z3/Y3-1 -> -0.031673441 | AA5: =+AA3/Z3-1 -> 0.56148011 | AB5: =+AB3/AA3-1 -> 0.40286726 | AC5: =+AC3/AB3-1 -> 0.041053171 | AD5: =+AD3/AC3-1 -> 0.083589595 | AE5: =+AE3/AD3-1 -> 0.63454697 | AF5: =+AF3/AE3-1 -> 0.1168441 | ... AM5: =+AM3/AL3-1 -> 0.37185343 | AP5: Capital Alliance | AY5: 7.64 | AZ5: 3.06 | BD5: 8.41 | BE5: 3.36
B6: GPM | C6: =C5/C$3*100 -> 12.605368 | D6: =D5/D$3*100 -> 11.691631 | E6: =E5/E$3*100 -> 10.535489 | F6: =F5/F$3*100 -> 11.922686 | G6: =G5/G$3*100 -> 12.962088 | H6: =H5/H$3*100 -> 13.673522 | I6: =I5/I$3*100 -> 13.021255 | J6: =AVERAGE(D6:I6) -> 12.301112 | M6: 3Q21 | N6: =261.001/415.481776 -> 0.6281888 | AP6: Asia Securities | AQ6: 66126 | AR6: 6855 | AS6: 3815 | AT6: 9.18 | AU6: 2.75
B7: EBIT | C7: =+C9--118.373 -> 375.379 | D7: =+D9--140.04 -> 202.055 | E7: =+E9--151.365 -> 143.743 | F7: =+F9--152.896 -> 469.664 | G7: =+G9--145.801 -> 449.796 | H7: =+H9--159.323 -> 889.898 | I7: =+I9-1399.847 -> 1755.797 | M7: 4Q21 | N7: ='[1]LT Portfolio'!P294 -> 0 | W7: Revenue (in USD) | X7: 22386114 | Y7: 20462583 | Z7: 18813703 | AA7: 28796894 | AB7: 40189860 | AC7: 41826038 | AD7: 39405896 | AE7: 41283608 | AF7: 45535349 | AG7: 40229056 | AH7: 39583449 | AI7: 45114143 | AJ7: 47978792 | AK7: 31973060 | AL7: 30260825 | AM7: 42207980 | AP7: First Capital | AQ7: 65198 | AR7: 5724 | AS7: 3356 | AT7: 8.1 | AU7: 2.4 | AV7: 57931 | AW7: 6428 | AX7: 4095 | AY7: 9.9 | AZ7: 3 | BA7: 66531 | BB7: 7036 | BC7: 4744 | BD7: 11.4 | BE7: 3.4
B8: EBIT Margin | C8: =C7/C$3*100 -> 4.4189055 | D8: =D7/D$3*100 -> 2.4248059 | E8: =E7/E$3*100 -> 1.6034641 | F8: =F7/F$3*100 -> 3.9194231 | G8: =G7/G$3*100 -> 3.6792066 | H8: =H7/H$3*100 -> 6.0253987 | I8: =I7/I$3*100 -> 5.5470897 | J8: =AVERAGE(D8:I8) -> 3.8665647 | M8: 1Q22 | N8: ='[1]LT Portfolio'!Q294 -> 0 | W8: YoY% | AB8: =+AB7/X7-1 -> 0.79530311 | AC8: =+AC7/Y7-1 -> 1.0440253 | AD8: =+AD7/Z7-1 -> 1.0945316 | AE8: =+AE7/AA7-1 -> 0.43361322 | AF8: =+AF7/AB7-1 -> 0.13300591 | AG8: =+AG7/AC7-1 -> -0.038181527 | AH8: =+AH7/AD7-1 -> 0.0045057471 | AI8: =+AI7/AE7-1 -> 0.092785858 | ... AM8: =+AM7/AI7-1 -> -0.064418003 | AP8: Acuity Research | AY8: 5.56 | AZ8: 2 | BD8: 6.15 | BE8: 2
B9: PBT | C9: 257.006 | D9: 62.015 | E9: -7.622 | F9: 316.768 | G9: 303.995 | H9: 730.575 | I9: 3155.644 | M9: 2Q22 | N9: ='[1]LT Portfolio'!R294 -> 0 | O9: =N9/N5-1 -> -1 | W9: QoQ% | Y9: =+Y7/X7-1 -> -0.085925186 | Z9: =+Z7/Y7-1 -> -0.080580247 | AA9: =+AA7/Z7-1 -> 0.53063403 | AB9: =+AB7/AA7-1 -> 0.39563177 | AC9: =+AC7/AB7-1 -> 0.040711214 | AD9: =+AD7/AC7-1 -> -0.057862091 | AE9: =+AE7/AD7-1 -> 0.047650534 | AF9: =+AF7/AE7-1 -> 0.1029886 | ... AM9: =+AM7/AL7-1 -> 0.39480599 | AP9: Asia Capital | AQ9: 61649 | AR9: 4200 | AS9: 2600 | AT9: 6.3
B10: Net Profit | C10: 261.605 | D10: 73.56 | E10: -105.597 | F10: 181.325 | G10: 231.445 | H10: 736.239 | I10: 2692.346 | J10: =((I10/D10)^(1/5)-1)*100 -> 105.44607 | M10: 3Q22 | N10: ='[1]LT Portfolio'!S294 -> 0 | O10: =N10/N6-1 -> -1 | AP10: JKSB | AQ10: 57649 | AR10: 4507 | AS10: 2529 | AT10: 6.09 | AV10: 53877 | AW10: 5164 | AX10: 3005 | AY10: 7.23 | AZ10: 2.5 | BA10: 58741 | BB10: 5618 | BC10: 3061 | BD10: 7.37 | BE10: 2.6
B11: NP Margin | C11: =C10/C$3*100 -> 3.079575 | D11: =D10/D$3*100 -> 0.88277311 | E11: =E10/E$3*100 -> -1.1779425 | F11: =F10/F$3*100 -> 1.5131869 | G11: =G10/G$3*100 -> 1.893156 | H11: =H10/H$3*100 -> 4.984991 | I11: =I10/I$3*100 -> 8.5059291 | J11: =AVERAGE(D11:I11) -> 2.7670156 | M11: 4Q22 | N11: ='[1]LT Portfolio'!T294 -> 0 | O11: =N11/N7-1 -> #DIV/0! | W11: Gross Profit | X11: 536176 | Y11: 543061 | Z11: 494974 | AA11: 830348 | AB11: 990442 | AC11: 1131305 | AD11: 1170194 | AE11: 1947604 | AF11: 1795972 | AG11: 2012466 | AH11: 2069956 | AI11: 2759012 | AJ11: 2792611 | AK11: 1967739 | AL11: 1920313 | AM11: 2536969 | AP11: Consensus | AQ11: =+AVERAGE(AQ4:AQ10) -> 62655.5 | AR11: =+AVERAGE(AR4:AR10) -> 5321.5 | AS11: =+AVERAGE(AS4:AS10) -> 3075 | AT11: =+AVERAGE(AT4:AT10) -> 7.4175 | AU11: =+AVERAGE(AU4:AU10) -> 2.575 | AV11: =+AVERAGE(AV4:AV10) -> 55904 | AW11: =+AVERAGE(AW4:AW10) -> 5796 | AX11: =+AVERAGE(AX4:AX10) -> 3550 | ... BE11: =+AVERAGE(BE4:BE10) -> 2.84
B12: NP Growth | D12: =(D10/C10-1)*100 -> -71.881271 | E12: =(E10/D10-1)*100 -> -243.5522 | F12: =-(F10/E10-1)*100 -> 271.71416 | G12: =(G10/F10-1)*100 -> 27.640976 | H12: =(H10/G10-1)*100 -> 218.10538 | I12: =(I10/H10-1)*100 -> 265.68913 | J12: =AVERAGE(D12:I12) -> 77.952696 | S12: 1Q22 | T12: 2Q22 | W12: GPM% | X12: =+X11/X3 -> 0.12748405 | Y12: =+Y11/Y3 -> 0.14123867 | Z12: =+Z11/Z3 -> 0.13294302 | AA12: =+AA11/AA3 -> 0.14282586 | AB12: =+AB11/AB3 -> 0.12143928 | AC12: =+AC11/AC3 -> 0.13324071 | AD12: =+AD11/AD3 -> 0.12718921 | AE12: =+AE11/AE3 -> 0.12950772 | ... AM12: =+AM11/AM3 -> 0.19647104 | AU12: DY | AZ12: DY | BE12: DY
M13: TTM | N13: =SUM(N8:N11) -> 0 | Q13: =N13*J21 -> 0 | S13: 19.109574 | T13: 18.873653 | AP13: Leading P/E | AT13: =+$X$1/AT11 -> 6.3228851 | AU13: =+AU11/$X$1 -> 0.054904051 | AY13: =+$X$1/AY11 -> 6.1852951 | AZ13: =+AZ11/$X$1 -> 0.056289979 | BD13: =+$X$1/BD11 -> 5.6285629 | BE13: =+BE11/$X$1 -> 0.060554371
B14: EPS | C14: =1.26/2 -> 0.63 | D14: =0.35/2 -> 0.175 | E14: =-0.51/2 -> -0.255 | F14: =0.87/2 -> 0.435 | G14: 0.56 | H14: 1.77 | I14: 6.48 | J14: =AVERAGE(D14:I14) -> 1.5275 | M14: P/E | N14: =N2/N13 -> #VALUE! | Q14: =Q13/N2-1 -> #VALUE! | S14: =S13/N2-1 -> #VALUE! | T14: =T13/N2-1 -> #VALUE! | W14: EBIT | X14: =+X20-X17 -> 288324 | Y14: =+Y20-Y17 -> 273890 | Z14: =+Z20-Z17 -> 144579 | AA14: =+AA20-AA17 -> 339439 | AB14: =+AB20-AB17 -> 536419 | AC14: =+AC20-AC17 -> 576435 | AD14: =+AD20-AD17 -> 304232 | AE14: =+AE20-AE17 -> 1018801 | ... AM14: =+AM20-AM17 -> 1355526
B15: DPS | C15: 0 | D15: 0 | E15: 0 | F15: 0 | G15: 0.3 | H15: 0.7 | I15: 2.1 | W15: EBIT margin % | X15: =+X14/X3 -> 0.068553445 | Y15: =+Y14/Y3 -> 0.071232992 | Z15: =+Z14/Z3 -> 0.038831877 | AA15: =+AA14/AA3 -> 0.058385963 | AB15: =+AB14/AB3 -> 0.065770976 | AC15: =+AC14/AC3 -> 0.067890274 | AD15: =+AD14/AD3 -> 0.03306719 | AE15: =+AE14/AE3 -> 0.067746108 | ... AM15: =+AM14/AM3 -> 0.10497629
B16: MPS | C16: 9 | D16: =13.6/2 -> 6.8 | E16: =12.5/2 -> 6.25 | F16: =8.5/2 -> 4.25 | G16: =8.7/2 -> 4.35 | H16: 14.1 | I16: 29.1 | J16: =((I16/D16)^(1/5)-1)*100 -> 33.744772
B17: BVPS | C17: =2578.373/415.481776 -> 6.2057427 | D17: =2707.107/415.481776 -> 6.5155854 | E17: =2683.152/415.481776 -> 6.4579295 | F17: =3179.299/415.481776 -> 7.6520781 | G17: =3543.165/415.481776 -> 8.527847 | H17: =4225.563/415.481776 -> 10.170273 | I17: =9106.62/415.481776 -> 21.918218 | J17: =((I17/D17)^(1/6)-1)*100 -> 22.40767 | W17: Net Finance Income/Cost | X17: -54287 | Y17: -38665 | Z17: 2948 | AA17: -36232 | AB17: -90483 | AC17: -148715 | AD17: 1674940 | AE17: 986461 | AF17: -412419 | AG17: -536441 | AH17: -1170365 | AI17: -828137 | AJ17: -203592 | AK17: -271856 | AL17: -675330 | AM17: -192506
B18: ROE | C18: =C14/AVERAGE(B17:C17)*100 -> 10.151887 | D18: =D14/AVERAGE(C17:D17)*100 -> 2.7512851 | E18: =E14/AVERAGE(D17:E17)*100 -> -3.9310858 | F18: =F14/AVERAGE(E17:F17)*100 -> 6.1658365 | G18: =G14/AVERAGE(F17:G17)*100 -> 6.9221581 | H18: =H14/AVERAGE(G17:H17)*100 -> 18.932385 | I18: =I14/AVERAGE(H17:I17)*100 -> 40.388313 | J18: =AVERAGE(D18:I18) -> 11.871482 | M18: MGT | W18: As a % of EBIT | X18: =+X17/X14 -> -0.18828471 | Y18: =+Y17/Y14 -> -0.14116981 | Z18: =+Z17/Z14 -> 0.020390236 | AA18: =+AA17/AA14 -> -0.10674083 | AB18: =+AB17/AB14 -> -0.16867971 | AC18: =+AC17/AC14 -> -0.25799093 | AD18: =+AD17/AD14 -> 5.5054695 | AE18: =+AE17/AE14 -> 0.9682568 | ... AM18: =+AM17/AM14 -> -0.14201572
B19: DY | C19: =C15/C16*100 -> 0 | D19: =D15/D16*100 -> 0 | E19: =E15/E16*100 -> 0 | F19: =F15/F16*100 -> 0 | G19: =G15/G16*100 -> 6.8965517 | H19: =H15/H16*100 -> 4.964539 | I19: =I15/I16*100 -> 7.2164948 | J19: =AVERAGE(G19:I19) -> 6.3591952
B20: Dividend Payout | C20: =C15/C14*100 -> 0 | D20: =D15/D14*100 -> 0 | E20: =E15/E14*100 -> 0 | F20: =F15/F14*100 -> 0 | G20: =G15/G14*100 -> 53.571429 | H20: =H15/H14*100 -> 39.548023 | I20: =I15/I14*100 -> 32.407407 | J20: =AVERAGE(G20:I20) -> 41.842286 | M20: YoY Growth | N20: =N13/H14-1 -> -1 | W20: PBT | X20: 234037 | Y20: 235225 | Z20: 147527 | AA20: 303207 | AB20: 445936 | AC20: 427720 | AD20: 1979172 | AE20: 2005262 | AF20: 535611 | AG20: 505819 | AH20: 19443 | AI20: 1062325 | AJ20: 1464266 | AK20: 826887 | AL20: 447230 | AM20: 1163020
B21: P/E | C21: =C16/C14 -> 14.285714 | D21: =D16/D14 -> 38.857143 | E21: N/A | F21: =F16/F14 -> 9.7701149 | G21: =G16/G14 -> 7.7678571 | H21: =H16/H14 -> 7.9661017 | I21: =I16/I14 -> 4.4907407 | J21: =AVERAGE(D21:I21) -> 13.770391 | W21: PBT Margin% | X21: =+X20/X3 -> 0.05564588 | Y21: =+Y20/Y3 -> 0.061177044 | Z21: =+Z20/Z3 -> 0.039623668 | AA21: =+AA20/AA3 -> 0.052153797 | AB21: =+AB20/AB3 -> 0.054676747 | AC21: =+AC20/AC3 -> 0.050375199 | AD21: =+AD20/AD3 -> 0.21511759 | AE21: =+AE20/AE3 -> 0.13334174 | ... AM21: =+AM20/AM3 -> 0.090068008
B22: P/B | C22: =C16/C17 -> 1.4502696 | D22: =D16/D17 -> 1.0436514 | E22: =E16/E17 -> 0.96780246 | F22: =F16/F17 -> 0.55540468 | G22: =G16/G17 -> 0.51009358 | H22: =H16/H17 -> 1.3863935 | I22: =I16/I17 -> 1.3276627 | J22: =AVERAGE(D22:I22) -> 0.96516806
W23: Taxes | X23: -31462 | Y23: 25776 | Z23: 19850 | AA23: -3025 | AB23: -52092 | AC23: -30616 | AD23: -377685 | AE23: -394976 | AF23: -34224 | AG23: -2257323 | AH23: 34825 | AI23: -160723 | AJ23: -533986 | AK23: -275218 | AL23: -286369 | AM23: -374214
W24: ETR% | X24: =+X23/X20 -> -0.13443174 | Y24: =+Y23/Y20 -> 0.10958019 | Z24: =+Z23/Z20 -> 0.13455164 | AA24: =+AA23/AA20 -> -0.0099766826 | AB24: =+AB23/AB20 -> -0.11681497 | AC24: =+AC23/AC20 -> -0.071579538 | AD24: =+AD23/AD20 -> -0.1908298 | AE24: =+AE23/AE20 -> -0.19696977 | ... AM24: =+AM23/AM20 -> -0.32176059
W26: Net Profit Attributable to Equity Holders | X26: =+X20+X23 -> 202575 | Y26: =+Y20+Y23 -> 261001 | Z26: =+Z20+Z23 -> 167377 | AA26: 298809 | AB26: =+AB20+AB23 -> 393844 | AC26: =+AC20+AC23 -> 397104 | AD26: =+AD20+AD23 -> 1601487 | AE26: =+AE20+AE23 -> 1610286 | AF26: =+AF20+AF23 -> 501387 | AG26: =+AG20+AG23 -> -1751504 | AH26: =+AH20+AH23 -> 54268 | AI26: =+AI20+AI23 -> 901602 | ... AM26: =+AM20+AM23 -> 788806
W27: NP Margin | X27: =+X26/X3 -> 0.048165308 | Y27: =+Y26/Y3 -> 0.067880836 | Z27: =+Z26/Z3 -> 0.044955098 | AA27: =+AA26/AA3 -> 0.051397309 | AB27: =+AB26/AB3 -> 0.048289684 | AC27: =+AC26/AC3 -> 0.046769366 | AD27: =+AD26/AD3 -> 0.17406675 | AE27: =+AE26/AE3 -> 0.10707745 | ... AM27: =+AM26/AM3 -> 0.061087673
W29: EPS | X29: =+X26/X44 -> 0.48756651 | Y29: =+Y26/Y44 -> 0.6281888 | Z29: =+Z26/Z44 -> 0.4028504 | AA29: =+AA26/AA44 -> 0.71918678 | AB29: =+AB26/AB44 -> 0.94792124 | AC29: =+AC26/AC44 -> 0.95576755 | AD29: =+AD26/AD44 -> 3.8545301 | AE29: =+AE26/AE44 -> 3.8757079 | ... AM29: =+AM26/AM44 -> 1.8985333
W30: YoY% | AB30: =+AB29/X29-1 -> 0.94418857 | AC30: =+AC29/Y29-1 -> 0.52146543 | AD30: =+AD29/Z29-1 -> 8.5681426 | AE30: =+AE29/AA29-1 -> 4.3890144 | AF30: =+AF29/AB29-1 -> 0.27305989 | AG30: =+AG29/AC29-1 -> -5.4106934 | AH30: =+AH29/AD29-1 -> -0.96611399 | AI30: =+AI29/AE29-1 -> -0.44009822 | ... AM30: =+AM29/AI29-1 -> -0.1251062
W31: QoQ% | Y31: =+Y29/X29-1 -> 0.28841664 | Z31: =+Z29/Y29-1 -> -0.35871127 | AA31: =+AA29/Z29-1 -> 0.78524528 | AB31: =+AB29/AA29-1 -> 0.31804598 | AC31: =+AC29/AB29-1 -> 0.008277389 | AD31: =+AD29/AC29-1 -> 3.0329158 | AE31: =+AE29/AD29-1 -> 0.0054942688 | AF31: =+AF29/AE29-1 -> -0.68863481 | ... AM31: =+AM29/AL29-1 -> 3.9036497
W33: RoE | X33: =+X26*4/X38 -> 0.21880325 | Y33: =+Y26*4/Y38 -> 0.26608611 | Z33: =+Z26*4/Z38 -> 0.15844232 | AA33: =+AA26*4/AA38 -> 0.26417908 | AB33: =+AB26*4/AB38 -> 0.33463886 | AC33: =+AC26*4/AC38 -> 0.32163279 | AD33: =+AD26*4/AD38 -> 0.70343852 | AE33: =+AE26*4/AE38 -> 0.52541963 | ... AM33: =+AM26*4/AM38 -> 0.29170884 | AO33: =+AVERAGE(X33:AM33) -> 0.22511269 | AP33: RoE
AO34: =AVERAGE(X33:AM33)*AM46 -> 5.8604182 | AP34: Normalized EPS
W35: Debt | X35: =458156+20243+117220+2518992+120544+73430 -> 3308585 | Y35: =427579+20515+37702+2071957+130492+259+14173 -> 2702677 | Z35: =665230+21442+2450325+206964+1710+14513 -> 3360184 | AA35: =2475789+50187+410550+5199370+645148+5694+16681 -> 8803419 | AB35: =3184597+52828+347748+6048749+838725+5749+109192 -> 10587588 | AC35: =3263109+50583+228179+5751721+980500+6110+112463 -> 10392665 | AD35: =5159752+56481+451023+5743337+1483655+6307+101485 -> 13002040 | AE35: =5547633+65114+838008+7402911+1636129+7291+270345 -> 15767431 | AF35: =6224823+778972+5252626+1764488+8021+35415+66326 -> 14130671 | AG35: =5846288+63700+698790+7061420+1778365+8575+78300 -> 15535438 | AH35: =5268880+54205+1115814+6252914+1709815+7132+24957 -> 14433717 | AI35: =5350879+52804+564162+4618204+1979211+7691+45958 -> 12618909 | AJ35: =4984053+54870+77686+4156073+2308739+8421+400393 -> 11990235 | AK35: =5737074+51732+174112+2783377+2848164+9081+142756 -> 11746296 | AL35: =5172466+43558+616901+3103581+2775437+7899+81127 -> 11800969 | AM35: =4692694+45982+728005+3988047+2860326+7168+173065 -> 12495287 | AO35: =X1/AO34 -> 8.0028419 | AP35: P/E
W36: Cash | X36: 291769 | Y36: 645466 | Z36: 646002 | AA36: 1002776 | AB36: 1909683 | AC36: 1877694 | AD36: 2952809 | AE36: 2662859 | AF36: 2098362 | AG36: 1776260 | AH36: 1529726 | AI36: 2811177 | AJ36: 4040619 | AK36: 3756291 | AL36: 3371785 | AM36: 3971423
W37: Net Debt | X37: =+X35-X36 -> 3016816 | Y37: =+Y35-Y36 -> 2057211 | Z37: =+Z35-Z36 -> 2714182 | AA37: =+AA35-AA36 -> 7800643 | AB37: =+AB35-AB36 -> 8677905 | AC37: =+AC35-AC36 -> 8514971 | AD37: =+AD35-AD36 -> 10049231 | AE37: =+AE35-AE36 -> 13104572 | ... AM37: =+AM35-AM36 -> 8523864
W38: Equity | X38: 3703327 | Y38: 3923557 | Z38: 4225563 | AA38: 4524340 | AB38: 4707690 | AC38: 4938601 | AD38: 9106621 | AE38: 12259047 | AF38: 12433522 | AG38: 10587154 | AH38: 9491660 | AI38: 9822005 | AJ38: 10397293 | AK38: 10726162 | AL38: 10017634 | AM38: 10816347
W40: Debt/Equity | X40: =+X35/X38 -> 0.89340882 | Y40: =+Y35/Y38 -> 0.68883337 | Z40: =+Z35/Z38 -> 0.79520386 | AA40: =+AA35/AA38 -> 1.9457908 | AB40: =+AB35/AB38 -> 2.2489986 | AC40: =+AC35/AC38 -> 2.1043743 | AD40: =+AD35/AD38 -> 1.4277568 | AE40: =+AE35/AE38 -> 1.2861873 | ... AM40: =+AM35/AM38 -> 1.1552225
W42: Average Exchange rate (income Statement) | X42: =+(X3*1000)/X7 -> 187.87665 | Y42: =+(Y3*1000)/Y7 -> 187.90336 | Z42: =+(Z3*1000)/Z7 -> 197.89852 | AA42: =+(AA3*1000)/AA7 -> 201.88667 | AB42: =+(AB3*1000)/AB7 -> 202.93333 | AC42: =+(AC3*1000)/AC7 -> 203.00001 | AD42: =+(AD3*1000)/AD7 -> 233.47823 | AE42: =+(AE3*1000)/AE7 -> 364.27332 | ... AM42: =+(AM3*1000)/AM7 -> 305.92999
W44: Number of shares | X44: 415481.78 | Y44: 415481.78 | Z44: 415481.78 | AA44: 415481.78 | AB44: 415481.78 | AC44: 415481.78 | AD44: 415481.78 | AE44: 415481.78 | AF44: 415481.78 | AG44: 415481.78 | AH44: 415481.78 | AI44: 415481.78 | AJ44: 415481.78 | AK44: 415481.78 | AL44: 415481.78 | AM44: 415481.78
W46: Net Asset Value per share | X46: =+X38/X44 -> 8.913332 | Y46: =+Y38/Y44 -> 9.4433913 | Z46: =+Z38/Z44 -> 10.170273 | AA46: =+AA38/AA44 -> 10.889383 | AB46: =+AB38/AB44 -> 11.330677 | AC46: =+AC38/AC44 -> 11.886444 | AD46: =+AD38/AD44 -> 21.91822 | AE46: =+AE38/AE44 -> 29.505619 | ... AM46: =+AM38/AM44 -> 26.033265
W48: Cashflow from operations (in USD) | Y48: =+Y52-X52 -> 8266883 | Z48: =+Z52-Y52 -> -599282 | AA48: =+AA52 -> -2082902 | AB48: =+AB52-AA52 -> -639658 | AC48: =+AC52-AB52 -> 2935745 | AD48: =+AD52-AC52 -> 6978985 | AE48: =+AE52 -> -1748438 | AF48: =+AF52-AE52 -> 5876196 | AG48: =+AG52-AF52 -> -4033069 | AH48: =+AH52-AG52 -> 1241217 | AI48: =+AI52 -> 9026075 | AJ48: =+AJ52-AI52 -> 8257139 | AK48: =+AK52-AJ52 -> 2183018 | AL48: =+AL52-AK52 -> -475189 | AM48: =+AM52 -> 2025071
W49: Capex | Y49: =+Y53-X53 -> -2560827 | Z49: =+Z53-Y53 -> -1531468 | AA49: =+AA53 -> -1857616 | AB49: =+AB53-AA53 -> -813693 | AC49: =+AC53-AB53 -> -1413703 | AD49: =+AD53-AC53 -> -4460304 | AE49: =+AE53 -> -2672343 | AF49: =+AF53-AE53 -> -1197691 | AG49: =+AG53-AF53 -> -35019 | AH49: =+AH53-AG53 -> -789080 | AI49: =+AI53 -> -634019 | AJ49: =+AJ53-AI53 -> -975801 | AK49: =+AK53-AJ53 -> -1106004 | AL49: =+AL53-AK53 -> -1109299 | AM49: =+AM53 -> -1694448
W50: FCF (in USD) | Y50: =+Y48+Y49 -> 5706056 | Z50: =+Z48+Z49 -> -2130750 | AA50: =+AA48+AA49 -> -3940518 | AB50: =+AB48+AB49 -> -1453351 | AC50: =+AC48+AC49 -> 1522042 | AD50: =+AD48+AD49 -> 2518681 | AE50: =+AE48+AE49 -> -4420781 | AF50: =+AF48+AF49 -> 4678505 | ... AM50: =+AM48+AM49 -> 330623
W52: Cashflow from operations (in USD) | X52: 1498416 | Y52: 9765299 | Z52: 9166017 | AA52: -2082902 | AB52: -2722560 | AC52: 213185 | AD52: 7192170 | AE52: -1748438 | AF52: 4127758 | AG52: 94689 | AH52: 1335906 | AI52: 9026075 | AJ52: 17283214 | AK52: 19466232 | AL52: 18991043 | AM52: 2025071
W53: Capex | X53: -830578 | Y53: -3391405 | Z53: -4922873 | AA53: -1857616 | AB53: -2671309 | AC53: -4085012 | AD53: -8545316 | AE53: -2672343 | AF53: -3870034 | AG53: -3905053 | AH53: -4694133 | AI53: -634019 | AJ53: -1609820 | AK53: -2715824 | AL53: -3825123 | AM53: -1694448
W54: FCF (in USD) | X54: =+X52+X53 -> 667838 | Y54: =+Y52+Y53 -> 6373894 | Z54: =+Z52+Z53 -> 4243144 | AA54: =+AA52+AA53 -> -3940518 | AB54: =+AB52+AB53 -> -5393869 | AC54: =+AC52+AC53 -> -3871827 | AD54: =+AD52+AD53 -> -1353146 | AE54: =+AE52+AE53 -> -4420781 | ... AM54: =+AM52+AM53 -> 330623

Sheet TJL
A1: TJL | B1: 4Q23 | C1: 1Q24 | D1: 2Q24 | E1: 3Q24 | F1: 4Q24 | G1: 1Q25 | H1: 2Q25
A2: Revenue (LKR 000) | B2: 17301185 | C2: 13997150 | D2: 15549880 | E2: 15897519 | F2: 15254331 | G2: 15392521 | H2: 17280011
A3: YoY% | F3: =(F2-B2)/B2 -> -0.11830716 | G3: =(G2-C2)/C2 -> 0.099689651 | H3: =(H2-D2)/D2 -> 0.1112633
A4: QoQ% | C4: =+C2/B2-1 -> -0.1909716 | D4: =+D2/C2-1 -> 0.11093187 | E4: =+E2/D2-1 -> 0.022356378 | F4: =+F2/E2-1 -> -0.040458389 | G4: =+G2/F2-1 -> 0.0090590666 | H4: =+H2/G2-1 -> 0.12262384
A6: COGS | C6: =C2-C9 -> 13714016 | D6: =D2-D9 -> 13658699 | E6: =E2-E9 -> 14615257 | F6: =F2-F9 -> 13752961 | G6: =G2-G9 -> 14098757 | H6: =H2-H9 -> 15371064
A7: COGS % | C7: =C6/C$2 -> 0.97977203 | D7: =D6/D$2 -> 0.8783797 | E7: =E6/E$2 -> 0.91934201 | F7: =F6/F$2 -> 0.90157746 | G7: =G6/G$2 -> 0.91594853 | H7: =H6/H$2 -> 0.8895286
A9: Gross Profit | B9: 1185626 | C9: 283134 | D9: 1891181 | E9: 1282262 | F9: 1501370 | G9: 1293764 | H9: 1908947
A10: GPM% | B10: =+B9/B2 -> 0.068528601 | C10: =C9/C$2 -> 0.020227975 | D10: =D9/D$2 -> 0.1216203 | E10: =E9/E$2 -> 0.080657994 | F10: =F9/F$2 -> 0.09842254 | G10: =G9/G$2 -> 0.084051469 | H10: =H9/H$2 -> 0.1104714
A12: EBIT | B12: 772864 | C12: -582128 | D12: =+D18-D15 -> 1217053 | E12: 859610 | F12: 647884 | G12: =+G18-G15 -> 381975 | H12: 1908947
A13: EBIT margin % | B13: =+B12/B2 -> 0.04467116 | C13: =C12/C$2 -> -0.041589038 | D13: =D12/D$2 -> 0.078267678 | E13: =E12/E$2 -> 0.054071959 | F13: =F12/F$2 -> 0.042472135 | G13: =G12/G$2 -> 0.024815623 | H13: =H12/H$2 -> 0.1104714
A15: Net Finance Income/Cost | B15: -363780 | C15: -118995 | D15: 6968 | E15: -181936 | F15: -260940 | G15: -108269 | H15: -180545
A16: As a % of EBIT | B16: =+B15/B12 -> -0.47069083 | C16: =+C15/C12 -> 0.20441381 | D16: =+D15/D12 -> 0.0057253053 | E16: =+E15/E12 -> -0.21164947 | F16: =+F15/F12 -> -0.40275728 | G16: =+G15/G12 -> -0.28344525 | H16: =+H15/H12 -> -0.09457832
A18: PBT | B18: 409084 | C18: -701123 | D18: 1224021 | E18: 677674 | F18: 386944 | G18: 273706 | H18: 1004447
A19: PBT Margin% | B19: =+B18/B2 -> 0.023644854 | C19: =+C18/C2 -> -0.050090411 | D19: =+D18/D2 -> 0.078715784 | E19: =+E18/E2 -> 0.042627658 | F19: =+F18/F2 -> 0.025366173 | G19: =+G18/G2 -> 0.017781753 | H19: =+H18/H2 -> 0.058127683
A21: Taxes | B21: -256694 | C21: -151893 | D21: -281019 | E21: -200314 | F21: 162189 | G21: -115405 | H21: -248365
A22: ETR% | B22: =+B21/B18 -> -0.62748482 | C22: =+C21/C18 -> 0.21664244 | D22: =+D21/D18 -> -0.22958675 | E22: =+E21/E18 -> -0.29559051 | F22: =+F21/F18 -> 0.41915368 | G22: =+G21/G18 -> -0.42163855 | H22: =+H21/H18 -> -0.24726541
A24: Net Profit Attributable to Equity Holders | B24: =+B18+B21 -> 152390 | C24: =+C18+C21 -> -853016 | D24: =+D18+D21 -> 943002 | E24: =+E18+E21 -> 477360 | F24: =+F18+F21 -> 549133 | G24: =+G18+G21 -> 158301 | H24: 756082
A25: NP Margin | B25: =+B24/B2 -> 0.0088080672 | C25: =+C24/C2 -> -0.06094212 | D25: =+D24/D2 -> 0.060643683 | E25: =+E24/E2 -> 0.030027327 | F25: =+F24/F2 -> 0.035998498 | G25: =+G24/G2 -> 0.01028428 | H25: =+H24/H2 -> 0.043754718
A27: EPS | B27: =+B24/B43 -> 0.21261546 | C27: =+C24/C43 -> -1.1901331 | D27: =+D24/D43 -> 1.3156822 | E27: =+E24/E43 -> 0.66601559 | F27: =+F24/F43 -> 0.76615372 | G27: =+G24/G43 -> 0.22086252 | H27: 1.05
A28: YoY% | B28: =+B27/#REF!-1 -> #REF! | G28: =+G27/C27-1 -> -1.185578 | H28: =+H27/D27-1 -> -0.20193491
A29: QoQ% | B29: =+B27/#REF!-1 -> #REF! | C29: =+C27/B27-1 -> -6.5975851 | D29: =+D27/C27-1 -> -2.1054916 | E29: =+E27/D27-1 -> -0.49378686 | F29: =+F27/E27-1 -> 0.15035403 | G29: =+G27/F27-1 -> -0.71172557 | H29: =+H27/G27-1 -> 3.7540886
A31: RoE | B31: =+B24*4/B36 -> 0.019022974 | C31: =+C24*4/C37 -> -0.11573328 | D31: =+D24*4/D37 -> 0.11934432 | E31: =+E24*4/E37 -> 0.059332498 | F31: =+F24*4/F37 -> 0.072946743 | G31: =+G24*4/G37 -> 0.020795666
A33: Total asset | B33: =6238676+1329873+125243+6347896 -> 14041688
A34: Total Liability | B34: =3281426+7907029 -> 11188455
A35: Current asset | B35: =+B33-B34 -> 2853233
A36: Current Liability | B36: 32043359
A37: Equity | C37: 29482133 | D37: 31606096 | E37: 32182026 | F37: 30111447 | G37: 30448844
H38: =+C41/#REF!-1 -> #REF!
A39: Debt/Equity | B39: =+B33/B36 -> 0.43820899 | C39: =+C33/C37 -> 0 | D39: =+D33/D37 -> 0 | E39: =+E33/E37 -> 0 | F39: =+F33/F37 -> 0 | G39: =+G33/G37 -> 0
A41: Average Exchange rate (income Statement) | B41: =+(B2*1000)/#REF! -> #REF! | C41: =+(C2*1000)/#REF! -> #REF! | D41: =+(D2*1000)/#REF! -> #REF! | E41: =+(E2*1000)/#REF! -> #REF! | F41: =+(F2*1000)/#REF! -> #REF! | G41: =+(G2*1000)/#REF! -> #REF!
A43: Number of shares | B43: 716739.97 | C43: 716739.97 | D43: 716739.97 | E43: 716739.97 | F43: 716739.97 | G43: 716739.97
A45: Net Asset Value per share | B45: =+B36/B43 -> 44.707091 | C45: =+C37/C43 -> 41.133652 | D45: =+D37/D43 -> 44.097019 | E45: =+E37/E43 -> 44.90056 | F45: =+F37/F43 -> 42.011675 | G45: =+G37/G43 -> 42.482414
A47: Cashflow from operations (in LKR 000') | B47: =+B51-#REF! -> #REF! | C47: =+C51 -> 708033 | D47: =+D51-C51 -> 3097710 | E47: =+E51-D51 -> 1005237 | F47: =+F51-E51 -> -1400791 | G47: =+G51-F51 -> -2449397
A48: Capex | B48: =+B52-#REF! -> #REF! | C48: =+C52 -> -305304 | D48: =+D52-C52 -> -504882 | E48: =+E52-D52 -> -719042 | F48: =+F52-E52 -> -410914 | G48: =+G52 -> -173765
A49: FCF (in LKR 000') | B49: =+B47+B48 -> #REF! | C49: =+C47+C48 -> 402729 | D49: =+D47+D48 -> 2592828 | E49: =+E47+E48 -> 286195 | F49: =+F47+F48 -> -1811705 | G49: =+G47+G48 -> -2623162
A51: Cashflow from operations (in LKR 000') | B51: 7904112 | C51: 708033 | D51: 3805743 | E51: 4810980 | F51: 3410189 | G51: 960792
A52: Capex | B52: -3634954 | C52: -305304 | D52: -810186 | E52: -1529228 | F52: -1940142 | G52: -173765
A53: FCF (in LKR 000') | B53: =+B51+B52 -> 4269158 | C53: =+C51+C52 -> 402729 | D53: =+D51+D52 -> 2995557 | E53: =+E51+E52 -> 3281752 | F53: =+F51+F52 -> 1470047 | G53: =+G51+G52 -> 787027

Sheet BPPL
W1: Stock Price | X1: =+'Valuation Sheet'!C5 -> 18.4
B2: TJL - Rs mn | C2: FY16 | D2: FY17 | E2: FY18 | F2: FY19 | G2: FY20 | H2: FY21 | I2: FY22 | J2: CAGR/AVG | M2: MPS | N2: ='[1]LT Portfolio'!I294 -> SELL | P2: AVG | Q2: =J14*J21 -> #DIV/0! | W2: BPPL | X2: 2Q21 | Y2: 3Q21 | Z2: 4Q21 | AA2: 1Q22 | AB2: 2Q22 | AC2: 3Q22 | AD2: 4Q22 | AE2: 1Q23 | AF2: 2Q23 | AG2: 3Q23 | AH2: 4Q23 | AI2: 1Q24 | AJ2: 2Q24 | AK2: 3Q24 | AL2: 4Q24 | AM2: 1Q25 | AP2: =+W2 -> BPPL | AQ2: FY24E | AV2: FY25E | BE2: 1Q | BF2: 2Q | BG2: 3Q | BH2: 4Q
B3: Net Revenue | C3: 17820.179 | M3: P/E | N3: ='[1]LT Portfolio'!W294 -> 0 | W3: Revenue (LKR 000) | X3: 892337.88 | Y3: 896770.81 | Z3: 1055051.6 | AA3: 1005142.4 | AB3: 1152804.1 | AC3: 1253127 | AD3: 1397553.2 | AE3: 1585565.2 | AF3: 1713112.1 | AG3: 1445926 | AH3: 1506287 | AI3: 1158914 | AJ3: 1531197 | AK3: 1520706 | AL3: 1488408 | AM3: 1393105 | AQ3: Revenue | AR3: EBIT | AS3: NP | AT3: EPS | AU3: DPS | AV3: Revenue | AW3: EBIT | AX3: NP | AY3: EPS | AZ3: DPS | BD3: Revenue | BE3: =+AI3 -> 1158914 | BF3: =+AJ3 -> 1531197 | BG3: =+AK3 -> 1520706 | BH3: =+AL3 -> 1488408
B4: Revenue Growth | D4: =(D3/C3-1)*100 -> -100 | E4: =(E3/D3-1)*100 -> #DIV/0! | F4: =(F3/E3-1)*100 -> #DIV/0! | G4: =(G3/F3-1)*100 -> #DIV/0! | H4: =(H3/G3-1)*100 -> #DIV/0! | I4: =(I3/H3-1)*100 -> #DIV/0! | J4: =((I3/D3)^(1/5)-1)*100 -> #DIV/0! | W4: YoY% | AB4: =+AB3/X3-1 -> 0.29189194 | AC4: =+AC3/Y3-1 -> 0.39737711 | AD4: =+AD3/Z3-1 -> 0.32463018 | AE4: =+AE3/AA3-1 -> 0.57745319 | AF4: =+AF3/AB3-1 -> 0.48603921 | AG4: =+AG3/AC3-1 -> 0.15385432 | AH4: =+AH3/AD3-1 -> 0.077802978 | AI4: =+AI3/AE3-1 -> -0.26908459 | ... AM4: =+AM3/AI3-1 -> 0.20207798 | AP4: CT CLSA | BD4: GP | BE4: =+AI11 -> 208405 | BF4: =+AJ11 -> 450930 | BG4: =+AK11 -> 350186 | BH4: =+AL11 -> 351383
B5: Gross Profit | C5: 2994.862 | M5: 2Q21 | N5: =202.575/415.481776 -> 0.48756651 | W5: QoQ% | Y5: =+Y3/X3-1 -> 0.0049677651 | Z5: =+Z3/Y3-1 -> 0.17650084 | AA5: =+AA3/Z3-1 -> -0.047304951 | AB5: =+AB3/AA3-1 -> 0.14690621 | AC5: =+AC3/AB3-1 -> 0.087025094 | AD5: =+AD3/AC3-1 -> 0.11525264 | AE5: =+AE3/AD3-1 -> 0.13452937 | AF5: =+AF3/AE3-1 -> 0.080442586 | ... AM5: =+AM3/AL3-1 -> -0.064030158 | AP5: Capital Alliance | BD5: OP | BE5: =+AI14 -> 145690 | BF5: =+AJ14 -> 161492 | BG5: =+AK14 -> 220228 | BH5: =+AL14 -> 256133.88
B6: GPM | C6: =C5/C$3*100 -> 16.806015 | D6: =D5/D$3*100 -> #DIV/0! | E6: =E5/E$3*100 -> #DIV/0! | F6: =F5/F$3*100 -> #DIV/0! | G6: =G5/G$3*100 -> #DIV/0! | H6: =H5/H$3*100 -> #DIV/0! | I6: =I5/I$3*100 -> #DIV/0! | J6: =AVERAGE(D6:I6) -> #DIV/0! | M6: 3Q21 | N6: =261.001/415.481776 -> 0.6281888 | AP6: Asia Securities | BD6: NP | BE6: =+AI26 -> 61355 | BF6: =+AJ26 -> 98923 | BG6: =+AK26 -> 88445 | BH6: =+AL26 -> 253509.36
B7: EBIT | C7: 2167.608 | M7: 4Q21 | N7: ='[1]LT Portfolio'!P294 -> 0 | W7: Revenue (in USD) | X7: =+X3/X42 -> 4749.5945 | Y7: =+Y3/Y42 -> 4772.5109 | Z7: =+Z3/Z42 -> 5331.2759 | AA7: =+AA3/AA42 -> 4978.746 | AB7: =+AB3/AB42 -> 5680.7038 | AC7: =+AC3/AC42 -> 6173.0392 | AD7: =+AD3/AD42 -> 5985.7965 | AE7: =+AE3/AE42 -> 4352.6799 | ... AM7: =+AM3/AM42 -> #DIV/0! | AP7: First Capital | BD7: EPS | BE7: =+AI29 -> 0.19995545 | BF7: =+AJ29 -> 0.32238925 | BG7: =+AK29 -> 0.28824153 | BH7: =+AL29 -> 0.82618493
B8: EBIT Margin | C8: =C7/C$3*100 -> 12.163784 | D8: =D7/D$3*100 -> #DIV/0! | E8: =E7/E$3*100 -> #DIV/0! | F8: =F7/F$3*100 -> #DIV/0! | G8: =G7/G$3*100 -> #DIV/0! | H8: =H7/H$3*100 -> #DIV/0! | I8: =I7/I$3*100 -> #DIV/0! | J8: =AVERAGE(D8:I8) -> #DIV/0! | M8: 1Q22 | N8: ='[1]LT Portfolio'!Q294 -> 0 | W8: YoY% | AB8: =+AB7/X7-1 -> 0.19603974 | AC8: =+AC7/Y7-1 -> 0.29345733 | AD8: =+AD7/Z7-1 -> 0.12276999 | AE8: =+AE7/AA7-1 -> -0.12574775 | AF8: =+AF7/AB7-1 -> -0.18241155 | AG8: =+AG7/AC7-1 -> -0.36996259 | AH8: =+AH7/AD7-1 -> -0.29646666 | AI8: =+AI7/AE7-1 -> -0.15864314 | ... AM8: =+AM7/AI7-1 -> #DIV/0! | AP8: Bartleet
B9: PBT | C9: 2228.947 | M9: 2Q22 | N9: ='[1]LT Portfolio'!R294 -> 0 | O9: =N9/N5-1 -> -1 | W9: QoQ% | Y9: =+Y7/X7-1 -> 0.0048249125 | Z9: =+Z7/Y7-1 -> 0.11707987 | AA9: =+AA7/Z7-1 -> -0.066124859 | AB9: =+AB7/AA7-1 -> 0.14099088 | AC9: =+AC7/AB7-1 -> 0.086668036 | AD9: =+AD7/AC7-1 -> -0.030332333 | AE9: =+AE7/AD7-1 -> -0.27283197 | AF9: =+AF7/AE7-1 -> 0.06703868 | ... AM9: =+AM7/AL7-1 -> #DIV/0! | AP9: NDBS | AQ9: 8454 | AR9: 1726 | AS9: 1031 | AT9: 3.36 | AU9: 0.42 | AV9: 11369 | AW9: 2644 | AX9: 1760 | AY9: 5.73 | AZ9: 0.42 | BD9: GPM | BE9: =+BE4/BE$3*100 -> 17.982784 | BF9: =+BF4/BF$3*100 -> 29.449509 | BG9: =+BG4/BG$3*100 -> 23.027857 | BH9: =+BH4/BH$3*100 -> 23.607976
B10: Net Profit | C10: 2170.667 | J10: =((I10/D10)^(1/5)-1)*100 -> #DIV/0! | M10: 3Q22 | N10: ='[1]LT Portfolio'!S294 -> 0 | O10: =N10/N6-1 -> -1 | AP10: JKSB | BD10: OPM | BE10: =+BE5/BE$3*100 -> 12.571252 | BF10: =+BF5/BF$3*100 -> 10.546781 | BG10: =+BG5/BG$3*100 -> 14.481958 | BH10: =+BH5/BH$3*100 -> 17.20858
B11: NP Margin | C11: =C10/C$3*100 -> 12.180949 | D11: =D10/D$3*100 -> #DIV/0! | E11: =E10/E$3*100 -> #DIV/0! | F11: =F10/F$3*100 -> #DIV/0! | G11: =G10/G$3*100 -> #DIV/0! | H11: =H10/H$3*100 -> #DIV/0! | I11: =I10/I$3*100 -> #DIV/0! | J11: =AVERAGE(D11:I11) -> #DIV/0! | M11: 4Q22 | N11: ='[1]LT Portfolio'!T294 -> 0 | O11: =N11/N7-1 -> #DIV/0! | W11: Gross Profit | X11: 311138.53 | Y11: 311186.91 | Z11: 375132.08 | AA11: 307416.65 | AB11: 338985.05 | AC11: 342614 | AD11: 416715.15 | AE11: 619340.26 | AF11: 547987.64 | AG11: 412787 | AH11: 281414 | AI11: 208405 | AJ11: 450930 | AK11: 350186 | AL11: 351383 | AM11: 326232 | AP11: Consensus | AQ11: =+AVERAGE(AQ4:AQ10) -> 8454 | AR11: =+AVERAGE(AR4:AR10) -> 1726 | AS11: =+AVERAGE(AS4:AS10) -> 1031 | AT11: =+AVERAGE(AT4:AT10) -> 3.36 | AU11: =+AVERAGE(AU4:AU10) -> 0.42 | AV11: =+AVERAGE(AV4:AV10) -> 11369 | AW11: =+AVERAGE(AW4:AW10) -> 2644 | AX11: =+AVERAGE(AX4:AX10) -> 1760 | ... AZ11: =+AVERAGE(AZ4:AZ10) -> 0.42 | BD11: NPM | BE11: =+BE6/BE$3*100 -> 5.2941806 | BF11: =+BF6/BF$3*100 -> 6.4605012 | BG11: =+BG6/BG$3*100 -> 5.8160486 | BH11: =+BH6/BH$3*100 -> 17.032249
B12: NP Growth | D12: =(D10/C10-1)*100 -> -100 | E12: =(E10/D10-1)*100 -> #DIV/0! | F12: =(F10/E10-1)*100 -> #DIV/0! | G12: =(G10/F10-1)*100 -> #DIV/0! | H12: =(H10/G10-1)*100 -> #DIV/0! | I12: =(I10/H10-1)*100 -> #DIV/0! | J12: =AVERAGE(D12:I12) -> #DIV/0! | S12: 1Q22 | T12: 2Q22 | W12: GPM% | X12: =+X11/X3 -> 0.34867793 | Y12: =+Y11/Y3 -> 0.3470083 | Z12: =+Z11/Z3 -> 0.35555804 | AA12: =+AA11/AA3 -> 0.30584386 | AB12: =+AB11/AB3 -> 0.2940526 | AC12: =+AC11/AC3 -> 0.27340724 | AD12: =+AD11/AD3 -> 0.2981748 | AE12: =+AE11/AE3 -> 0.39061167 | ... AM12: =+AM11/AM3 -> 0.23417617 | AU12: DY | AZ12: DY
M13: TTM | N13: =SUM(N8:N11) -> 0 | Q13: =N13*J21 -> #DIV/0! | S13: 19.109574 | T13: 18.873653 | AP13: Leading P/E | AT13: =+$X$1/AT11 -> 5.4761905 | AU13: =+AU11/$X$1 -> 0.022826087 | AY13: =+$X$1/AY11 -> 3.2111693 | AZ13: =+AZ11/$X$1 -> 0.022826087
B14: EPS | C14: 3.24 | J14: =AVERAGE(D14:I14) -> #DIV/0! | M14: P/E | N14: =N2/N13 -> #VALUE! | Q14: =Q13/N2-1 -> #DIV/0! | S14: =S13/N2-1 -> #VALUE! | T14: =T13/N2-1 -> #VALUE! | W14: EBIT | X14: =+X20-X17 -> 175971.5 | Y14: =+Y20-Y17 -> 157600.41 | Z14: =+Z20-Z17 -> 213998.57 | AA14: =+AA20-AA17 -> 141542.46 | AB14: =+AB20-AB17 -> 170023.22 | AC14: =+AC20-AC17 -> 131202 | AD14: =+AD20-AD17 -> 327672.05 | AE14: =+AE20-AE17 -> 434847.96 | ... AM14: =+AM20-AM17 -> 88129
B15: DPS | C15: =1+0.6 -> 1.6 | W15: EBIT margin % | X15: =+X14/X3 -> 0.19720277 | Y15: =+Y14/Y3 -> 0.17574212 | Z15: =+Z14/Z3 -> 0.20283232 | AA15: =+AA14/AA3 -> 0.14081831 | AB15: =+AB14/AB3 -> 0.14748665 | AC15: =+AC14/AC3 -> 0.10469968 | AD15: =+AD14/AD3 -> 0.23446123 | AE15: =+AE14/AE3 -> 0.27425424 | ... AM15: =+AM14/AM3 -> 0.063260845
B16: MPS | C16: 31.7 | J16: =((I16/D16)^(1/5)-1)*100 -> #DIV/0!
B17: BVPS | C17: 14.6 | J17: =((I17/D17)^(1/6)-1)*100 -> #DIV/0! | W17: Net Finance Income/Cost | X17: -10365.329 | Y17: -7177.808 | Z17: -6734.965 | AA17: =-15701.342+7239.066 -> -8462.276 | AB17: -9462.69 | AC17: -12318 | AD17: -22313.5 | AE17: =-64237.103+3416.424 -> -60820.679 | AF17: -78636.354 | AG17: -83080 | AH17: -83330 | AI17: -69832 | AJ17: -79158 | AK17: -72523 | AL17: -59600 | AM17: -73298
B18: ROE | C18: =C14/AVERAGE(B17:C17)*100 -> 22.191781 | D18: =D14/AVERAGE(C17:D17)*100 -> 0 | E18: =E14/AVERAGE(D17:E17)*100 -> #DIV/0! | F18: =F14/AVERAGE(E17:F17)*100 -> #DIV/0! | G18: =G14/AVERAGE(F17:G17)*100 -> #DIV/0! | H18: =H14/AVERAGE(G17:H17)*100 -> #DIV/0! | I18: =I14/AVERAGE(H17:I17)*100 -> #DIV/0! | J18: =AVERAGE(D18:I18) -> #DIV/0! | M18: MGT | W18: As a % of EBIT | X18: =+X17/X14 -> -0.058903453 | Y18: =+Y17/Y14 -> -0.04554435 | Z18: =+Z17/Z14 -> -0.031472009 | AA18: =+AA17/AA14 -> -0.059786131 | AB18: =+AB17/AB14 -> -0.05565528 | AC18: =+AC17/AC14 -> -0.093885764 | AD18: =+AD17/AD14 -> -0.06809705 | AE18: =+AE17/AE14 -> -0.13986654 | ... AM18: =+AM17/AM14 -> -0.8317126
B19: DY | C19: =C15/C16*100 -> 5.0473186 | D19: =D15/D16*100 -> #DIV/0! | E19: =E15/E16*100 -> #DIV/0! | F19: =F15/F16*100 -> #DIV/0! | G19: =G15/G16*100 -> #DIV/0! | H19: =H15/H16*100 -> #DIV/0! | I19: =I15/I16*100 -> #DIV/0! | J19: =AVERAGE(D19:I19) -> #DIV/0!
B20: Dividend Payout | C20: =C15/C14*100 -> 49.382716 | D20: =D15/D14*100 -> #DIV/0! | E20: =E15/E14*100 -> #DIV/0! | F20: =F15/F14*100 -> #DIV/0! | G20: =G15/G14*100 -> #DIV/0! | H20: =H15/H14*100 -> #DIV/0! | I20: =I15/I14*100 -> #DIV/0! | J20: =AVERAGE(D20:I20) -> #DIV/0! | M20: YoY Growth | N20: =N13/H14-1 -> #DIV/0! | W20: PBT | X20: 165606.17 | Y20: 150422.6 | Z20: 207263.61 | AA20: 133080.18 | AB20: 160560.53 | AC20: 118884 | AD20: 305358.55 | AE20: 374027.28 | AF20: 236816.41 | AG20: 136962 | AH20: -41370 | AI20: 75858 | AJ20: 82334 | AK20: 147705 | AL20: =+AL84-AK20-AJ20-AI20 -> 196533.88 | AM20: 14831
B21: P/E | C21: =C16/C14 -> 9.7839506 | D21: =D16/D14 -> #DIV/0! | E21: =E16/E14 -> #DIV/0! | F21: =F16/F14 -> #DIV/0! | G21: =G16/G14 -> #DIV/0! | H21: =H16/H14 -> #DIV/0! | I21: =I16/I14 -> #DIV/0! | J21: =AVERAGE(D21:I21) -> #DIV/0! | W21: PBT Margin% | X21: =+X20/X3 -> 0.18558684 | Y21: =+Y20/Y3 -> 0.16773806 | Z21: =+Z20/Z3 -> 0.19644878 | AA21: =+AA20/AA3 -> 0.13239933 | AB21: =+AB20/AB3 -> 0.13927824 | AC21: =+AC20/AC3 -> 0.094869874 | AD21: =+AD20/AD3 -> 0.21849512 | AE21: =+AE20/AE3 -> 0.23589525 | ... AM21: =+AM20/AM3 -> 0.010646003
B22: P/B | C22: =C16/C17 -> 2.1712329 | D22: =D16/D17 -> #DIV/0! | E22: =E16/E17 -> #DIV/0! | F22: =F16/F17 -> #DIV/0! | G22: =G16/G17 -> #DIV/0! | H22: =H16/H17 -> #DIV/0! | I22: =I16/I17 -> #DIV/0! | J22: =AVERAGE(D22:I22) -> #DIV/0!
W23: Taxes | X23: -30822.281 | Y23: -21391.238 | Z23: -33928.704 | AA23: -28780.983 | AB23: -33158.298 | AC23: =-14900-6485 -> -21385 | AD23: -46580.095 | AE23: -73659.358 | AF23: -14322.784 | AG23: =-39933-139450 -> -179383 | AH23: =2038+70050 -> 72088 | AI23: =-18452+3949 -> -14503 | AJ23: 16589 | AK23: -59260 | AL23: =+AL85-AI23-AJ23-AK23 -> 56975.477 | AM23: =-28944-4761 -> -33705
G24: 701.95658 | H24: 709.32254 | I24: 716.73997 | W24: ETR% | X24: =+X23/X20 -> -0.18611795 | Y24: =+Y23/Y20 -> -0.14220761 | Z24: =+Z23/Z20 -> -0.16369832 | AA24: =+AA23/AA20 -> -0.21626798 | AB24: =+AB23/AB20 -> -0.20651587 | AC24: =+AC23/AC20 -> -0.17988123 | AD24: =+AD23/AD20 -> -0.1525423 | AE24: =+AE23/AE20 -> -0.19693579 | ... AM24: =+AM23/AM20 -> -2.2726047
G25: =+G10/G24 -> 0 | H25: =+H10/H24 -> 0 | I25: =+I10/I24 -> 0
W26: Net Profit Attributable to Equity Holders | X26: =+X20+X23 -> 134783.89 | Y26: =+Y20+Y23 -> 129031.36 | Z26: =+Z20+Z23 -> 173334.9 | AA26: =+AA20+AA23 -> 104299.2 | AB26: =+AB20+AB23 -> 127402.23 | AC26: =+AC20+AC23 -> 97499 | AD26: =+AD20+AD23 -> 258778.45 | AE26: =+AE20+AE23 -> 300367.93 | ... AM26: =+AM20+AM23 -> -18874
W27: NP Margin | X27: =+X26/X3 -> 0.1510458 | Y27: =+Y26/Y3 -> 0.14388443 | Z27: =+Z26/Z3 -> 0.16429045 | AA27: =+AA26/AA3 -> 0.10376559 | AB27: =+AB26/AB3 -> 0.11051507 | AC27: =+AC26/AC3 -> 0.077804564 | AD27: =+AD26/AD3 -> 0.18516537 | AE27: =+AE26/AE3 -> 0.18943903 | ... AM27: =+AM26/AM3 -> -0.013548153
W29: EPS | X29: =+X26/X44 -> 0.4392596 | Y29: =+Y26/Y44 -> 0.42051215 | Z29: =+Z26/Z44 -> 0.56489703 | AA29: =+AA26/AA44 -> 0.33991024 | AB29: =+AB26/AB44 -> 0.41520284 | AC29: =+AC26/AC44 -> 0.31774845 | AD29: =+AD26/AD44 -> 0.84335687 | AE29: =+AE26/AE44 -> 0.97889663 | ... AM29: =+AM26/AM44 -> -0.061510212
W30: YoY% | AB30: =+AB29/X29-1 -> -0.054766619 | AC30: =+AC29/Y29-1 -> -0.24437749 | AD30: =+AD29/Z29-1 -> 0.49293912 | AE30: =+AE29/AA29-1 -> 1.879868 | AF30: =+AF29/AB29-1 -> 0.74638718 | AG30: =+AG29/AC29-1 -> -1.4350916 | AH30: =+AH29/AD29-1 -> -0.88129615 | AI30: =+AI29/AE29-1 -> -0.79573385 | ... AM30: =+AM29/AI29-1 -> -1.3076196
W31: QoQ% | Y31: =+Y29/X29-1 -> -0.042679663 | Z31: =+Z29/Y29-1 -> 0.34335483 | AA31: =+AA29/Z29-1 -> -0.39827929 | AB31: =+AB29/AA29-1 -> 0.22150729 | AC31: =+AC29/AB29-1 -> -0.23471514 | AD31: =+AD29/AC29-1 -> 1.6541652 | AE31: =+AE29/AD29-1 -> 0.16071459 | AF31: =+AF29/AE29-1 -> -0.25926304 | ... AM31: =+AM29/AL29-1 -> -1.0744509
W33: RoE | X33: =+X26*4/X38 -> 0.17512429 | Y33: =+Y26*4/Y38 -> 0.16125518 | Z33: =+Z26*4/Z38 -> 0.21392051 | AA33: =+AA26*4/AA38 -> 0.12444602 | AB33: =+AB26*4/AB38 -> 0.16604009 | AC33: =+AC26*4/AC38 -> 0.11045142 | AD33: =+AD26*4/AD38 -> 0.3437744 | AE33: =+AE26*4/AE38 -> 0.41273896 | ... AM33: =+AM26*4/AM38 -> -0.018800495 | AO33: =+AVERAGE(X33:AM33) -> 0.15382125 | AP33: RoE
AO34: =AVERAGE(X33:AM33)*AM46 -> 2.0130486 | AP34: Normalized EPS
W35: Debt | X35: =426032.725+43189.375+947386.696 -> 1416608.8 | Y35: =1056608.135+40504.796+419040.114 -> 1516153 | Z35: =825943.002+36009.829+1737.629+1037079.851 -> 1900770.3 | AA35: =999991.123+36982.83-1999.5+1251100.352 -> 2286074.8 | AB35: =1910009.447+228766.544+2091814.003+870.389 -> 4231460.4 | AC35: =1930726+36236+1117388 -> 3084350 | AD35: =2030315.505+35135.746+872.487+1971507.945 -> 4037831.7 | AE35: =1783721.111+34900.99+872.487+2876409.838 -> 4695904.4 | AF35: =1760634.388+34659.12+22100.72+2760257.49 -> 4577651.7 | AG35: =2069054+47698+1740380+6176 -> 3863308 | AH35: =1231028+36086+1936017+10996 -> 3214127 | AI35: =1481395+36843+1418958+10996 -> 2948192 | AJ35: =974946+36539+8144+2106053 -> 3125682 | AK35: =974946+33333+8099+1883544 -> 2899922 | AL35: =705541+32781+2179+2037051 -> 2777552 | AM35: =840036+98556+76581+2072056 -> 3087229 | AO35: =X1/AO34 -> 9.1403653 | AP35: P/E
W36: Cash | X36: 328900.05 | Y36: 335189.23 | Z36: =275808.326+55498.469 -> 331306.79 | AA36: =232498.822+282848.236 -> 515347.06 | AB36: =115561.187+59077.6 -> 174638.79 | AC36: =687380+180483 -> 867863 | AD36: =115561.187+59077.6 -> 174638.79 | AE36: =281309.783+62346.154 -> 343655.94 | AF36: =192217.469+66379.769 -> 258597.24 | AG36: 150104 | AH36: 185416 | AI36: 65982 | AJ36: 111761 | AK36: 124546 | AL36: 35446 | AM36: =95485+30240 -> 125725
W37: Net Debt | X37: =+X35-X36 -> 1087708.7 | Y37: =+Y35-Y36 -> 1180963.8 | Z37: =+Z35-Z36 -> 1569463.5 | AA37: =+AA35-AA36 -> 1770727.7 | AB37: =+AB35-AB36 -> 4056821.6 | AC37: =+AC35-AC36 -> 2216487 | AD37: =+AD35-AD36 -> 3863192.9 | AE37: =+AE35-AE36 -> 4352248.5 | ... AM37: =+AM35-AM36 -> 2961504
W38: Equity | X38: 3078588.2 | Y38: 3200675.1 | Z38: 3241108.6 | AA38: 3352431.8 | AB38: 3069192 | AC38: 3530928 | AD38: 3011026.4 | AE38: 2910972.3 | AF38: 3209857.4 | AG38: 3243912 | AH38: 3615384 | AI38: 3676739 | AJ38: 3775661 | AK38: 3864106 | AL38: 4053820 | AM38: 4015639
W40: Debt/Equity | X40: =+X35/X38 -> 0.46014884 | Y40: =+Y35/Y38 -> 0.47369789 | Z40: =+Z35/Z38 -> 0.58645684 | AA40: =+AA35/AA38 -> 0.68191538 | AB40: =+AB35/AB38 -> 1.3786887 | AC40: =+AC35/AC38 -> 0.8735239 | AD40: =+AD35/AD38 -> 1.341015 | AE40: =+AE35/AE38 -> 1.6131738 | ... AM40: =+AM35/AM38 -> 0.76880143
W42: Average Exchange rate (income Statement) | X42: =+MGT!X42 -> 187.87665 | Y42: =+MGT!Y42 -> 187.90336 | Z42: =+MGT!Z42 -> 197.89852 | AA42: =+MGT!AA42 -> 201.88667 | AB42: =+MGT!AB42 -> 202.93333 | AC42: =+MGT!AC42 -> 203.00001 | AD42: =+MGT!AD42 -> 233.47823 | AE42: =+MGT!AE42 -> 364.27332 | ... AL42: =+MGT!AL42 -> 311.04853 | AM42: =+MGT!AN42 -> 0
W44: Number of shares | X44: 306843.36 | Y44: 306843.36 | Z44: 306843.36 | AA44: 306843.36 | AB44: 306843.36 | AC44: 306843.36 | AD44: 306843.36 | AE44: 306843.36 | AF44: 306843.36 | AG44: 306843.36 | AH44: 306843.36 | AI44: 306843.36 | AJ44: 306843.36 | AK44: 306843.36 | AL44: 306843.36 | AM44: 306843.36
W46: Net Asset Value per share | X46: =+X38/X44 -> 10.033094 | Y46: =+Y38/Y44 -> 10.430974 | Z46: =+Z38/Z44 -> 10.562747 | AA46: =+AA38/AA44 -> 10.925548 | AB46: =+AB38/AB44 -> 10.002472 | AC46: =+AC38/AC44 -> 11.507266 | AD46: =+AD38/AD44 -> 9.8129106 | AE46: =+AE38/AE44 -> 9.4868351 | ... AM46: =+AM38/AM44 -> 13.086935
W48: Cashflow from operations (in LKR 000') | Y48: =+Y52-X52 -> 221883.47 | Z48: =+Z52-Y52 -> -24632.445 | AA48: =+AA52 -> -100495.69 | AB48: =+AB52-AA52 -> -29331.656 | AC48: =+AC52-AB52 -> 44024.349 | AD48: =+AD52-AC52 -> -847286.43 | AE48: =+AE52 -> -460861.78 | AF48: =+AF52-AE52 -> 120048.07 | AG48: =+AG52-AF52 -> 645641.71 | AH48: =+AH52-AG52 -> 740250 | AI48: =+AI52 -> 188651 | AJ48: =+AJ52-AI52 -> -71470 | AK48: =+AK52-AJ52 -> 383425 | AL48: =+AL52-AK52 -> -153996 | AM48: =+AM52 -> -52089
W49: Capex | Y49: =+Y53-X53 -> -165776.01 | Z49: =+Z53-Y53 -> -58181.232 | AA49: =+AA53 -> -110771.73 | AB49: =+AB53-AA53 -> -176982.18 | AC49: =+AC53-AB53 -> -237399.09 | AD49: =+AD53-AC53 -> -729932.46 | AE49: =+AE53 -> -31844.989 | AF49: =+AF53-AE53 -> -70011.791 | AG49: =+AG53-AF53 -> -43347.22 | AH49: =+AH53-AG53 -> -62825 | AI49: =+AI53 -> -41486 | AJ49: =+AJ53-AI53 -> -63470 | AK49: =+AK53-AJ53 -> -389492 | AL49: =+AL53-AK53 -> 83146 | AM49: =+AM53 -> -28693
W50: FCF (in LKR 000') | Y50: =+Y48+Y49 -> 56107.457 | Z50: =+Z48+Z49 -> -82813.677 | AA50: =+AA48+AA49 -> -211267.43 | AB50: =+AB48+AB49 -> -206313.83 | AC50: =+AC48+AC49 -> -193374.74 | AD50: =+AD48+AD49 -> -1577218.9 | AE50: =+AE48+AE49 -> -492706.77 | AF50: =+AF48+AF49 -> 50036.274 | ... AM50: =+AM48+AM49 -> -80782
W52: Cashflow from operations (in LKR 000') | X52: -129827.35 | Y52: 92056.119 | Z52: 67423.674 | AA52: -100495.69 | AB52: -129827.35 | AC52: -85803 | AD52: -933089.43 | AE52: -460861.78 | AF52: -340813.71 | AG52: 304828 | AH52: 1045078 | AI52: 188651 | AJ52: 117181 | AK52: 500606 | AL52: 346610 | AM52: -52089
W53: Capex | X53: -287753.91 | Y53: -453529.92 | Z53: -511711.15 | AA53: -110771.73 | AB53: -287753.91 | AC53: -525153 | AD53: -1255085.5 | AE53: -31844.989 | AF53: -101856.78 | AG53: -145204 | AH53: -208029 | AI53: -41486 | AJ53: -104956 | AK53: -494448 | AL53: -411302 | AM53: -28693
W54: FCF (in LKR 000') | X54: =+X52+X53 -> -417581.26 | Y54: =+Y52+Y53 -> -361473.8 | Z54: =+Z52+Z53 -> -444287.48 | AA54: =+AA52+AA53 -> -211267.43 | AB54: =+AB52+AB53 -> -417581.26 | AC54: =+AC52+AC53 -> -610956 | AD54: =+AD52+AD53 -> -2188174.9 | AE54: =+AE52+AE53 -> -492706.77 | ... AM54: =+AM52+AM53 -> -80782
W56: Segments
W57: Brushware
W58: Revenue | AB58: 1129958.1 | AC58: 1146005 | AD58: 1305105 | AE58: 1332532 | AF58: 1561554.6 | AG58: 1294267 | AH58: 1249081 | AI58: 957383 | AJ58: 1334700 | AK58: 1348664 | AL58: 1085850 | AM58: 974029
W59: YoY% | AD59: =+AD58/Z58-1 -> #DIV/0! | AE59: =+AE58/AA58-1 -> #DIV/0! | AF59: =+AF58/AB58-1 -> 0.38195802 | AG59: =+AG58/AC58-1 -> 0.12937291 | AH59: =+AH58/AD58-1 -> -0.042926814 | AI59: =+AI58/AE58-1 -> -0.28153095 | AJ59: =+AJ58/AF58-1 -> -0.14527487 | AK59: =+AK58/AG58-1 -> 0.042029195 | ... AM59: =+AM58/AI58-1 -> 0.017386981
W60: QoQ% | AA60: =+AA58/Z58-1 -> #DIV/0! | AB60: =+AB58/AA58-1 -> #DIV/0! | AC60: =+AC58/AB58-1 -> 0.014201333 | AD60: =+AD58/AC58-1 -> 0.13883011 | AE60: =+AE58/AD58-1 -> 0.021015167 | AF60: =+AF58/AE58-1 -> 0.17187028 | AG60: =+AG58/AF58-1 -> -0.17116766 | AH60: =+AH58/AG58-1 -> -0.034912425 | ... AM60: =+AM58/AL58-1 -> -0.10298015
W61: Gross profit | AB61: 289771.87 | AC61: 276445 | AD61: 319426 | AE61: 496953 | AF61: 439278.59 | AG61: 348866 | AH61: 322265 | AI61: 194090 | AJ61: 299043 | AK61: 276004 | AL61: 283390 | AM61: 261468
W62: margin% | Z62: =+Z61/Z58 -> #DIV/0! | AA62: =+AA61/AA58 -> #DIV/0! | AB62: =+AB61/AB58 -> 0.2564448 | AC62: =+AC61/AC58 -> 0.24122495 | AD62: =+AD61/AD58 -> 0.24475119 | AE62: =+AE61/AE58 -> 0.37293889 | AF62: =+AF61/AF58 -> 0.2813085 | AG62: =+AG61/AG58 -> 0.26954716 | ... AM62: =+AM61/AM58 -> 0.26843965
W63: PBT | AB63: =171470.825+24219.854 -> 195690.68 | AC63: 86405 | AD63: 111150 | AE63: 226938 | AF63: =204486.055+9226.466 -> 213712.52 | AG63: 155159 | AH63: 119270 | AI63: 57284 | AJ63: 81215 | AK63: 157540 | AL63: =61551+68500-52038 -> 78013 | AM63: 50681
W64: margin% | Z64: =+Z63/Z58 -> #DIV/0! | AA64: =+AA63/AA58 -> #DIV/0! | AB64: =+AB63/AB58 -> 0.17318402 | AC64: =+AC63/AC58 -> 0.075396704 | AD64: =+AD63/AD58 -> 0.085165561 | AE64: =+AE63/AE58 -> 0.17030585 | AF64: =+AF63/AF58 -> 0.13685882 | AG64: =+AG63/AG58 -> 0.11988176 | ... AM64: =+AM63/AM58 -> 0.052032332
W66: Filament and Yarn
W67: Revenue | AB67: 385768.65 | AC67: 431896 | AD67: 561384 | AE67: 581267 | AF67: 618207.91 | AG67: 471203 | AH67: 349153 | AI67: 449271 | AJ67: 556537 | AK67: 648170 | AL67: 536498 | AM67: 556426
W68: YoY% | AD68: =+AD67/Z67-1 -> #DIV/0! | AE68: =+AE67/AA67-1 -> #DIV/0! | AF68: =+AF67/AB67-1 -> 0.60253539 | AG68: =+AG67/AC67-1 -> 0.091010336 | AH68: =+AH67/AD67-1 -> -0.37804961 | AI68: =+AI67/AE67-1 -> -0.22708325 | AJ68: =+AJ67/AF67-1 -> -0.09975756 | AK68: =+AK67/AG67-1 -> 0.37556425 | ... AM68: =+AM67/AI67-1 -> 0.23850861
W69: QoQ% | AA69: =+AA67/Z67-1 -> #DIV/0! | AB69: =+AB67/AA67-1 -> #DIV/0! | AC69: =+AC67/AB67-1 -> 0.11957258 | AD69: =+AD67/AC67-1 -> 0.29981292 | AE69: =+AE67/AD67-1 -> 0.035417825 | AF69: =+AF67/AE67-1 -> 0.0635524 | AG69: =+AG67/AF67-1 -> -0.23779203 | AH69: =+AH67/AG67-1 -> -0.25901788 | ... AM69: =+AM67/AL67-1 -> 0.037144593
W70: Gross profit | AB70: 47149.066 | AC70: 70942 | AD70: 116213 | AE70: 132247 | AF70: 110830.75 | AG70: 58393 | AH70: -43776 | AI70: 8159 | AJ70: 105172 | AK70: 46906 | AL70: 33955 | AM70: 37947
W71: margin% | Z71: =+Z70/Z67 -> #DIV/0! | AA71: =+AA70/AA67 -> #DIV/0! | AB71: =+AB70/AB67 -> 0.12222109 | AC71: =+AC70/AC67 -> 0.16425714 | AD71: =+AD70/AD67 -> 0.2070116 | AE71: =+AE70/AE67 -> 0.22751507 | AF71: =+AF70/AF67 -> 0.17927747 | AG71: =+AG70/AG67 -> 0.12392323 | ... AM71: =+AM70/AM67 -> 0.068197748
W72: PBT | AB72: =13493.486+8938.444 -> 22431.93 | AC72: 38270 | AD72: 223485 | AE72: 157971 | AF72: =21161.872+5096.318 -> 26258.19 | AG72: -23938 | AH72: -162551 | AI72: 13436 | AJ72: 13290 | AK72: -6449 | AL72: =-405152+466000-354.01 -> 60493.99 | AM72: -38440
W73: margin% | Z73: =+Z72/Z67 -> #DIV/0! | AA73: =+AA72/AA67 -> #DIV/0! | AB73: =+AB72/AB67 -> 0.05814866 | AC73: =+AC72/AC67 -> 0.088609295 | AD73: =+AD72/AD67 -> 0.39809649 | AE73: =+AE72/AE67 -> 0.27177012 | AF73: =+AF72/AF67 -> 0.042474691 | AG73: =+AG72/AG67 -> -0.050801884 | ... AM73: =+AM72/AM67 -> -0.06908376
W75: Foreign Exchange Gain or Loss | AF75: -4936 | AG75: 5789 | AH75: -31356 | AI75: 107231 | AJ75: -98901 | AK75: -2252 | AL75: 118741 | AM75: -33169
W76: Average Rate | AF76: 363.36 | AG76: 366.01 | AH76: 352.66 | AI76: 310.25 | AJ76: 321.2 | AK76: 326.52 | AL76: 313.23 | AM76: 300.91
W77: Ending Rate | AE77: 361.44 | AF77: 364.54 | AG77: 366.01 | AH77: 327.14 | AI77: 308.92 | AJ77: 323.58 | AK77: 323.98 | AL77: 300.44 | AM77: 305.69
AL79: Hedging Reserve
AL80: Brush | AN80: 68.5 | AO80: =+AN80/AN82*AO82 -> 52.037957
AL81: Polyester | AN81: 466 | AO81: =+AN81/AN82*AO82 -> 354.01004
AN82: =+SUM(AN80:AN81) -> 534.5 | AO82: 406.048
AK84: Adjusted OP | AL84: =96382.868+406048.013 -> 502430.88
AK85: Adjusted Taxes | AL85: -198.523

Sheet HAYL
W1: Stock Price | X1: =+'Valuation Sheet'!C6 -> 95.6
B2: TJL - Rs mn | C2: FY16 | D2: FY17 | E2: FY18 | F2: FY19 | G2: FY20 | H2: FY21 | I2: FY22 | J2: CAGR/AVG | M2: MPS | N2: ='[1]LT Portfolio'!I294 -> SELL | P2: AVG | Q2: =J14*J21 -> #DIV/0! | W2: HAYL | X2: 2Q21 | Y2: 3Q21 | Z2: 4Q21 | AA2: 1Q22 | AB2: 2Q22 | AC2: 3Q22 | AD2: 4Q22 | AE2: 1Q23 | AF2: 2Q23 | AG2: 3Q23 | AH2: 4Q23 | AI2: 1Q24 | AJ2: 2Q24 | AK2: 3Q24 | AL2: 4Q24 | AM2: 1Q25 | AO2: =+W2 -> HAYL | AP2: FY24E | AU2: FY25E
B3: Net Revenue | C3: 17820.179 | M3: P/E | N3: ='[1]LT Portfolio'!W294 -> 0 | W3: Revenue (LKR 000) | AB3: 79438158 | AC3: 92217650 | AD3: 95743008 | AE3: 123641304 | AF3: 129931777 | AG3: 116350572 | AH3: 117507228 | AI3: 96938050 | AJ3: 105256047 | AK3: 122302403 | AL3: 112336770 | AM3: 113607627 | AP3: Revenue | AQ3: EBIT | AR3: NP | AS3: EPS | AT3: DPS | AU3: Revenue | AV3: EBIT | AW3: NP | AX3: EPS | AY3: DPS
B4: Revenue Growth | D4: =(D3/C3-1)*100 -> -100 | E4: =(E3/D3-1)*100 -> #DIV/0! | F4: =(F3/E3-1)*100 -> #DIV/0! | G4: =(G3/F3-1)*100 -> #DIV/0! | H4: =(H3/G3-1)*100 -> #DIV/0! | I4: =(I3/H3-1)*100 -> #DIV/0! | J4: =((I3/D3)^(1/5)-1)*100 -> #DIV/0! | W4: YoY% | AB4: =+AB3/X3-1 -> #DIV/0! | AC4: =+AC3/Y3-1 -> #DIV/0! | AD4: =+AD3/Z3-1 -> #DIV/0! | AE4: =+AE3/AA3-1 -> #DIV/0! | AF4: =+AF3/AB3-1 -> 0.63563431 | AG4: =+AG3/AC3-1 -> 0.26169526 | AH4: =+AH3/AD3-1 -> 0.22731916 | AI4: =+AI3/AE3-1 -> -0.21597357 | ... AM4: =+AM3/AI3-1 -> 0.17196113 | AO4: Acuity | AP4: 416563 | AQ4: 36452 | AR4: 6892 | AS4: 9.19 | AU4: 448372 | AV4: 42475 | AW4: 13460 | AX4: 17.95
B5: Gross Profit | C5: 2994.862 | M5: 2Q21 | N5: =202.575/415.481776 -> 0.48756651 | W5: QoQ% | Y5: =+Y3/X3-1 -> #DIV/0! | Z5: =+Z3/Y3-1 -> #DIV/0! | AA5: =+AA3/Z3-1 -> #DIV/0! | AB5: =+AB3/AA3-1 -> #DIV/0! | AC5: =+AC3/AB3-1 -> 0.16087347 | AD5: =+AD3/AC3-1 -> 0.038228669 | AE5: =+AE3/AD3-1 -> 0.29138729 | AF5: =+AF3/AE3-1 -> 0.050876793 | ... AM5: =+AM3/AL3-1 -> 0.011312921
B6: GPM | C6: =C5/C$3*100 -> 16.806015 | D6: =D5/D$3*100 -> #DIV/0! | E6: =E5/E$3*100 -> #DIV/0! | F6: =F5/F$3*100 -> #DIV/0! | G6: =G5/G$3*100 -> #DIV/0! | H6: =H5/H$3*100 -> #DIV/0! | I6: =I5/I$3*100 -> #DIV/0! | J6: =AVERAGE(D6:I6) -> #DIV/0! | M6: 3Q21 | N6: =261.001/415.481776 -> 0.6281888
B7: EBIT | C7: 2167.608 | M7: 4Q21 | N7: ='[1]LT Portfolio'!P294 -> 0 | W7: Revenue (in USD) | AB7: =+AB3/AB44 -> 391449.54 | AC7: =+AC3/AC44 -> 454274.12 | AD7: =+AD3/AD44 -> 410072.52 | AE7: =+AE3/AE44 -> 339419.05 | AF7: =+AF3/AF44 -> 352262.56 | AG7: =+AG3/AG44 -> 312959.27 | AH7: =+AH3/AH44 -> 328521.26 | AI7: =+AI3/AI44 -> 306323.31 | ... AM7: =+AM3/AM44 -> 371351.71
B8: EBIT Margin | C8: =C7/C$3*100 -> 12.163784 | D8: =D7/D$3*100 -> #DIV/0! | E8: =E7/E$3*100 -> #DIV/0! | F8: =F7/F$3*100 -> #DIV/0! | G8: =G7/G$3*100 -> #DIV/0! | H8: =H7/H$3*100 -> #DIV/0! | I8: =I7/I$3*100 -> #DIV/0! | J8: =AVERAGE(D8:I8) -> #DIV/0! | M8: 1Q22 | N8: ='[1]LT Portfolio'!Q294 -> 0 | W8: YoY% | AB8: =+AB7/X7-1 -> #DIV/0! | AC8: =+AC7/Y7-1 -> #DIV/0! | AD8: =+AD7/Z7-1 -> #DIV/0! | AE8: =+AE7/AA7-1 -> #DIV/0! | AF8: =+AF7/AB7-1 -> -0.10010738 | AG8: =+AG7/AC7-1 -> -0.31107836 | AH8: =+AH7/AD7-1 -> -0.19887033 | AI8: =+AI7/AE7-1 -> -0.097507029 | ... AM8: =+AM7/AI7-1 -> 0.21228685
B9: PBT | C9: 2228.947 | M9: 2Q22 | N9: ='[1]LT Portfolio'!R294 -> 0 | O9: =N9/N5-1 -> -1 | W9: QoQ% | Y9: =+Y7/X7-1 -> #DIV/0! | Z9: =+Z7/Y7-1 -> #DIV/0! | AA9: =+AA7/Z7-1 -> #DIV/0! | AB9: =+AB7/AA7-1 -> #DIV/0! | AC9: =+AC7/AB7-1 -> 0.16049215 | AD9: =+AD7/AC7-1 -> -0.097301605 | AE9: =+AE7/AD7-1 -> -0.17229507 | AF9: =+AF7/AE7-1 -> 0.037839678 | ... AM9: =+AM7/AL7-1 -> 0.028233259
B10: Net Profit | C10: 2170.667 | J10: =((I10/D10)^(1/5)-1)*100 -> #DIV/0! | M10: 3Q22 | N10: ='[1]LT Portfolio'!S294 -> 0 | O10: =N10/N6-1 -> -1
B11: NP Margin | C11: =C10/C$3*100 -> 12.180949 | D11: =D10/D$3*100 -> #DIV/0! | E11: =E10/E$3*100 -> #DIV/0! | F11: =F10/F$3*100 -> #DIV/0! | G11: =G10/G$3*100 -> #DIV/0! | H11: =H10/H$3*100 -> #DIV/0! | I11: =I10/I$3*100 -> #DIV/0! | J11: =AVERAGE(D11:I11) -> #DIV/0! | M11: 4Q22 | N11: ='[1]LT Portfolio'!T294 -> 0 | O11: =N11/N7-1 -> #DIV/0! | W11: Gross Profit | AB11: 17634178 | AC11: 21646404 | AD11: 21788356 | AE11: 32477265 | AF11: 29685645 | AG11: 28693187 | AH11: 28377936 | AI11: 22642278 | AJ11: 25208153 | AK11: 29935583 | AL11: 31639764 | AM11: 25961963 | AO11: Consensus | AP11: =+AVERAGE(AP4:AP10) -> 416563 | AQ11: =+AVERAGE(AQ4:AQ10) -> 36452 | AR11: =+AVERAGE(AR4:AR10) -> 6892 | AS11: =+AVERAGE(AS4:AS10) -> 9.19 | AT11: =+AVERAGE(AT4:AT10) -> #DIV/0! | AU11: =+AVERAGE(AU4:AU10) -> 448372 | AV11: =+AVERAGE(AV4:AV10) -> 42475 | AW11: =+AVERAGE(AW4:AW10) -> 13460 | ... AY11: =+AVERAGE(AY4:AY10) -> #DIV/0!
B12: NP Growth | D12: =(D10/C10-1)*100 -> -100 | E12: =(E10/D10-1)*100 -> #DIV/0! | F12: =(F10/E10-1)*100 -> #DIV/0! | G12: =(G10/F10-1)*100 -> #DIV/0! | H12: =(H10/G10-1)*100 -> #DIV/0! | I12: =(I10/H10-1)*100 -> #DIV/0! | J12: =AVERAGE(D12:I12) -> #DIV/0! | S12: 1Q22 | T12: 2Q22 | W12: GPM% | X12: =+X11/X3 -> #DIV/0! | Y12: =+Y11/Y3 -> #DIV/0! | Z12: =+Z11/Z3 -> #DIV/0! | AA12: =+AA11/AA3 -> #DIV/0! | AB12: =+AB11/AB3 -> 0.22198624 | AC12: =+AC11/AC3 -> 0.23473168 | AD12: =+AD11/AD3 -> 0.22757125 | AE12: =+AE11/AE3 -> 0.26267326 | ... AM12: =+AM11/AM3 -> 0.22852306 | AT12: DY | AY12: DY
M13: TTM | N13: =SUM(N8:N11) -> 0 | Q13: =N13*J21 -> #DIV/0! | S13: 19.109574 | T13: 18.873653 | AO13: Leading P/E | AS13: =+$X$1/AS11 -> 10.402612 | AT13: =+AT11/$X$1 -> #DIV/0! | AX13: =+$X$1/AX11 -> 5.3259053 | AY13: =+AY11/$X$1 -> #DIV/0!
B14: EPS | C14: 3.24 | J14: =AVERAGE(D14:I14) -> #DIV/0! | M14: P/E | N14: =N2/N13 -> #VALUE! | Q14: =Q13/N2-1 -> #DIV/0! | S14: =S13/N2-1 -> #VALUE! | T14: =T13/N2-1 -> #VALUE! | W14: EBIT | AB14: 7377111 | AC14: 10546997 | AD14: 9133256 | AE14: 18154352 | AF14: 15898975 | AG14: 13571888 | AH14: 13447532 | AI14: 8326846 | AJ14: 8537727 | AK14: 11204613 | AL14: 14653674 | AM14: 8492527
B15: DPS | C15: =1+0.6 -> 1.6 | W15: EBIT margin % | X15: =+X14/X3 -> #DIV/0! | Y15: =+Y14/Y3 -> #DIV/0! | Z15: =+Z14/Z3 -> #DIV/0! | AA15: =+AA14/AA3 -> #DIV/0! | AB15: =+AB14/AB3 -> 0.092866088 | AC15: =+AC14/AC3 -> 0.1143707 | AD15: =+AD14/AD3 -> 0.095393452 | AE15: =+AE14/AE3 -> 0.1468308 | ... AM15: =+AM14/AM3 -> 0.074753141
B16: MPS | C16: 31.7 | J16: =((I16/D16)^(1/5)-1)*100 -> #DIV/0!
B17: BVPS | C17: 14.6 | J17: =((I17/D17)^(1/6)-1)*100 -> #DIV/0! | W17: Net Finance Income/Cost | AB17: -1543700 | AC17: -1743743 | AD17: 6942999 | AE17: 1779517 | AF17: -6090674 | AG17: -6935352 | AH17: -7570892 | AI17: -6015556 | AJ17: =2209881-5867753 -> -3657872 | AK17: =-6244033+2727978 -> -3516055 | AL17: -4052833 | AM17: -2744974
B18: ROE | C18: =C14/AVERAGE(B17:C17)*100 -> 22.191781 | D18: =D14/AVERAGE(C17:D17)*100 -> 0 | E18: =E14/AVERAGE(D17:E17)*100 -> #DIV/0! | F18: =F14/AVERAGE(E17:F17)*100 -> #DIV/0! | G18: =G14/AVERAGE(F17:G17)*100 -> #DIV/0! | H18: =H14/AVERAGE(G17:H17)*100 -> #DIV/0! | I18: =I14/AVERAGE(H17:I17)*100 -> #DIV/0! | J18: =AVERAGE(D18:I18) -> #DIV/0! | M18: MGT | W18: As a % of EBIT | X18: =+X17/X14 -> #DIV/0! | Y18: =+Y17/Y14 -> #DIV/0! | Z18: =+Z17/Z14 -> #DIV/0! | AA18: =+AA17/AA14 -> #DIV/0! | AB18: =+AB17/AB14 -> -0.20925536 | AC18: =+AC17/AC14 -> -0.16533076 | AD18: =+AD17/AD14 -> 0.76018881 | AE18: =+AE17/AE14 -> 0.09802151 | ... AM18: =+AM17/AM14 -> -0.32322229
B19: DY | C19: =C15/C16*100 -> 5.0473186 | D19: =D15/D16*100 -> #DIV/0! | E19: =E15/E16*100 -> #DIV/0! | F19: =F15/F16*100 -> #DIV/0! | G19: =G15/G16*100 -> #DIV/0! | H19: =H15/H16*100 -> #DIV/0! | I19: =I15/I16*100 -> #DIV/0! | J19: =AVERAGE(D19:I19) -> #DIV/0!
B20: Dividend Payout | C20: =C15/C14*100 -> 49.382716 | D20: =D15/D14*100 -> #DIV/0! | E20: =E15/E14*100 -> #DIV/0! | F20: =F15/F14*100 -> #DIV/0! | G20: =G15/G14*100 -> #DIV/0! | H20: =H15/H14*100 -> #DIV/0! | I20: =I15/I14*100 -> #DIV/0! | J20: =AVERAGE(D20:I20) -> #DIV/0! | M20: YoY Growth | N20: =N13/H14-1 -> #DIV/0! | W20: PBT | AB20: 5889250 | AC20: 8731640 | AD20: 16255437 | AE20: 20007560 | AF20: 10009854 | AG20: 6534672 | AH20: 6196982 | AI20: 2295396 | AJ20: 4843074 | AK20: 7614809 | AL20: 10582428 | AM20: 5734473
B21: P/E | C21: =C16/C14 -> 9.7839506 | D21: =D16/D14 -> #DIV/0! | E21: =E16/E14 -> #DIV/0! | F21: =F16/F14 -> #DIV/0! | G21: =G16/G14 -> #DIV/0! | H21: =H16/H14 -> #DIV/0! | I21: =I16/I14 -> #DIV/0! | J21: =AVERAGE(D21:I21) -> #DIV/0! | W21: PBT Margin% | X21: =+X20/X3 -> #DIV/0! | Y21: =+Y20/Y3 -> #DIV/0! | Z21: =+Z20/Z3 -> #DIV/0! | AA21: =+AA20/AA3 -> #DIV/0! | AB21: =+AB20/AB3 -> 0.074136286 | AC21: =+AC20/AC3 -> 0.094685128 | AD21: =+AD20/AD3 -> 0.16978198 | AE21: =+AE20/AE3 -> 0.16181939 | ... AM21: =+AM20/AM3 -> 0.050476127
B22: P/B | C22: =C16/C17 -> 2.1712329 | D22: =D16/D17 -> #DIV/0! | E22: =E16/E17 -> #DIV/0! | F22: =F16/F17 -> #DIV/0! | G22: =G16/G17 -> #DIV/0! | H22: =H16/H17 -> #DIV/0! | I22: =I16/I17 -> #DIV/0! | J22: =AVERAGE(D22:I22) -> #DIV/0!
W23: Taxes | AB23: -1461068 | AC23: -2104970 | AD23: -2801798 | AE23: -3711611 | AF23: -2852657 | AG23: -5709782 | AH23: -2802718 | AI23: -974629 | AJ23: -3007890 | AK23: -3620587 | AL23: -2885878 | AM23: -2615823
G24: 701.95658 | H24: 709.32254 | I24: 716.73997 | W24: ETR% | X24: =+X23/X20 -> #DIV/0! | Y24: =+Y23/Y20 -> #DIV/0! | Z24: =+Z23/Z20 -> #DIV/0! | AA24: =+AA23/AA20 -> #DIV/0! | AB24: =+AB23/AB20 -> -0.24809067 | AC24: =+AC23/AC20 -> -0.24107384 | AD24: =+AD23/AD20 -> -0.17236067 | AE24: =+AE23/AE20 -> -0.18551043 | ... AM24: =+AM23/AM20 -> -0.45615752
G25: =+G10/G24 -> 0 | H25: =+H10/H24 -> 0 | I25: =+I10/I24 -> 0
W26: NCI | AB26: 1640478 | AC26: 2093012 | AD26: 4689963 | AE26: 5807124 | AF26: 3110888 | AG26: 806100 | AH26: 1596343 | AI26: 1291457 | AJ26: 1795617 | AK26: 1882762 | AL26: 2988117 | AM26: 1717380
W28: Net Profit Attributable to Equity Holders | X28: =+X20+X23-X26 -> 0 | Y28: =+Y20+Y23-Y26 -> 0 | Z28: =+Z20+Z23-Z26 -> 0 | AA28: =+AA20+AA23-AA26 -> 0 | AB28: =+AB20+AB23-AB26 -> 2787704 | AC28: =+AC20+AC23-AC26 -> 4533658 | AD28: =+AD20+AD23-AD26 -> 8763676 | AE28: =+AE20+AE23-AE26 -> 10488825 | ... AM28: =+AM20+AM23-AM26 -> 1401270
W29: NP Margin | X29: =+X28/X3 -> #DIV/0! | Y29: =+Y28/Y3 -> #DIV/0! | Z29: =+Z28/Z3 -> #DIV/0! | AA29: =+AA28/AA3 -> #DIV/0! | AB29: =+AB28/AB3 -> 0.035092757 | AC29: =+AC28/AC3 -> 0.049162584 | AD29: =+AD28/AD3 -> 0.091533326 | AE29: =+AE28/AE3 -> 0.084832695 | ... AM29: =+AM28/AM3 -> 0.012334295
W31: EPS | X31: =+X28/X46 -> 0 | Y31: =+Y28/Y46 -> 0 | Z31: =+Z28/Z46 -> 0 | AA31: =+AA28/AA46 -> 0 | AB31: =+AB28/AB46 -> 3.7169387 | AC31: =+AC28/AC46 -> 6.0448773 | AD31: =+AD28/AD46 -> 11.684901 | AE31: =+AE28/AE46 -> 13.9851 | ... AM31: =+AM28/AM46 -> 1.86836
W32: YoY% | AB32: =+AB31/X31-1 -> #DIV/0! | AC32: =+AC31/Y31-1 -> #DIV/0! | AD32: =+AD31/Z31-1 -> #DIV/0! | AE32: =+AE31/AA31-1 -> #DIV/0! | AF32: =+AF31/AB31-1 -> 0.45148445 | AG32: =+AG31/AC31-1 -> -0.99585544 | AH32: =+AH31/AD31-1 -> -0.79484397 | AI32: =+AI31/AE31-1 -> -0.9972056 | ... AM32: =+AM31/AI31-1 -> 46.808598
W33: QoQ% | Y33: =+Y31/X31-1 -> #DIV/0! | Z33: =+Z31/Y31-1 -> #DIV/0! | AA33: =+AA31/Z31-1 -> #DIV/0! | AB33: =+AB31/AA31-1 -> #DIV/0! | AC33: =+AC31/AB31-1 -> 0.62630538 | AD33: =+AD31/AC31-1 -> 0.93302538 | AE33: =+AE31/AD31-1 -> 0.19685221 | AF33: =+AF31/AE31-1 -> -0.61422667 | ... AM33: =+AM31/AL31-1 -> -0.70239143
W35: RoE | X35: =+X28*4/X40 -> #DIV/0! | Y35: =+Y28*4/Y40 -> #DIV/0! | Z35: =+Z28*4/Z40 -> #DIV/0! | AA35: =+AA28*4/AA40 -> #DIV/0! | AB35: =+AB28*4/AB40 -> 0.21425453 | AC35: =+AC28*4/AC40 -> 0.32121879 | AD35: =+AD28*4/AD40 -> 0.52017779 | AE35: =+AE28*4/AE40 -> 0.52936605 | ... AM35: =+AM28*4/AM40 -> 0.068676866 | AN35: =+AVERAGE(AB35:AL35) -> 0.20139277 | AO35: RoE
AN36: =AVERAGE(AB35:AL35)*AL48 -> 21.525663 | AO36: Normalized EPS
W37: Debt | AB37: =60934208+21429845+62967305 -> 145331358 | AC37: =60413662+65027148+23431134 -> 148871944 | AD37: =63540193+27568587+80825555 -> 171934335 | AE37: =63846265+31674899+97954786 -> 193475950 | AF37: =56843387+32805837+92681015 -> 182330239 | AG37: =57233464+32388188+81829452 -> 171451104 | AH37: =59158207+31573389+68964025 -> 159695621 | AI37: =62164305+29207430+68554899 -> 159926634 | AJ37: =57457192+28899860+80679267 -> 167036319 | AK37: =61487609+28962540+79151448 -> 169601597 | AL37: =56654168+27160079+88068606 -> 171882853 | AM37: =55828604+27717809+88502223 -> 172048636 | AN37: =X1/AN36 -> 4.4412104 | AO37: P/E
W38: Cash | AB38: =21886229+13358415+943388 -> 36188032 | AC38: =23740389+14596135+1754310 -> 40090834 | AD38: =27409656+19927939+1400423 -> 48738018 | AE38: =35634271+26973362+652085 -> 63259718 | AF38: =28932413+17836260+178766 -> 46947439 | AG38: =30688439+17193746+762280 -> 48644465 | AH38: =24177336+19780454+855239 -> 44813029 | AI38: =18384511+957877+29822112 -> 49164500 | AJ38: =26367731+24351233+888280 -> 51607244 | AK38: =30140311+27105430+2518057 -> 59763798 | AL38: =28175378+21356037+2176135 -> 51707550 | AM38: =2565859+19392228+27151110 -> 49109197
W39: Net Debt | X39: =+X37-X38 -> 0 | Y39: =+Y37-Y38 -> 0 | Z39: =+Z37-Z38 -> 0 | AA39: =+AA37-AA38 -> 0 | AB39: =+AB37-AB38 -> 109143326 | AC39: =+AC37-AC38 -> 108781110 | AD39: =+AD37-AD38 -> 123196317 | AE39: =+AE37-AE38 -> 130216232 | ... AM39: =+AM37-AM38 -> 122939439
W40: Equity | AB40: 52044715 | AC40: 56455701 | AD40: 67389851 | AE40: 79255743 | AF40: 82703608 | AG40: 83278330 | AH40: 78930304 | AI40: 77984220 | AJ40: 78272996 | AK40: 81119206 | AL40: 80162993 | AM40: 81615256
W42: Debt/Equity | X42: =+X37/X40 -> #DIV/0! | Y42: =+Y37/Y40 -> #DIV/0! | Z42: =+Z37/Z40 -> #DIV/0! | AA42: =+AA37/AA40 -> #DIV/0! | AB42: =+AB37/AB40 -> 2.7924326 | AC42: =+AC37/AC40 -> 2.6369692 | AD42: =+AD37/AD40 -> 2.5513387 | AE42: =+AE37/AE40 -> 2.44116 | ... AM42: =+AM37/AM40 -> 2.108045
W44: Average Exchange rate (income Statement) | X44: =+MGT!X42 -> 187.87665 | Y44: =+MGT!Y42 -> 187.90336 | Z44: =+MGT!Z42 -> 197.89852 | AA44: =+MGT!AA42 -> 201.88667 | AB44: =+MGT!AB42 -> 202.93333 | AC44: =+MGT!AC42 -> 203.00001 | AD44: =+MGT!AD42 -> 233.47823 | AE44: =+MGT!AE42 -> 364.27332 | ... AM44: =+MGT!AM42 -> 305.92999
W46: Number of shares | X46: 750000 | Y46: 750000 | Z46: 750000 | AA46: 750000 | AB46: 750000 | AC46: 750000 | AD46: 750000 | AE46: 750000 | AF46: 750000 | AG46: 750000 | AH46: 750000 | AI46: 750000 | AJ46: 750000 | AK46: 750000 | AL46: 750000 | AM46: 750000
W48: Net Asset Value per share | X48: =+X40/X46 -> 0 | Y48: =+Y40/Y46 -> 0 | Z48: =+Z40/Z46 -> 0 | AA48: =+AA40/AA46 -> 0 | AB48: =+AB40/AB46 -> 69.392953 | AC48: =+AC40/AC46 -> 75.274268 | AD48: =+AD40/AD46 -> 89.853135 | AE48: =+AE40/AE46 -> 105.67432 | ... AM48: =+AM40/AM46 -> 108.82034
W50: Cashflow from operations (in LKR 000') | Y50: =+Y54-X54 -> 0 | Z50: =+Z54-Y54 -> 0 | AA50: =+AA54 -> 0 | AB50: =+AB54-AA54 -> 0 | AC50: =+AC54-AB54 -> 0 | AD50: =+AD54-AC54 -> 0 | AE50: =+AE54 -> 0 | AF50: =+AF54-AE54 -> 0 | AG50: =+AG54-AF54 -> 36652990 | AH50: =+AH54-AG54 -> -36652990 | AI50: =+AI54 -> 0 | AJ50: =+AJ54-AI54 -> 0 | AK50: =+AK54-AJ54 -> 25143939 | AL50: =+AL54-AK54 -> 5266482 | AM50: =+AM54-AL54 -> -22300173
W51: Capex | Y51: =+Y55-X55 -> 0 | Z51: =+Z55-Y55 -> 0 | AA51: =+AA55 -> 0 | AB51: =+AB55-AA55 -> 0 | AC51: =+AC55-AB55 -> 0 | AD51: =+AD55-AC55 -> 0 | AE51: =+AE55 -> 0 | AF51: =+AF55-AE55 -> 0 | AG51: =+AG55-AF55 -> -11331392 | AH51: =+AH55-AG55 -> 11331392 | AI51: =+AI55 -> 0 | AJ51: =+AJ55-AI55 -> 0 | AK51: =+AK55-AJ55 -> -13729920 | AL51: =+AL55-AK55 -> -6189549 | AM51: =+AM55-AL55 -> 17030378
W52: FCF (in LKR 000') | Y52: =+Y50+Y51 -> 0 | Z52: =+Z50+Z51 -> 0 | AA52: =+AA50+AA51 -> 0 | AB52: =+AB50+AB51 -> 0 | AC52: =+AC50+AC51 -> 0 | AD52: =+AD50+AD51 -> 0 | AE52: =+AE50+AE51 -> 0 | AF52: =+AF50+AF51 -> 0 | ... AM52: =+AM50+AM51 -> -5269795
W54: Cashflow from operations (in LKR 000') | AG54: 36652990 | AK54: 25143939 | AL54: 30410421 | AM54: 8110248
W55: Capex | AG55: -11331392 | AK55: -13729920 | AL55: -19919469 | AM55: -2889091
W56: FCF (in LKR 000') | X56: =+X54+X55 -> 0 | Y56: =+Y54+Y55 -> 0 | Z56: =+Z54+Z55 -> 0 | AA56: =+AA54+AA55 -> 0 | AB56: =+AB54+AB55 -> 0 | AC56: =+AC54+AC55 -> 0 | AD56: =+AD54+AD55 -> 0 | AE56: =+AE54+AE55 -> 0 | ... AM56: =+AM54+AM55 -> 5221157
W58: Segments
W59: Brushware
W60: Revenue
W61: YoY% | AD61: =+AD60/Z60-1 -> #DIV/0! | AE61: =+AE60/AA60-1 -> #DIV/0! | AF61: =+AF60/AB60-1 -> #DIV/0! | AG61: =+AG60/AC60-1 -> #DIV/0! | AH61: =+AH60/AD60-1 -> #DIV/0! | AI61: =+AI60/AE60-1 -> #DIV/0! | AJ61: =+AJ60/AF60-1 -> #DIV/0! | AK61: =+AK60/AG60-1 -> #DIV/0! | ... AM61: =+AM60/AI60-1 -> #DIV/0!
W62: QoQ% | AA62: =+AA60/Z60-1 -> #DIV/0! | AB62: =+AB60/AA60-1 -> #DIV/0! | AC62: =+AC60/AB60-1 -> #DIV/0! | AD62: =+AD60/AC60-1 -> #DIV/0! | AE62: =+AE60/AD60-1 -> #DIV/0! | AF62: =+AF60/AE60-1 -> #DIV/0! | AG62: =+AG60/AF60-1 -> #DIV/0! | AH62: =+AH60/AG60-1 -> #DIV/0! | ... AM62: =+AM60/AL60-1 -> #DIV/0!
W63: Gross profit
W64: margin% | Z64: =+Z63/Z60 -> #DIV/0! | AA64: =+AA63/AA60 -> #DIV/0! | AB64: =+AB63/AB60 -> #DIV/0! | AC64: =+AC63/AC60 -> #DIV/0! | AD64: =+AD63/AD60 -> #DIV/0! | AE64: =+AE63/AE60 -> #DIV/0! | AF64: =+AF63/AF60 -> #DIV/0! | AG64: =+AG63/AG60 -> #DIV/0! | ... AM64: =+AM63/AM60 -> #DIV/0!
W65: PBT
W66: margin% | Z66: =+Z65/Z60 -> #DIV/0! | AA66: =+AA65/AA60 -> #DIV/0! | AB66: =+AB65/AB60 -> #DIV/0! | AC66: =+AC65/AC60 -> #DIV/0! | AD66: =+AD65/AD60 -> #DIV/0! | AE66: =+AE65/AE60 -> #DIV/0! | AF66: =+AF65/AF60 -> #DIV/0! | AG66: =+AG65/AG60 -> #DIV/0! | ... AM66: =+AM65/AM60 -> #DIV/0!
W68: Filament and Yarn
W69: Revenue
W70: YoY% | AD70: =+AD69/Z69-1 -> #DIV/0! | AE70: =+AE69/AA69-1 -> #DIV/0! | AF70: =+AF69/AB69-1 -> #DIV/0! | AG70: =+AG69/AC69-1 -> #DIV/0! | AH70: =+AH69/AD69-1 -> #DIV/0! | AI70: =+AI69/AE69-1 -> #DIV/0! | AJ70: =+AJ69/AF69-1 -> #DIV/0! | AK70: =+AK69/AG69-1 -> #DIV/0! | ... AM70: =+AM69/AI69-1 -> #DIV/0!
W71: QoQ% | AA71: =+AA69/Z69-1 -> #DIV/0! | AB71: =+AB69/AA69-1 -> #DIV/0! | AC71: =+AC69/AB69-1 -> #DIV/0! | AD71: =+AD69/AC69-1 -> #DIV/0! | AE71: =+AE69/AD69-1 -> #DIV/0! | AF71: =+AF69/AE69-1 -> #DIV/0! | AG71: =+AG69/AF69-1 -> #DIV/0! | AH71: =+AH69/AG69-1 -> #DIV/0! | ... AM71: =+AM69/AL69-1 -> #DIV/0!
W72: Gross profit
W73: margin% | Z73: =+Z72/Z69 -> #DIV/0! | AA73: =+AA72/AA69 -> #DIV/0! | AB73: =+AB72/AB69 -> #DIV/0! | AC73: =+AC72/AC69 -> #DIV/0! | AD73: =+AD72/AD69 -> #DIV/0! | AE73: =+AE72/AE69 -> #DIV/0! | AF73: =+AF72/AF69 -> #DIV/0! | AG73: =+AG72/AG69 -> #DIV/0! | ... AM73: =+AM72/AM69 -> #DIV/0!
W74: PBT
W75: margin% | Z75: =+Z74/Z69 -> #DIV/0! | AA75: =+AA74/AA69 -> #DIV/0! | AB75: =+AB74/AB69 -> #DIV/0! | AC75: =+AC74/AC69 -> #DIV/0! | AD75: =+AD74/AD69 -> #DIV/0! | AE75: =+AE74/AE69 -> #DIV/0! | AF75: =+AF74/AF69 -> #DIV/0! | AG75: =+AG74/AG69 -> #DIV/0! | ... AM75: =+AM74/AM69 -> #DIV/0!

Sheet HAYC
W1: Stock Price | X1: =+'Valuation Sheet'!C7 -> 79
B2: TJL - Rs mn | C2: FY16 | D2: FY17 | E2: FY18 | F2: FY19 | G2: FY20 | H2: FY21 | I2: FY22 | J2: CAGR/AVG | M2: MPS | N2: ='[1]LT Portfolio'!I294 -> SELL | P2: AVG | Q2: =J14*J21 -> 34.398438 | W2: HAYC | X2: 2Q21 | Y2: 3Q21 | Z2: 4Q21 | AA2: 1Q22 | AB2: 2Q22 | AC2: 3Q22 | AD2: 4Q22 | AE2: 1Q23 | AF2: 2Q23 | AG2: 3Q23 | AH2: 4Q23 | AI2: 1Q24 | AJ2: 2Q24 | AK2: 3Q24 | AL2: 4Q24 | AM2: 1Q25 | AO2: =+W2 -> HAYC | AP2: FY24E | AU2: FY25E | AZ2: FY26E
B3: Net Revenue | C3: 17820.179 | D3: 22137.641 | E3: 24647.488 | F3: 31746.592 | G3: 33276.977 | H3: 31780.287 | I3: 49587.964 | M3: P/E | N3: ='[1]LT Portfolio'!W294 -> 0 | W3: Revenue (LKR 000) | AB3: 7453002 | AC3: 8437660 | AD3: 9873278 | AE3: 15041682 | AF3: 18344396 | AG3: 14706816 | AH3: 12850362 | AI3: 10215398 | AJ3: 11391110 | AK3: 10700624 | AL3: 10872073 | AM3: 10059288 | AP3: Revenue | AQ3: EBIT | AR3: NP | AS3: EPS | AT3: DPS | AU3: Revenue | AV3: EBIT | AW3: NP | AX3: EPS | AY3: DPS | AZ3: Revenue | BA3: EBIT | BB3: NP | BC3: EPS | BD3: DPS
B4: Revenue Growth | D4: =(D3/C3-1)*100 -> 24.227938 | E4: =(E3/D3-1)*100 -> 11.337464 | F4: =(F3/E3-1)*100 -> 28.802546 | G4: =(G3/F3-1)*100 -> 4.8206277 | H4: =(H3/G3-1)*100 -> -4.4976742 | I4: =(I3/H3-1)*100 -> 56.03372 | J4: =((I3/D3)^(1/5)-1)*100 -> 17.503009 | W4: YoY% | AB4: =+AB3/X3-1 -> #DIV/0! | AC4: =+AC3/Y3-1 -> #DIV/0! | AD4: =+AD3/Z3-1 -> #DIV/0! | AE4: =+AE3/AA3-1 -> #DIV/0! | AF4: =+AF3/AB3-1 -> 1.4613432 | AG4: =+AG3/AC3-1 -> 0.74299699 | AH4: =+AH3/AD3-1 -> 0.30152944 | AI4: =+AI3/AE3-1 -> -0.32086066 | ... AM4: =+AM3/AI3-1 -> -0.015281832 | AO4: CT CLSA
B5: Gross Profit | C5: 2994.862 | D5: 3075.715 | E5: 2911.199 | F5: 3686.058 | G5: 4229.042 | H5: 3789.959 | I5: 4577.641 | M5: 2Q21 | N5: =202.575/415.481776 -> 0.48756651 | W5: QoQ% | Y5: =+Y3/X3-1 -> #DIV/0! | Z5: =+Z3/Y3-1 -> #DIV/0! | AA5: =+AA3/Z3-1 -> #DIV/0! | AB5: =+AB3/AA3-1 -> #DIV/0! | AC5: =+AC3/AB3-1 -> 0.13211562 | AD5: =+AD3/AC3-1 -> 0.17014409 | AE5: =+AE3/AD3-1 -> 0.52347397 | AF5: =+AF3/AE3-1 -> 0.21957079 | ... AM5: =+AM3/AL3-1 -> -0.074758972 | AO5: Capital Alliance | AX5: 7.64 | AY5: 3.06 | BC5: 8.41 | BD5: 3.36
B6: GPM | C6: =C5/C$3*100 -> 16.806015 | D6: =D5/D$3*100 -> 13.893599 | E6: =E5/E$3*100 -> 11.811342 | F6: =F5/F$3*100 -> 11.610878 | G6: =G5/G$3*100 -> 12.708612 | H6: =H5/H$3*100 -> 11.925503 | I6: =I5/I$3*100 -> 9.231355 | J6: =AVERAGE(D6:I6) -> 11.863548 | M6: 3Q21 | N6: =261.001/415.481776 -> 0.6281888 | AO6: Asia Securities | AP6: 66126 | AQ6: 6855 | AR6: 3815 | AS6: 9.18 | AT6: 2.75
B7: EBIT | C7: 2167.608 | D7: 1992.405 | E7: 1810.842 | F7: 2344.649 | G7: 2728.431 | H7: 2441.401 | I7: 2573.103 | M7: 4Q21 | N7: ='[1]LT Portfolio'!P294 -> 0 | W7: Revenue (in USD) | AB7: =+AB3/AB45 -> 36726.358 | AC7: =+AC3/AC45 -> 41564.826 | AD7: =+AD3/AD45 -> 42287.788 | AE7: =+AE3/AE45 -> 41292.297 | AF7: =+AF3/AF45 -> 49734.129 | AG7: =+AG3/AG45 -> 39558.331 | AH7: =+AH3/AH45 -> 35926.447 | AI7: =+AI3/AI45 -> 32280.559 | ... AM7: =+AM3/AM45 -> 32881.013 | AO7: First Capital | AP7: 65198 | AQ7: 5724 | AR7: 3356 | AS7: 8.1 | AT7: 2.4 | AU7: 57931 | AV7: 6428 | AW7: 4095 | AX7: 9.9 | AY7: 3 | AZ7: 66531 | BA7: 7036 | BB7: 4744 | BC7: 11.4 | BD7: 3.4
B8: EBIT Margin | C8: =C7/C$3*100 -> 12.163784 | D8: =D7/D$3*100 -> 9.0000782 | E8: =E7/E$3*100 -> 7.3469637 | F8: =F7/F$3*100 -> 7.385514 | G8: =G7/G$3*100 -> 8.1991552 | H8: =H7/H$3*100 -> 7.6821238 | I8: =I7/I$3*100 -> 5.1889668 | J8: =AVERAGE(D8:I8) -> 7.4671336 | M8: 1Q22 | N8: ='[1]LT Portfolio'!Q294 -> 0 | W8: YoY% | AB8: =+AB7/X7-1 -> #DIV/0! | AC8: =+AC7/Y7-1 -> #DIV/0! | AD8: =+AD7/Z7-1 -> #DIV/0! | AE8: =+AE7/AA7-1 -> #DIV/0! | AF8: =+AF7/AB7-1 -> 0.35418082 | AG8: =+AG7/AC7-1 -> -0.048273869 | AH8: =+AH7/AD7-1 -> -0.15042974 | AI8: =+AI7/AE7-1 -> -0.21824258 | ... AM8: =+AM7/AI7-1 -> 0.018601085 | AO8: Acuity Research | AX8: 5.56 | AY8: 2 | BC8: 6.15 | BD8: 2
B9: PBT | C9: 2228.947 | D9: 2011.37 | E9: 1817.716 | F9: 2257.062 | G9: 2811.964 | H9: 2599.336 | I9: 2863.72 | M9: 2Q22 | N9: ='[1]LT Portfolio'!R294 -> 0 | O9: =N9/N5-1 -> -1 | W9: QoQ% | Y9: =+Y7/X7-1 -> #DIV/0! | Z9: =+Z7/Y7-1 -> #DIV/0! | AA9: =+AA7/Z7-1 -> #DIV/0! | AB9: =+AB7/AA7-1 -> #DIV/0! | AC9: =+AC7/AB7-1 -> 0.13174375 | AD9: =+AD7/AC7-1 -> 0.017393591 | AE9: =+AE7/AD7-1 -> -0.023540868 | AF9: =+AF7/AE7-1 -> 0.20444087 | ... AM9: =+AM7/AL7-1 -> -0.059278708 | AO9: Asia Capital | AP9: 61649 | AQ9: 4200 | AR9: 2600 | AS9: 6.3
B10: Net Profit | C10: 2170.667 | D10: 1959.175 | E10: 1596.114 | F10: 1858.717 | G10: 2383.784 | H10: 2139.597 | I10: 2531.25 | J10: =((I10/D10)^(1/5)-1)*100 -> 5.2573331 | M10: 3Q22 | N10: ='[1]LT Portfolio'!S294 -> 0 | O10: =N10/N6-1 -> -1 | AO10: JKSB | AP10: 57649 | AQ10: 4507 | AR10: 2529 | AS10: 6.09 | AU10: 53877 | AV10: 5164 | AW10: 3005 | AX10: 7.23 | AY10: 2.5 | AZ10: 58741 | BA10: 5618 | BB10: 3061 | BC10: 7.37 | BD10: 2.6
B11: NP Margin | C11: =C10/C$3*100 -> 12.180949 | D11: =D10/D$3*100 -> 8.8499719 | E11: =E10/E$3*100 -> 6.4757674 | F11: =F10/F$3*100 -> 5.8548552 | G11: =G10/G$3*100 -> 7.1634632 | H11: =H10/H$3*100 -> 6.7324659 | I11: =I10/I$3*100 -> 5.1045653 | J11: =AVERAGE(D11:I11) -> 6.6968482 | M11: 4Q22 | N11: ='[1]LT Portfolio'!T294 -> 0 | O11: =N11/N7-1 -> #DIV/0! | W11: Gross Profit | AB11: 1682537 | AC11: 2037774 | AD11: 1922278 | AE11: 4167624 | AF11: 3902906 | AG11: 3754056 | AH11: 3054311 | AI11: 2815072 | AJ11: 3167845 | AK11: 3542951 | AL11: 3742962 | AM11: 2751476 | AO11: Consensus | AP11: =+AVERAGE(AP4:AP10) -> 62655.5 | AQ11: =+AVERAGE(AQ4:AQ10) -> 5321.5 | AR11: =+AVERAGE(AR4:AR10) -> 3075 | AS11: =+AVERAGE(AS4:AS10) -> 7.4175 | AT11: =+AVERAGE(AT4:AT10) -> 2.575 | AU11: =+AVERAGE(AU4:AU10) -> 55904 | AV11: =+AVERAGE(AV4:AV10) -> 5796 | AW11: =+AVERAGE(AW4:AW10) -> 3550 | ... BD11: =+AVERAGE(BD4:BD10) -> 2.84
B12: NP Growth | D12: =(D10/C10-1)*100 -> -9.7431803 | E12: =(E10/D10-1)*100 -> -18.531321 | F12: =(F10/E10-1)*100 -> 16.452647 | G12: =(G10/F10-1)*100 -> 28.248894 | H12: =(H10/G10-1)*100 -> -10.243671 | I12: =(I10/H10-1)*100 -> 18.304989 | J12: =AVERAGE(D12:I12) -> 4.081393 | S12: 1Q22 | T12: 2Q22 | W12: GPM% | X12: =+X11/X3 -> #DIV/0! | Y12: =+Y11/Y3 -> #DIV/0! | Z12: =+Z11/Z3 -> #DIV/0! | AA12: =+AA11/AA3 -> #DIV/0! | AB12: =+AB11/AB3 -> 0.22575292 | AC12: =+AC11/AC3 -> 0.24150938 | AD12: =+AD11/AD3 -> 0.19469501 | AE12: =+AE11/AE3 -> 0.27707167 | ... AM12: =+AM11/AM3 -> 0.27352592 | AT12: DY | AY12: DY | BD12: DY
M13: TTM | N13: =SUM(N8:N11) -> 0 | Q13: =N13*J21 -> 0 | S13: 19.109574 | T13: 18.873653 | AO13: Leading P/E | AS13: =+$X$1/AS11 -> 10.650489 | AT13: =+AT11/$X$1 -> 0.032594937 | AX13: =+$X$1/AX11 -> 10.418727 | AY13: =+AY11/$X$1 -> 0.033417722 | BC13: =+$X$1/BC11 -> 9.4809481 | BD13: =+BD11/$X$1 -> 0.035949367
B14: EPS | C14: 3.24 | D14: 2.81 | E14: 2.28 | F14: 2.65 | G14: 3.4 | H14: 3.04 | I14: 3.54 | J14: =AVERAGE(D14:I14) -> 2.9533333 | M14: P/E | N14: =N2/N13 -> #VALUE! | Q14: =Q13/N2-1 -> #VALUE! | S14: =S13/N2-1 -> #VALUE! | T14: =T13/N2-1 -> #VALUE! | W14: EBIT | AB14: 772424 | AC14: 1033948 | AD14: 560507 | AE14: 2578924 | AF14: 2418814 | AG14: 2035111 | AH14: 1241434 | AI14: 1287570 | AJ14: 1444821 | AK14: 1941904 | AL14: 1846802 | AM14: 1151716
B15: DPS | C15: =1+0.6 -> 1.6 | D15: =1+1.25 -> 2.25 | E15: =0.9+0.7 -> 1.6 | F15: =1.1+0.85 -> 1.95 | G15: 1.3 | H15: =1.65+1.15 -> 2.8 | I15: =1.5+0.85 -> 2.35 | W15: EBIT margin % | X15: =+X14/X3 -> #DIV/0! | Y15: =+Y14/Y3 -> #DIV/0! | Z15: =+Z14/Z3 -> #DIV/0! | AA15: =+AA14/AA3 -> #DIV/0! | AB15: =+AB14/AB3 -> 0.10363931 | AC15: =+AC14/AC3 -> 0.12253966 | AD15: =+AD14/AD3 -> 0.056770102 | AE15: =+AE14/AE3 -> 0.17145184 | ... AM15: =+AM14/AM3 -> 0.1144928
B16: MPS | C16: 31.7 | D16: 37 | E16: 31.9 | F16: 30.4 | G16: 23.3 | H16: 40 | I16: 39.8 | J16: =((I16/D16)^(1/5)-1)*100 -> 1.4696751 | AR16: 52
B17: BVPS | C17: 14.6 | D17: 16 | E17: 16.7 | F17: 19.8 | G17: 22.3 | H17: 25 | I17: 39.4 | J17: =((I17/D17)^(1/6)-1)*100 -> 16.20622 | W17: Net Finance Income/Cost | AB17: -25802 | AC17: -90764 | AD17: 1707527 | AE17: 1114210 | AF17: -466735 | AG17: -346641 | AH17: -319502 | AI17: -224667 | AJ17: =318561-240079 -> 78482 | AK17: 39412 | AL17: -292244 | AM17: 64552 | AP17: =SUM(AI3:AL3) -> 43179205
B18: ROE | C18: =C14/AVERAGE(B17:C17)*100 -> 22.191781 | D18: =D14/AVERAGE(C17:D17)*100 -> 18.366013 | E18: =E14/AVERAGE(D17:E17)*100 -> 13.944954 | F18: =F14/AVERAGE(E17:F17)*100 -> 14.520548 | G18: =G14/AVERAGE(F17:G17)*100 -> 16.152019 | H18: =H14/AVERAGE(G17:H17)*100 -> 12.854123 | I18: =I14/AVERAGE(H17:I17)*100 -> 10.993789 | J18: =AVERAGE(D18:I18) -> 14.471908 | M18: MGT | W18: As a % of EBIT | X18: =+X17/X14 -> #DIV/0! | Y18: =+Y17/Y14 -> #DIV/0! | Z18: =+Z17/Z14 -> #DIV/0! | AA18: =+AA17/AA14 -> #DIV/0! | AB18: =+AB17/AB14 -> -0.033403934 | AC18: =+AC17/AC14 -> -0.087783912 | AD18: =+AD17/AD14 -> 3.0463973 | AE18: =+AE17/AE14 -> 0.43204453 | ... AM18: =+AM17/AM14 -> 0.05604854
B19: DY | C19: =C15/C16*100 -> 5.0473186 | D19: =D15/D16*100 -> 6.0810811 | E19: =E15/E16*100 -> 5.015674 | F19: =F15/F16*100 -> 6.4144737 | G19: =G15/G16*100 -> 5.5793991 | H19: =H15/H16*100 -> 7 | I19: =I15/I16*100 -> 5.9045226 | J19: =AVERAGE(D19:I19) -> 5.9991918
B20: Dividend Payout | C20: =C15/C14*100 -> 49.382716 | D20: =D15/D14*100 -> 80.071174 | E20: =E15/E14*100 -> 70.175439 | F20: =F15/F14*100 -> 73.584906 | G20: =G15/G14*100 -> 38.235294 | H20: =H15/H14*100 -> 92.105263 | I20: =I15/I14*100 -> 66.384181 | J20: =AVERAGE(D20:I20) -> 70.092709 | M20: YoY Growth | N20: =N13/H14-1 -> -1 | W20: PBT | AB20: 745130 | AC20: 941678 | AD20: 2251325 | AE20: 3685067 | AF20: 1950821 | AG20: 1683580 | AH20: 938564 | AI20: 1060275 | AJ20: 1519245 | AK20: 1976669 | AL20: 1557065 | AM20: 1212173
B21: P/E | C21: =C16/C14 -> 9.7839506 | D21: =D16/D14 -> 13.16726 | E21: =E16/E14 -> 13.991228 | F21: =F16/F14 -> 11.471698 | G21: =G16/G14 -> 6.8529412 | H21: =H16/H14 -> 13.157895 | I21: =I16/I14 -> 11.242938 | J21: =AVERAGE(D21:I21) -> 11.647327 | W21: PBT Margin% | X21: =+X20/X3 -> #DIV/0! | Y21: =+Y20/Y3 -> #DIV/0! | Z21: =+Z20/Z3 -> #DIV/0! | AA21: =+AA20/AA3 -> #DIV/0! | AB21: =+AB20/AB3 -> 0.099977164 | AC21: =+AC20/AC3 -> 0.11160417 | AD21: =+AD20/AD3 -> 0.22802204 | AE21: =+AE20/AE3 -> 0.24499035 | ... AM21: =+AM20/AM3 -> 0.12050286
B22: P/B | C22: =C16/C17 -> 2.1712329 | D22: =D16/D17 -> 2.3125 | E22: =E16/E17 -> 1.9101796 | F22: =F16/F17 -> 1.5353535 | G22: =G16/G17 -> 1.044843 | H22: =H16/H17 -> 1.6 | I22: =I16/I17 -> 1.0101523 | J22: =AVERAGE(D22:I22) -> 1.5688381
W23: Taxes | AB23: -133318 | AC23: -165921 | AD23: -451511 | AE23: -661558 | AF23: -531523 | AG23: -505211 | AH23: -54252 | AI23: -294582 | AJ23: -454443 | AK23: -520316 | AL23: -538284 | AM23: -355398
G24: 701.95658 | H24: 709.32254 | I24: 716.73997 | W24: ETR% | X24: =+X23/X20 -> #DIV/0! | Y24: =+Y23/Y20 -> #DIV/0! | Z24: =+Z23/Z20 -> #DIV/0! | AA24: =+AA23/AA20 -> #DIV/0! | AB24: =+AB23/AB20 -> -0.17891911 | AC24: =+AC23/AC20 -> -0.17619717 | AD24: =+AD23/AD20 -> -0.20055345 | AE24: =+AE23/AE20 -> -0.17952401 | ... AM24: =+AM23/AM20 -> -0.29319082
G25: =+G10/G24 -> 3.3959137 | H25: =+H10/H24 -> 3.016395 | I25: =+I10/I24 -> 3.5316155
W26: NCI | AB26: 78541 | AC26: 186816 | AD26: 76460 | AE26: 133319 | AF26: 218196 | AG26: 267348 | AH26: 63465 | AI26: 134517 | AJ26: 105696 | AK26: 176373 | AL26: 145114 | AM26: 114304
W29: Net Profit Attributable to Equity Holders | X29: =+X20+X23-X26 -> 0 | Y29: =+Y20+Y23-Y26 -> 0 | Z29: =+Z20+Z23-Z26 -> 0 | AA29: =+AA20+AA23-AA26 -> 0 | AB29: =+AB20+AB23-AB26 -> 533271 | AC29: =+AC20+AC23-AC26 -> 588941 | AD29: =+AD20+AD23-AD26 -> 1723354 | AE29: =+AE20+AE23-AE26 -> 2890190 | ... AM29: =+AM20+AM23-AM26 -> 742471
W30: NP Margin | X30: =+X29/X3 -> #DIV/0! | Y30: =+Y29/Y3 -> #DIV/0! | Z30: =+Z29/Z3 -> #DIV/0! | AA30: =+AA29/AA3 -> #DIV/0! | AB30: =+AB29/AB3 -> 0.071551168 | AC30: =+AC29/AC3 -> 0.069799091 | AD30: =+AD29/AD3 -> 0.1745473 | AE30: =+AE29/AE3 -> 0.1921454 | ... AM30: =+AM29/AM3 -> 0.073809498
W32: EPS | X32: =+X29/X47 -> #DIV/0! | Y32: =+Y29/Y47 -> #DIV/0! | Z32: =+Z29/Z47 -> #DIV/0! | AA32: =+AA29/AA47 -> #DIV/0! | AB32: =+AB29/AB47 -> 1.7947774 | AC32: =+AC29/AC47 -> 1.9821404 | AD32: =+AD29/AD47 -> 5.800122 | AE32: =+AE29/AE47 -> 9.7272265 | ... AM32: =+AM29/AM47 -> 2.4988612
W33: YoY% | AB33: =+AB32/X32-1 -> #DIV/0! | AC33: =+AC32/Y32-1 -> #DIV/0! | AD33: =+AD32/Z32-1 -> #DIV/0! | AE33: =+AE32/AA32-1 -> #DIV/0! | AF33: =+AF32/AB32-1 -> 1.2523295 | AG33: =+AG32/AC32-1 -> 0.54687991 | AH33: =+AH32/AD32-1 -> -0.52369217 | AI33: =+AI32/AE32-1 -> -0.78161436 | ... AM33: =+AM32/AI32-1 -> 0.17632958
W34: QoQ% | Y34: =+Y32/X32-1 -> #DIV/0! | Z34: =+Z32/Y32-1 -> #DIV/0! | AA34: =+AA32/Z32-1 -> #DIV/0! | AB34: =+AB32/AA32-1 -> #DIV/0! | AC34: =+AC32/AB32-1 -> 0.10439345 | AD34: =+AD32/AC32-1 -> 1.9261912 | AE34: =+AE32/AD32-1 -> 0.67707273 | AF34: =+AF32/AE32-1 -> -0.58442109 | ... AM34: =+AM32/AL32-1 -> -0.15016705
W36: RoE | X36: =+X29*4/X40 -> #DIV/0! | Y36: =+Y29*4/Y40 -> #DIV/0! | Z36: =+Z29*4/Z41 -> #DIV/0! | AA36: =+AA29*4/AA41 -> #DIV/0! | AB36: =+AB29*4/AB41 -> 0.14817176 | AC36: =+AC29*4/AC41 -> 0.16270591 | AD36: =+AD29*4/AD41 -> 0.37934391 | AE36: =+AE29*4/AE41 -> 0.53495963 | AF36: =+AF29*4/AF41 -> 0.2138527 | AG36: =+AG29*4/AG41 -> 0.16180892 | ... AM36: =+AM29*4/AM41 -> 0.12467499 | AN36: =+AVERAGE(AB36:AL36) -> 0.21881837 | AO36: RoE
AN37: =AVERAGE(AB36:AL36)*AL49 -> 16.868556 | AO37: Normalized EPS
W38: Debt | AB38: =358013+83471+5583087+67875+1736316 -> 7828762 | AC38: =698240+73203+7230602+62878+1289325 -> 9354248 | AD38: =677152+54051+10328363+59361+2186028 -> 13304955 | AE38: =637012+42123+14217002+52157+2567743 -> 17516037 | AF38: =572903+27765+13294546+51171+2301054 -> 16247439 | AG38: =168273+15081+8508323+51498+2052937 -> 10796112 | AH38: =140194+206177+6779510+86718+1635815 -> 8848414 | AI38: =526915+176595+5412054+73532+1732039 -> 7921135 | AJ38: =440704+176027+3733284+62773+1772295 -> 6185083 | AK38: =353309+183583+3376197+53932+1987544 -> 5954565 | AL38: =253719+416518+4122052+85960+2379820 -> 7258069 | AM38: =462060+407639+3559896+77676+2416349 -> 6923620 | AN38: =+X1/AN37 -> 4.6832699 | AO38: P/E
W39: Cash | AB39: 2106011 | AC39: 2196250 | AD39: 3117724 | AE39: 5959056 | AF39: 6026776 | AG39: 5011415 | AH39: 5072892 | AI39: 6111762 | AJ39: =5553474+1140948 -> 6694422 | AK39: 6948651 | AL39: 6722126 | AM39: 5733475
W40: Net Debt | X40: =+X38-X39 -> 0 | Y40: =+Y38-Y39 -> 0 | Z40: =+Z38-Z39 -> 0 | AA40: =+AA38-AA39 -> 0 | AB40: =+AB38-AB39 -> 5722751 | AC40: =+AC38-AC39 -> 7157998 | AD40: =+AD38-AD39 -> 10187231 | AE40: =+AE38-AE39 -> 11556981 | ... AM40: =+AM38-AM39 -> 1190145 | AN40: Dividend Payout
W41: Equity | AB41: 14396023 | AC41: 14478663 | AD41: 18171943 | AE41: 21610528 | AF41: 22465968 | AG41: 22520909 | AH41: 22141821 | AI41: 21848689 | AJ41: 22537492 | AK41: 23323216 | AL41: 22905063 | AM41: 23821008 | AN41: =7/+SUM(AI32:AL32) -> 0.55553037
W43: Debt/Equity | X43: =+X38/X41 -> #DIV/0! | Y43: =+Y38/Y41 -> #DIV/0! | Z43: =+Z38/Z41 -> #DIV/0! | AA43: =+AA38/AA41 -> #DIV/0! | AB43: =+AB38/AB41 -> 0.54381422 | AC43: =+AC38/AC41 -> 0.64607126 | AD43: =+AD38/AD41 -> 0.73217019 | AE43: =+AE38/AE41 -> 0.81053258 | ... AM43: =+AM38/AM41 -> 0.29065185
W45: Average Exchange rate (income Statement) | X45: =+MGT!X42 -> 187.87665 | Y45: =+MGT!Y42 -> 187.90336 | Z45: =+MGT!Z42 -> 197.89852 | AA45: =+MGT!AA42 -> 201.88667 | AB45: =+MGT!AB42 -> 202.93333 | AC45: =+MGT!AC42 -> 203.00001 | AD45: =+MGT!AD42 -> 233.47823 | AE45: =+MGT!AE42 -> 364.27332 | ... AM45: =+MGT!AM42 -> 305.92999
W47: Number of shares | AB47: 297123.75 | AC47: 297123.75 | AD47: 297123.75 | AE47: 297123.75 | AF47: 297123.75 | AG47: 297123.75 | AH47: 297123.75 | AI47: 297123.75 | AJ47: 297123.75 | AK47: 297123.75 | AL47: 297123.75 | AM47: 297123.75
W49: Net Asset Value per share | X49: =+X41/X47 -> #DIV/0! | Y49: =+Y41/Y47 -> #DIV/0! | Z49: =+Z41/Z47 -> #DIV/0! | AA49: =+AA41/AA47 -> #DIV/0! | AB49: =+AB41/AB47 -> 48.45127 | AC49: =+AC41/AC47 -> 48.729403 | AD49: =+AD41/AD47 -> 61.15951 | AE49: =+AE41/AE47 -> 72.732415 | ... AM49: =+AM41/AM47 -> 80.172009
W51: Cashflow from operations (in LKR 000') | Y51: =+Y55-X55 -> 0 | Z51: =+Z55-Y55 -> 0 | AA51: =+AA55 -> 0 | AB51: =+AB55-AA55 -> -498225 | AC51: =+AC55-AB55 -> -1253815 | AD51: =+AD55-AC55 -> -1062430 | AE51: =+AE55 -> -308439 | AF51: =+AF55-AE55 -> 1360936 | AG51: =+AG55-AF55 -> 5594265 | AH51: =+AH55-AG55 -> 3475192 | AI51: =+AI55 -> 2260578 | AJ51: =+AJ55-AI55 -> 1716512 | AK51: =+AK55-AJ55 -> 3086969 | AL51: =+AL55-AK55 -> 812775 | AM51: =+AM55-AL55 -> -7671278
W52: Capex | Y52: =+Y56-X56 -> 0 | Z52: =+Z56-Y56 -> 0 | AA52: =+AA56 -> 0 | AB52: =+AB56-AA56 -> -768817 | AC52: =+AC56-AB56 -> -429119 | AD52: =+AD56-AC56 -> -479794 | AE52: =+AE56 -> -445487 | AF52: =+AF56-AE56 -> -302317 | AG52: =+AG56-AF56 -> -638316 | AH52: =+AH56-AG56 -> -521169 | AI52: =+AI56 -> -273771 | AJ52: =+AJ56-AI56 -> -261080 | AK52: =+AK56-AJ56 -> -733715 | AL52: =+AL56-AK56 -> -866221 | AM52: =+AM56-AL56 -> 1494117
W53: FCF (in LKR 000') | Y53: =+Y51+Y52 -> 0 | Z53: =+Z51+Z52 -> 0 | AA53: =+AA51+AA52 -> 0 | AB53: =+AB51+AB52 -> -1267042 | AC53: =+AC51+AC52 -> -1682934 | AD53: =+AD51+AD52 -> -1542224 | AE53: =+AE51+AE52 -> -753926 | AF53: =+AF51+AF52 -> 1058619 | ... AM53: =+AM51+AM52 -> -6177161
W55: Cashflow from operations (in LKR 000') | AB55: -498225 | AC55: -1752040 | AD55: -2814470 | AE55: -308439 | AF55: 1052497 | AG55: 6646762 | AH55: 10121954 | AI55: 2260578 | AJ55: 3977090 | AK55: 7064059 | AL55: 7876834 | AM55: 205556
W56: Capex | AB56: -768817 | AC56: -1197936 | AD56: -1677730 | AE56: -445487 | AF56: -747804 | AG56: -1386120 | AH56: -1907289 | AI56: -273771 | AJ56: -534851 | AK56: -1268566 | AL56: -2134787 | AM56: -640670
W57: FCF (in LKR 000') | X57: =+X55+X56 -> 0 | Y57: =+Y55+Y56 -> 0 | Z57: =+Z55+Z56 -> 0 | AA57: =+AA55+AA56 -> 0 | AB57: =+AB55+AB56 -> -1267042 | AC57: =+AC55+AC56 -> -2949976 | AD57: =+AD55+AD56 -> -4492200 | AE57: =+AE55+AE56 -> -753926 | ... AM57: =+AM55+AM56 -> -435114
W59: Segments
W60: Activated Carbon
W61: Revenue | AF61: 32989586 | AG61: 47287181 | AH61: 59624425 | AI61: 9894042 | AJ61: =20905108-AI61 -> 11011066 | AK61: =31088433-AJ61-AI61 -> 10183325 | AL61: =41659615-AK61-AJ61-AI61 -> 10571182 | AM61: =41659615-AL61-AK61-AJ61 -> 9894042
W62: YoY% | AI62: =+AI61/AE61-1 -> #DIV/0!
W63: QoQ% | AI63: =+AI61/AH61-1 -> -0.83406059 | AJ63: =+AJ61/AI61-1 -> 0.11289865 | AK63: =+AK61/AJ61-1 -> -0.075173557 | AL63: =+AL61/AK61-1 -> 0.038087462 | AM63: =+AM61/AL61-1 -> -0.064055278
W64: Operating profit | AB64: 1468657 | AC64: 2382919 | AD64: 4584689 | AE64: 3784406 | AF64: 5804778 | AG64: 7535306 | AH64: 8497831 | AI64: 1097316 | AJ64: =2588027-AI64 -> 1490711 | AK64: =4533431-AJ64-AI64 -> 1945404 | AL64: =6065715-AK64-AJ64-AI64 -> 1532284 | AM64: =6065715-AL64-AK64-AJ64 -> 1097316
W65: margin% | AI65: =+AI64/AI61 -> 0.11090675 | AJ65: =+AJ64/AJ61 -> 0.13538299 | AK65: =+AK64/AK61 -> 0.19103819 | AL65: =+AL64/AL61 -> 0.14494916 | AM65: =+AM64/AM61 -> 0.11090675
W67: Environmental Engineering
W68: Revenue | AF68: 396492 | AG68: 805713 | AH68: 1318831 | AI68: 321356 | AJ68: =701400-AI68 -> 380044 | AK68: =1218699-AJ68-AI68 -> 517299 | AL68: =1519590-AK68-AJ68-AI68 -> 300891 | AM68: =1519590-AL68-AK68-AJ68 -> 321356
W69: YoY% | AI69: =+AI68/AE68-1 -> #DIV/0!
W70: QoQ% | AI70: =+AI68/AH68-1 -> -0.75633269 | AJ70: =+AJ68/AI68-1 -> 0.18262612 | AK70: =+AK68/AJ68-1 -> 0.36115555 | AL70: =+AL68/AK68-1 -> -0.4183422 | AM70: =+AM68/AL68-1 -> 0.068014663
W71: Operating profit | AB71: -2543 | AC71: 26403 | AD71: 111366 | AE71: -91272 | AF71: -158979 | AG71: -201623 | AH71: -241935 | AI71: -34413 | AJ71: =-1821-AI71 -> 32592 | AK71: =34091-AJ71-AI71 -> 35912 | AL71: =56365-AK71-AJ71-AI71 -> 22274 | AM71: =56365-AL71-AK71-AJ71 -> -34413
W72: margin% | AI72: =+AI71/AI68 -> -0.10708684 | AJ72: =+AJ71/AJ68 -> 0.085758491 | AK72: =+AK71/AK68 -> 0.069422133 | AL72: =+AL71/AL68 -> 0.074026807 | AM72: =+AM71/AM68 -> -0.10708684

Sheet HELA
W1: Stock Price | X1: =+'Valuation Sheet'!C8 -> 5.2
B2: TJL - Rs mn | C2: FY16 | D2: FY17 | E2: FY18 | F2: FY19 | G2: FY20 | H2: FY21 | I2: FY22 | J2: CAGR/AVG | M2: MPS | N2: ='[1]LT Portfolio'!I294 -> SELL | P2: AVG | Q2: =J14*J21 -> 34.398438 | W2: HELA | X2: 2Q21 | Y2: 3Q21 | Z2: 4Q21 | AA2: 1Q22 | AB2: 2Q22 | AC2: 3Q22 | AD2: 4Q22 | AE2: 1Q23 | AF2: 2Q23 | AG2: 3Q23 | AH2: 4Q23 | AI2: 1Q24 | AJ2: 2Q24 | AK2: 3Q24 | AL2: 4Q24 | AM2: 1Q25
B3: Net Revenue | C3: 17820.179 | D3: 22137.641 | E3: 24647.488 | F3: 31746.592 | G3: 33276.977 | H3: 31780.287 | I3: 49587.964 | M3: P/E | N3: ='[1]LT Portfolio'!W294 -> 0 | W3: Revenue (LKR 000) | AC3: 15021451 | AD3: 14593552 | AE3: 24468492 | AF3: 28156456 | AG3: 21750692 | AH3: 20521778 | AI3: 16992389 | AJ3: 17171910 | AK3: 14293333 | AL3: 21722634 | AM3: 19556519
B4: Revenue Growth | D4: =(D3/C3-1)*100 -> 24.227938 | E4: =(E3/D3-1)*100 -> 11.337464 | F4: =(F3/E3-1)*100 -> 28.802546 | G4: =(G3/F3-1)*100 -> 4.8206277 | H4: =(H3/G3-1)*100 -> -4.4976742 | I4: =(I3/H3-1)*100 -> 56.03372 | J4: =((I3/D3)^(1/5)-1)*100 -> 17.503009 | W4: YoY% | AB4: =+AB3/X3-1 -> #DIV/0! | AC4: =+AC3/Y3-1 -> #DIV/0! | AD4: =+AD3/Z3-1 -> #DIV/0! | AE4: =+AE3/AA3-1 -> #DIV/0! | AF4: =+AF3/AB3-1 -> #DIV/0! | AG4: =+AG3/AC3-1 -> 0.44797543 | AH4: =+AH3/AD3-1 -> 0.40622228 | AI4: =+AI3/AE3-1 -> -0.30554 | ... AM4: =+AM3/AI3-1 -> 0.15089873
B5: Gross Profit | C5: 2994.862 | D5: 3075.715 | E5: 2911.199 | F5: 3686.058 | G5: 4229.042 | H5: 3789.959 | I5: 4577.641 | M5: 2Q21 | N5: =202.575/415.481776 -> 0.48756651 | W5: QoQ% | Y5: =+Y3/X3-1 -> #DIV/0! | Z5: =+Z3/Y3-1 -> #DIV/0! | AA5: =+AA3/Z3-1 -> #DIV/0! | AB5: =+AB3/AA3-1 -> #DIV/0! | AC5: =+AC3/AB3-1 -> #DIV/0! | AD5: =+AD3/AC3-1 -> -0.028485863 | AE5: =+AE3/AD3-1 -> 0.6766646 | AF5: =+AF3/AE3-1 -> 0.15072298 | ... AM5: =+AM3/AL3-1 -> -0.099716959
B6: GPM | C6: =C5/C$3*100 -> 16.806015 | D6: =D5/D$3*100 -> 13.893599 | E6: =E5/E$3*100 -> 11.811342 | F6: =F5/F$3*100 -> 11.610878 | G6: =G5/G$3*100 -> 12.708612 | H6: =H5/H$3*100 -> 11.925503 | I6: =I5/I$3*100 -> 9.231355 | J6: =AVERAGE(D6:I6) -> 11.863548 | M6: 3Q21 | N6: =261.001/415.481776 -> 0.6281888
B7: EBIT | C7: 2167.608 | D7: 1992.405 | E7: 1810.842 | F7: 2344.649 | G7: 2728.431 | H7: 2441.401 | I7: 2573.103 | M7: 4Q21 | N7: ='[1]LT Portfolio'!P294 -> 0 | W7: Revenue (in USD) | AC7: 74622 | AD7: 62682 | AE7: 73287 | AF7: 78080 | AG7: 59898 | AH7: 56644 | AI7: 53975 | AJ7: 53615 | AK7: 43716 | AL7: 68491 | AM7: 65194
B8: EBIT Margin | C8: =C7/C$3*100 -> 12.163784 | D8: =D7/D$3*100 -> 9.0000782 | E8: =E7/E$3*100 -> 7.3469637 | F8: =F7/F$3*100 -> 7.385514 | G8: =G7/G$3*100 -> 8.1991552 | H8: =H7/H$3*100 -> 7.6821238 | I8: =I7/I$3*100 -> 5.1889668 | J8: =AVERAGE(D8:I8) -> 7.4671336 | M8: 1Q22 | N8: ='[1]LT Portfolio'!Q294 -> 0 | W8: YoY% | AB8: =+AB7/X7-1 -> #DIV/0! | AC8: =+AC7/Y7-1 -> #DIV/0! | AD8: =+AD7/Z7-1 -> #DIV/0! | AE8: =+AE7/AA7-1 -> #DIV/0! | AF8: =+AF7/AB7-1 -> #DIV/0! | AG8: =+AG7/AC7-1 -> -0.19731446 | AH8: =+AH7/AD7-1 -> -0.096327494 | AI8: =+AI7/AE7-1 -> -0.26351195 | ... AM8: =+AM7/AI7-1 -> 0.20785549
B9: PBT | C9: 2228.947 | D9: 2011.37 | E9: 1817.716 | F9: 2257.062 | G9: 2811.964 | H9: 2599.336 | I9: 2863.72 | M9: 2Q22 | N9: ='[1]LT Portfolio'!R294 -> 0 | O9: =N9/N5-1 -> -1 | W9: QoQ% | Y9: =+Y7/X7-1 -> #DIV/0! | Z9: =+Z7/Y7-1 -> #DIV/0! | AA9: =+AA7/Z7-1 -> #DIV/0! | AB9: =+AB7/AA7-1 -> #DIV/0! | AC9: =+AC7/AB7-1 -> #DIV/0! | AD9: =+AD7/AC7-1 -> -0.16000643 | AE9: =+AE7/AD7-1 -> 0.16918733 | AF9: =+AF7/AE7-1 -> 0.065400412 | ... AM9: =+AM7/AL7-1 -> -0.048137712
B10: Net Profit | C10: 2170.667 | D10: 1959.175 | E10: 1596.114 | F10: 1858.717 | G10: 2383.784 | H10: 2139.597 | I10: 2531.25 | J10: =((I10/D10)^(1/5)-1)*100 -> 5.2573331 | M10: 3Q22 | N10: ='[1]LT Portfolio'!S294 -> 0 | O10: =N10/N6-1 -> -1
B11: NP Margin | C11: =C10/C$3*100 -> 12.180949 | D11: =D10/D$3*100 -> 8.8499719 | E11: =E10/E$3*100 -> 6.4757674 | F11: =F10/F$3*100 -> 5.8548552 | G11: =G10/G$3*100 -> 7.1634632 | H11: =H10/H$3*100 -> 6.7324659 | I11: =I10/I$3*100 -> 5.1045653 | J11: =AVERAGE(D11:I11) -> 6.6968482 | M11: 4Q22 | N11: ='[1]LT Portfolio'!T294 -> 0 | O11: =N11/N7-1 -> #DIV/0! | W11: Gross Profit | AC11: 2064546 | AD11: 2908198 | AE11: 3517022 | AF11: 4731057 | AG11: 2174758 | AH11: 2767564 | AI11: 1044605 | AJ11: 1403896 | AK11: 1193754 | AL11: 1551694 | AM11: 2365077
B12: NP Growth | D12: =(D10/C10-1)*100 -> -9.7431803 | E12: =(E10/D10-1)*100 -> -18.531321 | F12: =(F10/E10-1)*100 -> 16.452647 | G12: =(G10/F10-1)*100 -> 28.248894 | H12: =(H10/G10-1)*100 -> -10.243671 | I12: =(I10/H10-1)*100 -> 18.304989 | J12: =AVERAGE(D12:I12) -> 4.081393 | S12: 1Q22 | T12: 2Q22 | W12: GPM% | X12: =+X11/X3 -> #DIV/0! | Y12: =+Y11/Y3 -> #DIV/0! | Z12: =+Z11/Z3 -> #DIV/0! | AA12: =+AA11/AA3 -> #DIV/0! | AB12: =+AB11/AB3 -> #DIV/0! | AC12: =+AC11/AC3 -> 0.13743985 | AD12: =+AD11/AD3 -> 0.19927965 | AE12: =+AE11/AE3 -> 0.14373677 | ... AM12: =+AM11/AM3 -> 0.12093548
M13: TTM | N13: =SUM(N8:N11) -> 0 | Q13: =N13*J21 -> 0 | S13: 19.109574 | T13: 18.873653
B14: EPS | C14: 3.24 | D14: 2.81 | E14: 2.28 | F14: 2.65 | G14: 3.4 | H14: 3.04 | I14: 3.54 | J14: =AVERAGE(D14:I14) -> 2.9533333 | M14: P/E | N14: =N2/N13 -> #VALUE! | Q14: =Q13/N2-1 -> #VALUE! | S14: =S13/N2-1 -> #VALUE! | T14: =T13/N2-1 -> #VALUE! | W14: EBIT | AC14: 777427 | AD14: 503210 | AE14: 1087664 | AF14: 1261857 | AG14: -428646 | AH14: 910808 | AI14: -1221780 | AJ14: -2127835 | AK14: -939546 | AL14: 4483860 | AM14: -1571787
B15: DPS | C15: =1+0.6 -> 1.6 | D15: =1+1.25 -> 2.25 | E15: =0.9+0.7 -> 1.6 | F15: =1.1+0.85 -> 1.95 | G15: 1.3 | H15: =1.65+1.15 -> 2.8 | I15: =1.5+0.85 -> 2.35 | W15: EBIT margin % | X15: =+X14/X3 -> #DIV/0! | Y15: =+Y14/Y3 -> #DIV/0! | Z15: =+Z14/Z3 -> #DIV/0! | AA15: =+AA14/AA3 -> #DIV/0! | AB15: =+AB14/AB3 -> #DIV/0! | AC15: =+AC14/AC3 -> 0.051754454 | AD15: =+AD14/AD3 -> 0.034481667 | AE15: =+AE14/AE3 -> 0.044451616 | ... AM15: =+AM14/AM3 -> -0.080371512
B16: MPS | C16: 31.7 | D16: 37 | E16: 31.9 | F16: 30.4 | G16: 23.3 | H16: 40 | I16: 39.8 | J16: =((I16/D16)^(1/5)-1)*100 -> 1.4696751
B17: BVPS | C17: 14.6 | D17: 16 | E17: 16.7 | F17: 19.8 | G17: 22.3 | H17: 25 | I17: 39.4 | J17: =((I17/D17)^(1/6)-1)*100 -> 16.20622 | W17: Net Finance Income/Cost | AC17: -321443 | AD17: -470249 | AE17: -669602 | AF17: =8552-721931 -> -713379 | AG17: -1073352 | AH17: -931458 | AI17: -998679 | AJ17: =6173-907205 -> -901032 | AK17: -1032767 | AL17: -1050048 | AM17: -995550
B18: ROE | C18: =C14/AVERAGE(B17:C17)*100 -> 22.191781 | D18: =D14/AVERAGE(C17:D17)*100 -> 18.366013 | E18: =E14/AVERAGE(D17:E17)*100 -> 13.944954 | F18: =F14/AVERAGE(E17:F17)*100 -> 14.520548 | G18: =G14/AVERAGE(F17:G17)*100 -> 16.152019 | H18: =H14/AVERAGE(G17:H17)*100 -> 12.854123 | I18: =I14/AVERAGE(H17:I17)*100 -> 10.993789 | J18: =AVERAGE(D18:I18) -> 14.471908 | M18: MGT | W18: As a % of EBIT | X18: =+X17/X14 -> #DIV/0! | Y18: =+Y17/Y14 -> #DIV/0! | Z18: =+Z17/Z14 -> #DIV/0! | AA18: =+AA17/AA14 -> #DIV/0! | AB18: =+AB17/AB14 -> #DIV/0! | AC18: =+AC17/AC14 -> -0.41347033 | AD18: =+AD17/AD14 -> -0.93449852 | AE18: =+AE17/AE14 -> -0.61563314 | ... AM18: =+AM17/AM14 -> 0.63338735
B19: DY | C19: =C15/C16*100 -> 5.0473186 | D19: =D15/D16*100 -> 6.0810811 | E19: =E15/E16*100 -> 5.015674 | F19: =F15/F16*100 -> 6.4144737 | G19: =G15/G16*100 -> 5.5793991 | H19: =H15/H16*100 -> 7 | I19: =I15/I16*100 -> 5.9045226 | J19: =AVERAGE(D19:I19) -> 5.9991918
B20: Dividend Payout | C20: =C15/C14*100 -> 49.382716 | D20: =D15/D14*100 -> 80.071174 | E20: =E15/E14*100 -> 70.175439 | F20: =F15/F14*100 -> 73.584906 | G20: =G15/G14*100 -> 38.235294 | H20: =H15/H14*100 -> 92.105263 | I20: =I15/I14*100 -> 66.384181 | J20: =AVERAGE(D20:I20) -> 70.092709 | M20: YoY Growth | N20: =N13/H14-1 -> -1 | W20: PBT | AC20: 463449 | AD20: -35777 | AE20: 410008 | AF20: 550550 | AG20: -1560227 | AH20: -43112 | AI20: -2265075 | AJ20: -3028128 | AK20: -1982046 | AL20: 3412106 | AM20: -2611549
B21: P/E | C21: =C16/C14 -> 9.7839506 | D21: =D16/D14 -> 13.16726 | E21: =E16/E14 -> 13.991228 | F21: =F16/F14 -> 11.471698 | G21: =G16/G14 -> 6.8529412 | H21: =H16/H14 -> 13.157895 | I21: =I16/I14 -> 11.242938 | J21: =AVERAGE(D21:I21) -> 11.647327 | W21: PBT Margin% | X21: =+X20/X3 -> #DIV/0! | Y21: =+Y20/Y3 -> #DIV/0! | Z21: =+Z20/Z3 -> #DIV/0! | AA21: =+AA20/AA3 -> #DIV/0! | AB21: =+AB20/AB3 -> #DIV/0! | AC21: =+AC20/AC3 -> 0.030852479 | AD21: =+AD20/AD3 -> -0.0024515622 | AE21: =+AE20/AE3 -> 0.01675657 | ... AM21: =+AM20/AM3 -> -0.13353854
B22: P/B | C22: =C16/C17 -> 2.1712329 | D22: =D16/D17 -> 2.3125 | E22: =E16/E17 -> 1.9101796 | F22: =F16/F17 -> 1.5353535 | G22: =G16/G17 -> 1.044843 | H22: =H16/H17 -> 1.6 | I22: =I16/I17 -> 1.0101523 | J22: =AVERAGE(D22:I22) -> 1.5688381
W23: Taxes | AC23: -11335 | AD23: -224902 | AE23: -56419 | AF23: -54029 | AG23: -128035 | AH23: -213753 | AI23: 312855 | AJ23: 431254 | AK23: 141917 | AL23: 1137300 | AM23: 155379
G24: 701.95658 | H24: 709.32254 | I24: 716.73997 | W24: ETR% | X24: =+X23/X20 -> #DIV/0! | Y24: =+Y23/Y20 -> #DIV/0! | Z24: =+Z23/Z20 -> #DIV/0! | AA24: =+AA23/AA20 -> #DIV/0! | AB24: =+AB23/AB20 -> #DIV/0! | AC24: =+AC23/AC20 -> -0.024457923 | AD24: =+AD23/AD20 -> 6.2862174 | AE24: =+AE23/AE20 -> -0.13760463 | ... AM24: =+AM23/AM20 -> -0.059496873
G25: =+G10/G24 -> 3.3959137 | H25: =+H10/H24 -> 3.016395 | I25: =+I10/I24 -> 3.5316155
W26: NCI | AC26: -82 | AD26: 28353 | AE26: 101992 | AF26: 3315 | AG26: -4437 | AH26: 99993 | AI26: 4423 | AJ26: 51289 | AK26: 38787 | AL26: -82099 | AM26: -7250
W28: Net Profit Attributable to Equity Holders | X28: =+X20+X23-X26 -> 0 | Y28: =+Y20+Y23-Y26 -> 0 | Z28: =+Z20+Z23-Z26 -> 0 | AA28: =+AA20+AA23-AA26 -> 0 | AB28: =+AB20+AB23-AB26 -> 0 | AC28: =+AC20+AC23-AC26 -> 452196 | AD28: =+AD20+AD23-AD26 -> -289032 | AE28: =+AE20+AE23-AE26 -> 251597 | ... AM28: =+AM20+AM23-AM26 -> -2448920
W29: NP Margin | X29: =+X28/X3 -> #DIV/0! | Y29: =+Y28/Y3 -> #DIV/0! | Z29: =+Z28/Z3 -> #DIV/0! | AA29: =+AA28/AA3 -> #DIV/0! | AB29: =+AB28/AB3 -> #DIV/0! | AC29: =+AC28/AC3 -> 0.03010335 | AD29: =+AD28/AD3 -> -0.019805459 | AE29: =+AE28/AE3 -> 0.010282489 | ... AM29: =+AM28/AM3 -> -0.12522269
W31: EPS | X31: =+X28/X46 -> 0 | Y31: =+Y28/Y46 -> 0 | Z31: =+Z28/Z46 -> 0 | AA31: =+AA28/AA46 -> 0 | AB31: =+AB28/AB46 -> 0 | AC31: =+AC28/AC46 -> 0.3451994 | AD31: =+AD28/AD46 -> -0.22064254 | AE31: =+AE28/AE46 -> 0.19206524 | ... AM31: =+AM28/AM46 -> -1.8589299
W32: YoY% | AB32: =+AB31/X31-1 -> #DIV/0! | AC32: =+AC31/Y31-1 -> #DIV/0! | AD32: =+AD31/Z31-1 -> #DIV/0! | AE32: =+AE31/AA31-1 -> #DIV/0! | AF32: =+AF31/AB31-1 -> #DIV/0! | AG32: =+AG31/AC31-1 -> -4.7236619 | AH32: =+AH31/AD31-1 -> 0.23466606 | AI32: =+AI31/AE31-1 -> -8.7768932 | ... AM32: =+AM31/AI31-1 -> 0.24453785
W33: QoQ% | Y33: =+Y31/X31-1 -> #DIV/0! | Z33: =+Z31/Y31-1 -> #DIV/0! | AA33: =+AA31/Z31-1 -> #DIV/0! | AB33: =+AB31/AA31-1 -> #DIV/0! | AC33: =+AC31/AB31-1 -> #DIV/0! | AD33: =+AD31/AC31-1 -> -1.6391742 | AE33: =+AE31/AD31-1 -> -1.8704815 | AF33: =+AF31/AE31-1 -> 0.96030159 | ... AM33: =+AM31/AL31-1 -> -1.5287525
W35: RoE | X35: =+X28*4/X40 -> #DIV/0! | Y35: =+Y28*4/Y40 -> #DIV/0! | Z35: =+Z28*4/Z40 -> #DIV/0! | AA35: =+AA28*4/AA40 -> #DIV/0! | AB35: =+AB28*4/AB40 -> #DIV/0! | AC35: =+AC28*4/AC40 -> 0.37602523 | AD35: =+AD28*4/AD40 -> -0.08907064 | AE35: =+AE28*4/AE40 -> 0.062861828 | ... AM35: =+AM28*4/AM40 -> -1.2497114 | AN35: =+AVERAGE(AC35:AL35) -> -0.20259708 | AO35: RoE
AN36: =AVERAGE(AC35:AL35)*AL48 -> -1.293448 | AO36: Normalized EPS
W37: Debt | AC37: =3455090+556799+75005+18091054 -> 22177948 | AD37: =2574365+350258+433857+25688921 -> 29047401 | AE37: =2594148+807385+123900+33533736 -> 37059169 | AF37: =2359856+952941+162178+32166979 -> 35641954 | AG37: =2256366+998189+162310+29698041 -> 33114906 | AH37: =2032101+304027+341521+25502550 -> 28180199 | AI37: =2380480+185947+451602+23955874 -> 26973903 | AJ37: =4493085+2208835+493711+23803411 -> 30999042 | AK37: =4249908+2184708+512074+26641868 -> 33588558 | AL37: =4966617+1069369+928240+27677141 -> 34641367 | AM37: =5121660+3071287+27603202+885913 -> 36682062 | AN37: =X1/AN36 -> -4.020262 | AO37: P/E
W38: Cash | AC38: 2679190 | AD38: 5244151 | AE38: 4008115 | AF38: 6843095 | AG38: 5113315 | AH38: 4038917 | AI38: 4402711 | AJ38: =3688860+174263 -> 3863123 | AK38: =2958045+292926 -> 3250971 | AL38: =8155515+1010516 -> 9166031 | AM38: 7615611
W39: Net Debt | X39: =+X37-X38 -> 0 | Y39: =+Y37-Y38 -> 0 | Z39: =+Z37-Z38 -> 0 | AA39: =+AA37-AA38 -> 0 | AB39: =+AB37-AB38 -> 0 | AC39: =+AC37-AC38 -> 19498758 | AD39: =+AD37-AD38 -> 23803250 | AE39: =+AE37-AE38 -> 33051054 | ... AM39: =+AM37-AM38 -> 29066451
W40: Equity | AC40: 4810273 | AD40: 12979900 | AE40: 16009525 | AF40: 16699030 | AG40: 14720047 | AH40: 14014630 | AI40: 10085765 | AJ40: 6332401 | AK40: 4451249 | AL40: 8410608 | AM40: 7838354
W42: Debt/Equity | X42: =+X37/X40 -> #DIV/0! | Y42: =+Y37/Y40 -> #DIV/0! | Z42: =+Z37/Z40 -> #DIV/0! | AA42: =+AA37/AA40 -> #DIV/0! | AB42: =+AB37/AB40 -> #DIV/0! | AC42: =+AC37/AC40 -> 4.6105383 | AD42: =+AD37/AD40 -> 2.2378756 | AE42: =+AE37/AE40 -> 2.31482 | ... AM42: =+AM37/AM40 -> 4.679817
W44: Average Exchange rate (income Statement) | X44: =+(X3)/X7 -> #DIV/0! | Y44: =+(Y3)/Y7 -> #DIV/0! | Z44: =+(Z3)/Z7 -> #DIV/0! | AA44: =+(AA3)/AA7 -> #DIV/0! | AB44: =+(AB3)/AB7 -> #DIV/0! | AC44: =+(AC3)/AC7 -> 201.30057 | AD44: =+(AD3)/AD7 -> 232.81886 | AE44: =+(AE3)/AE7 -> 333.8722 | ... AM44: =+(AM3)/AM7 -> 299.97422
W46: Number of shares | X46: 1309955.9 | Y46: 1309955.9 | Z46: 1309955.9 | AA46: 1309955.9 | AB46: 1309955.9 | AC46: 1309955.9 | AD46: 1309955.9 | AE46: 1309955.9 | AF46: 1309955.9 | AG46: 1309955.9 | AH46: 1309955.9 | AI46: 1309955.9 | AJ46: 1309955.9 | AK46: 1309955.9 | AL46: 1317381.6 | AM46: 1317381.6
W48: Net Asset Value per share | X48: =+X40/X46 -> 0 | Y48: =+Y40/Y46 -> 0 | Z48: =+Z40/Z46 -> 0 | AA48: =+AA40/AA46 -> 0 | AB48: =+AB40/AB46 -> 0 | AC48: =+AC40/AC46 -> 3.6720876 | AD48: =+AD40/AD46 -> 9.9086539 | AE48: =+AE40/AE46 -> 12.221423 | ... AM48: =+AM40/AM46 -> 5.9499497
W50: Cashflow from operations (in LKR 000') | Y50: =+Y54-X54 -> 0 | Z50: =+Z54-Y54 -> 0 | AA50: =+AA54 -> 0 | AB50: =+AB54-AA54 -> 0 | AC50: =+AC54-AB54 -> 0 | AD50: =+AD54-AC54 -> 0 | AE50: =+AE54 -> -3716223 | AF50: =+AF54-AE54 -> 4321427 | AG50: =+AG54-AF54 -> 1386677 | AH50: =+AH54-AG54 -> 3233416 | AI50: =+AI54 -> -79051 | AJ50: =+AJ54-AI54 -> -1210484 | AK50: =+AK54-AJ54 -> -2598751 | AL50: =+AL54-AK54 -> -889046 | AM50: =+AM54-AL54 -> 4777332
W51: Capex | Y51: =+Y55-X55 -> 0 | Z51: =+Z55-Y55 -> 0 | AA51: =+AA55 -> 0 | AB51: =+AB55-AA55 -> 0 | AC51: =+AC55-AB55 -> 0 | AD51: =+AD55-AC55 -> 0 | AE51: =+AE55 -> 0 | AF51: =+AF55-AE55 -> -363953 | AG51: =+AG55-AF55 -> -659459 | AH51: =+AH55-AG55 -> -1045133 | AI51: =+AI55 -> 0 | AJ51: =+AJ55-AI55 -> -43885 | AK51: =+AK55-AJ55 -> -568800 | AL51: =+AL55-AK55 -> -1240819 | AM51: =+AM55-AL55 -> 1853504
W52: FCF (in LKR 000') | Y52: =+Y50+Y51 -> 0 | Z52: =+Z50+Z51 -> 0 | AA52: =+AA50+AA51 -> 0 | AB52: =+AB50+AB51 -> 0 | AC52: =+AC50+AC51 -> 0 | AD52: =+AD50+AD51 -> 0 | AE52: =+AE50+AE51 -> -3716223 | AF52: =+AF50+AF51 -> 3957474 | ... AM52: =+AM50+AM51 -> 6630836
W54: Cashflow from operations (in LKR 000') | AE54: -3716223 | AF54: 605204 | AG54: 1991881 | AH54: 5225297 | AI54: -79051 | AJ54: -1289535 | AK54: -3888286 | AL54: -4777332
W55: Capex | AE55: 0 | AF55: -363953 | AG55: -1023412 | AH55: -2068545 | AI55: 0 | AJ55: -43885 | AK55: -612685 | AL55: -1853504
W56: FCF (in LKR 000') | X56: =+X54+X55 -> 0 | Y56: =+Y54+Y55 -> 0 | Z56: =+Z54+Z55 -> 0 | AA56: =+AA54+AA55 -> 0 | AB56: =+AB54+AB55 -> 0 | AC56: =+AC54+AC55 -> 0 | AD56: =+AD54+AD55 -> 0 | AE56: =+AE54+AE55 -> -3716223 | ... AM56: =+AM54+AM55 -> 0

Sheet EXPO
W1: Stock Price | X1: 151
B2: TJL - Rs mn | C2: FY16 | D2: FY17 | E2: FY18 | F2: FY19 | G2: FY20 | H2: FY21 | I2: FY22 | J2: CAGR/AVG | M2: MPS | N2: ='[1]LT Portfolio'!I294 -> SELL | P2: AVG | Q2: =J14*J21 -> 34.398438 | W2: EXPO | X2: 2Q21 | Y2: 3Q21 | Z2: 4Q21 | AA2: 1Q22 | AB2: 2Q22 | AC2: 3Q22 | AD2: 4Q22 | AE2: 1Q23 | AF2: 2Q23 | AG2: 3Q23 | AH2: 4Q23 | AI2: 1Q24 | AJ2: 2Q24 | AK2: 3Q24 | AL2: 4Q24 | AM2: 5Q24 | AP2: =+W2 -> EXPO | AQ2: FY24E | AV2: FY25E
B3: Net Revenue | C3: 17820.179 | D3: 22137.641 | E3: 24647.488 | F3: 31746.592 | G3: 33276.977 | H3: 31780.287 | I3: 49587.964 | M3: P/E | N3: ='[1]LT Portfolio'!W294 -> #REF! | W3: Revenue (LKR 000) | X3: 49150839 | Y3: 57881624 | Z3: 75512524 | AA3: 95732620 | AB3: 1.5142418e+08 | AC3: 2.0495412e+08 | AD3: 2.420465e+08 | AE3: 2.3518186e+08 | AF3: 1.6176842e+08 | AG3: 94280892 | AH3: 55169709 | AI3: 55514880 | AJ3: 61535566 | AK3: 66874464 | AL3: 66029296 | AN3: 500000 | AQ3: Revenue | AR3: EBIT | AS3: NP | AT3: EPS | AU3: DPS | AV3: Revenue | AW3: EBIT | AX3: NP | AY3: EPS | AZ3: DPS
B4: Revenue Growth | D4: =(D3/C3-1)*100 -> 24.227938 | E4: =(E3/D3-1)*100 -> 11.337464 | F4: =(F3/E3-1)*100 -> 28.802546 | G4: =(G3/F3-1)*100 -> 4.8206277 | H4: =(H3/G3-1)*100 -> -4.4976742 | I4: =(I3/H3-1)*100 -> 56.03372 | J4: =((I3/D3)^(1/5)-1)*100 -> 17.503009 | W4: YoY% | AB4: =+AB3/X3-1 -> 2.0808056 | AC4: =+AC3/Y3-1 -> 2.5409186 | AD4: =+AD3/Z3-1 -> 2.2053822 | AE4: =+AE3/AA3-1 -> 1.4566533 | AF4: =+AF3/AB3-1 -> 0.068313011 | AG4: =+AG3/AC3-1 -> -0.53999025 | AH4: =+AH3/AD3-1 -> -0.77206979 | AI4: =+AI3/AE3-1 -> -0.76394914 | ... AM4: =+AM3/AI3-1 -> -1
B5: Gross Profit | C5: 2994.862 | D5: 3075.715 | E5: 2911.199 | F5: 3686.058 | G5: 4229.042 | H5: 3789.959 | I5: 4577.641 | M5: 2Q21 | N5: =202.575/415.481776 -> 0.48756651 | W5: QoQ% | Y5: =+Y3/X3-1 -> 0.17763246 | Z5: =+Z3/Y3-1 -> 0.30460273 | AA5: =+AA3/Z3-1 -> 0.26777141 | AB5: =+AB3/AA3-1 -> 0.58174069 | AC5: =+AC3/AB3-1 -> 0.35350984 | AD5: =+AD3/AC3-1 -> 0.18097897 | AE5: =+AE3/AD3-1 -> -0.028360853 | AF5: =+AF3/AE3-1 -> -0.31215603 | ... AM5: =+AM3/AL3-1 -> -1
B6: GPM | C6: =C5/C$3*100 -> 16.806015 | D6: =D5/D$3*100 -> 13.893599 | E6: =E5/E$3*100 -> 11.811342 | F6: =F5/F$3*100 -> 11.610878 | G6: =G5/G$3*100 -> 12.708612 | H6: =H5/H$3*100 -> 11.925503 | I6: =I5/I$3*100 -> 9.231355 | J6: =AVERAGE(D6:I6) -> 11.863548 | M6: 3Q21 | N6: =261.001/415.481776 -> 0.6281888
B7: EBIT | C7: 2167.608 | D7: 1992.405 | E7: 1810.842 | F7: 2344.649 | G7: 2728.431 | H7: 2441.401 | I7: 2573.103 | M7: 4Q21 | N7: ='[1]LT Portfolio'!P294 -> #REF! | W7: Revenue (in USD 000) | X7: =+X3/X45 -> 261612.29 | Y7: =+Y3/Y45 -> 308039.33 | Z7: =+Z3/Z45 -> 381571.95 | AA7: =+AA3/AA45 -> 474189.9 | AB7: =+AB3/AB45 -> 746177 | AC7: =+AC3/AC45 -> 1009626.2 | AD7: =+AD3/AD45 -> 1036698.4 | AE7: =+AE3/AE45 -> 645619.22 | ... AM7: =+AM3/AM45 -> #DIV/0!
B8: EBIT Margin | C8: =C7/C$3*100 -> 12.163784 | D8: =D7/D$3*100 -> 9.0000782 | E8: =E7/E$3*100 -> 7.3469637 | F8: =F7/F$3*100 -> 7.385514 | G8: =G7/G$3*100 -> 8.1991552 | H8: =H7/H$3*100 -> 7.6821238 | I8: =I7/I$3*100 -> 5.1889668 | J8: =AVERAGE(D8:I8) -> 7.4671336 | M8: 1Q22 | N8: ='[1]LT Portfolio'!Q294 -> #REF! | W8: YoY% | AB8: =+AB7/X7-1 -> 1.8522246 | AC8: =+AC7/Y7-1 -> 2.2775885 | AD8: =+AD7/Z7-1 -> 1.7169145 | AE8: =+AE7/AA7-1 -> 0.36152039 | AF8: =+AF7/AB7-1 -> -0.41223598 | AG8: =+AG7/AC7-1 -> -0.74882154 | AH8: =+AH7/AD7-1 -> -0.8512191 | AI8: =+AI7/AE7-1 -> -0.72828181 | ... AM8: =+AM7/AI7-1 -> #DIV/0!
B9: PBT | C9: 2228.947 | D9: 2011.37 | E9: 1817.716 | F9: 2257.062 | G9: 2811.964 | H9: 2599.336 | I9: 2863.72 | M9: 2Q22 | N9: ='[1]LT Portfolio'!R294 -> #REF! | O9: =N9/N5-1 -> #REF! | W9: QoQ% | Y9: =+Y7/X7-1 -> 0.17746507 | Z9: =+Z7/Y7-1 -> 0.23871178 | AA9: =+AA7/Z7-1 -> 0.24272737 | AB9: =+AB7/AA7-1 -> 0.57358263 | AC9: =+AC7/AB7-1 -> 0.35306525 | AD9: =+AD7/AC7-1 -> 0.026814082 | AE9: =+AE7/AD7-1 -> -0.37723523 | AF9: =+AF7/AE7-1 -> -0.32068938 | ... AM9: =+AM7/AL7-1 -> #DIV/0!
B10: Net Profit | C10: 2170.667 | D10: 1959.175 | E10: 1596.114 | F10: 1858.717 | G10: 2383.784 | H10: 2139.597 | I10: 2531.25 | J10: =((I10/D10)^(1/5)-1)*100 -> 5.2573331 | M10: 3Q22 | N10: ='[1]LT Portfolio'!S294 -> #REF! | O10: =N10/N6-1 -> #REF!
B11: NP Margin | C11: =C10/C$3*100 -> 12.180949 | D11: =D10/D$3*100 -> 8.8499719 | E11: =E10/E$3*100 -> 6.4757674 | F11: =F10/F$3*100 -> 5.8548552 | G11: =G10/G$3*100 -> 7.1634632 | H11: =H10/H$3*100 -> 6.7324659 | I11: =I10/I$3*100 -> 5.1045653 | J11: =AVERAGE(D11:I11) -> 6.6968482 | M11: 4Q22 | N11: ='[1]LT Portfolio'!T294 -> #REF! | O11: =N11/N7-1 -> #REF! | W11: Gross Profit | X11: 10542896 | Y11: 9701678.3 | Z11: 11906298 | AA11: 14457158 | AB11: 22603748 | AC11: 38758141 | AD11: 46089112 | AE11: 36972107 | AF11: 28341218 | AG11: 20639193 | AH11: 19316330 | AI11: 11270365 | AJ11: 12078113 | AK11: 10923800 | AL11: 12865458 | AP11: Consensus | AQ11: =+AVERAGE(AQ4:AQ10) -> #DIV/0! | AR11: =+AVERAGE(AR4:AR10) -> #DIV/0! | AS11: =+AVERAGE(AS4:AS10) -> #DIV/0! | AT11: =+AVERAGE(AT4:AT10) -> #DIV/0! | AU11: =+AVERAGE(AU4:AU10) -> #DIV/0! | AV11: =+AVERAGE(AV4:AV10) -> #DIV/0! | AW11: =+AVERAGE(AW4:AW10) -> #DIV/0! | AX11: =+AVERAGE(AX4:AX10) -> #DIV/0! | ... AZ11: =+AVERAGE(AZ4:AZ10) -> #DIV/0!
B12: NP Growth | D12: =(D10/C10-1)*100 -> -9.7431803 | E12: =(E10/D10-1)*100 -> -18.531321 | F12: =(F10/E10-1)*100 -> 16.452647 | G12: =(G10/F10-1)*100 -> 28.248894 | H12: =(H10/G10-1)*100 -> -10.243671 | I12: =(I10/H10-1)*100 -> 18.304989 | J12: =AVERAGE(D12:I12) -> 4.081393 | S12: 1Q22 | T12: 2Q22 | W12: GPM% | X12: =+X11/X3 -> 0.21450083 | Y12: =+Y11/Y3 -> 0.16761241 | Z12: =+Z11/Z3 -> 0.15767316 | AA12: =+AA11/AA3 -> 0.151016 | AB12: =+AB11/AB3 -> 0.14927436 | AC12: =+AC11/AC3 -> 0.18910643 | AD12: =+AD11/AD3 -> 0.19041428 | AE12: =+AE11/AE3 -> 0.15720646 | ... AM12: =+AM11/AM3 -> #DIV/0!
M13: TTM | N13: =SUM(N8:N11) -> #REF! | Q13: =N13*J21 -> #REF! | S13: 19.109574 | T13: 18.873653 | AP13: Leading P/E | AT13: =+$X$1/AT11 -> #DIV/0! | AU13: =+AU11/$X$1 -> #DIV/0! | AY13: =+$X$1/AY11 -> #DIV/0! | AZ13: =+AZ11/$X$1 -> #DIV/0!
B14: EPS | C14: 3.24 | D14: 2.81 | E14: 2.28 | F14: 2.65 | G14: 3.4 | H14: 3.04 | I14: 3.54 | J14: =AVERAGE(D14:I14) -> 2.9533333 | M14: P/E | N14: =N2/N13 -> #VALUE! | Q14: =Q13/N2-1 -> #REF! | S14: =S13/N2-1 -> #VALUE! | T14: =T13/N2-1 -> #VALUE! | W14: EBIT | X14: =+X21-X18 -> 5530766.1 | Y14: =+Y21-Y18 -> 4681029.8 | Z14: =+Z21-Z18 -> 4259638.5 | AA14: =+AA21-AA18 -> 7923435.4 | AB14: =+AB21-AB18 -> 14654372 | AC14: =+AC21-AC18 -> 26569605 | AD14: =+AD21-AD18 -> 37622295 | AE14: =+AE21-AE18 -> 24943804 | ... AM14: =+AM21-AM18 -> 0
B15: DPS | C15: =1+0.6 -> 1.6 | D15: =1+1.25 -> 2.25 | E15: =0.9+0.7 -> 1.6 | F15: =1.1+0.85 -> 1.95 | G15: 1.3 | H15: =1.65+1.15 -> 2.8 | I15: =1.5+0.85 -> 2.35 | W15: EBIT margin % | X15: =+X14/X3 -> 0.11252638 | Y15: =+Y14/Y3 -> 0.080872468 | Z15: =+Z14/Z3 -> 0.056409695 | AA15: =+AA14/AA3 -> 0.082766307 | AB15: =+AB14/AB3 -> 0.096776958 | AC15: =+AC14/AC3 -> 0.12963685 | AD15: =+AD14/AD3 -> 0.15543416 | AE15: =+AE14/AE3 -> 0.10606177 | ... AM15: =+AM14/AM3 -> #DIV/0! | AN15: =+AN3*0.06 -> 30000
B16: MPS | C16: 31.7 | D16: 37 | E16: 31.9 | F16: 30.4 | G16: 23.3 | H16: 40 | I16: 39.8 | J16: =((I16/D16)^(1/5)-1)*100 -> 1.4696751 | W16: EBIT/GP conversion | X16: =+X14/X11 -> 0.52459649 | Y16: =+Y14/Y11 -> 0.48249691 | Z16: =+Z14/Z11 -> 0.35776347 | AA16: =+AA14/AA11 -> 0.54806315 | AB16: =+AB14/AB11 -> 0.648316 | AC16: =+AC14/AC11 -> 0.68552322 | AD16: =+AD14/AD11 -> 0.81629465 | AE16: =+AE14/AE11 -> 0.67466548 | ... AM16: =+AM14/AM11 -> #DIV/0!
B17: BVPS | C17: 14.6 | D17: 16 | E17: 16.7 | F17: 19.8 | G17: 22.3 | H17: 25 | I17: 39.4 | J17: =((I17/D17)^(1/6)-1)*100 -> 16.20622
B18: ROE | C18: =C14/AVERAGE(B17:C17)*100 -> 22.191781 | D18: =D14/AVERAGE(C17:D17)*100 -> 18.366013 | E18: =E14/AVERAGE(D17:E17)*100 -> 13.944954 | F18: =F14/AVERAGE(E17:F17)*100 -> 14.520548 | G18: =G14/AVERAGE(F17:G17)*100 -> 16.152019 | H18: =H14/AVERAGE(G17:H17)*100 -> 12.854123 | I18: =I14/AVERAGE(H17:I17)*100 -> 10.993789 | J18: =AVERAGE(D18:I18) -> 14.471908 | M18: MGT | W18: Net Finance Income/Cost | X18: =14046.083-93564.028 -> -79517.945 | Y18: =19995.868-92312.269 -> -72316.401 | Z18: =19256.91-77144.832 -> -57887.922 | AA18: =25284.486-97308.781 -> -72024.295 | AB18: =14326.699-195923.589 -> -181596.89 | AC18: =27907.555-400522.274 -> -372614.72 | AD18: =20456.56-568970.619 -> -548514.06 | AE18: =40333.511-552310.647 -> -511977.14 | AF18: =72688.443-607942.541 -> -535254.1 | AG18: =246581.159-278225.441 -> -31644.282 | AH18: =343225.57-321243.838 -> 21981.732 | AI18: =565604.637-378552.916 -> 187051.72 | AJ18: =617282.892-430827.913 -> 186454.98 | AK18: =559517.652-394333.748 -> 165183.9 | AL18: =509523.115-379296.838 -> 130226.28
B19: DY | C19: =C15/C16*100 -> 5.0473186 | D19: =D15/D16*100 -> 6.0810811 | E19: =E15/E16*100 -> 5.015674 | F19: =F15/F16*100 -> 6.4144737 | G19: =G15/G16*100 -> 5.5793991 | H19: =H15/H16*100 -> 7 | I19: =I15/I16*100 -> 5.9045226 | J19: =AVERAGE(D19:I19) -> 5.9991918 | W19: As a % of EBIT | X19: =+X18/X14 -> -0.014377383 | Y19: =+Y18/Y14 -> -0.015448823 | Z19: =+Z18/Z14 -> -0.013589867 | AA19: =+AA18/AA14 -> -0.0090900337 | AB19: =+AB18/AB14 -> -0.012391994 | AC19: =+AC18/AC14 -> -0.014024097 | AD19: =+AD18/AD14 -> -0.014579495 | AE19: =+AE18/AE14 -> -0.020525223 | ... AM19: =+AM18/AM14 -> #DIV/0!
B20: Dividend Payout | C20: =C15/C14*100 -> 49.382716 | D20: =D15/D14*100 -> 80.071174 | E20: =E15/E14*100 -> 70.175439 | F20: =F15/F14*100 -> 73.584906 | G20: =G15/G14*100 -> 38.235294 | H20: =H15/H14*100 -> 92.105263 | I20: =I15/I14*100 -> 66.384181 | J20: =AVERAGE(D20:I20) -> 70.092709 | M20: YoY Growth | N20: =N13/H14-1 -> #REF!
B21: P/E | C21: =C16/C14 -> 9.7839506 | D21: =D16/D14 -> 13.16726 | E21: =E16/E14 -> 13.991228 | F21: =F16/F14 -> 11.471698 | G21: =G16/G14 -> 6.8529412 | H21: =H16/H14 -> 13.157895 | I21: =I16/I14 -> 11.242938 | J21: =AVERAGE(D21:I21) -> 11.647327 | W21: PBT | X21: 5451248.1 | Y21: 4608713.4 | Z21: 4201750.6 | AA21: 7851411.1 | AB21: 14472775 | AC21: 26196991 | AD21: 37073781 | AE21: 24431827 | AF21: 11381626 | AG21: 3852269.8 | AH21: -1150140.2 | AI21: -5144142.5 | AJ21: -1002819.5 | AK21: -4886182.4 | AL21: 5389105.5 | AN21: 41000
B22: P/B | C22: =C16/C17 -> 2.1712329 | D22: =D16/D17 -> 2.3125 | E22: =E16/E17 -> 1.9101796 | F22: =F16/F17 -> 1.5353535 | G22: =G16/G17 -> 1.044843 | H22: =H16/H17 -> 1.6 | I22: =I16/I17 -> 1.0101523 | J22: =AVERAGE(D22:I22) -> 1.5688381 | W22: PBT Margin% | X22: =+X21/X3 -> 0.11090855 | Y22: =+Y21/Y3 -> 0.079623084 | Z22: =+Z21/Z3 -> 0.055643095 | AA22: =+AA21/AA3 -> 0.082013958 | AB22: =+AB21/AB3 -> 0.095577699 | AC22: =+AC21/AC3 -> 0.12781881 | AD22: =+AD21/AD3 -> 0.15316801 | AE22: =+AE21/AE3 -> 0.10388483 | ... AM22: =+AM21/AM3 -> #DIV/0!
G24: 701.95658 | H24: 709.32254 | I24: 716.73997 | W24: Taxes | X24: -906239.68 | Y24: -48326.732 | Z24: -181281.2 | AA24: -1549103.6 | AB24: -2393470.7 | AC24: -3144086.9 | AD24: -5716575.3 | AE24: -4279785.1 | AF24: -2323045.9 | AG24: -841324.55 | AH24: -21268.936 | AI24: -541465.14 | AJ24: -500885.67 | AK24: -278108.18 | AL24: 49451.02
G25: =+G10/G24 -> 3.3959137 | H25: =+H10/H24 -> 3.016395 | I25: =+I10/I24 -> 3.5316155 | W25: ETR% | X25: =+X24/X21 -> -0.16624444 | Y25: =+Y24/Y21 -> -0.010485949 | Z25: =+Z24/Z21 -> -0.043144207 | AA25: =+AA24/AA21 -> -0.19730257 | AB25: =+AB24/AB21 -> -0.16537746 | AC25: =+AC24/AC21 -> -0.1200171 | AD25: =+AD24/AD21 -> -0.15419456 | AE25: =+AE24/AE21 -> -0.17517253 | ... AM25: =+AM24/AM21 -> #DIV/0!
W27: NCI | X27: 13176.566 | Y27: 9229.534 | Z27: 21205.007 | AA27: 15906.232 | AB27: 19066.17 | AC27: 11660.246 | AD27: 2557.396 | AE27: -2804.394 | AF27: 79856.285 | AG27: 21266.113 | AH27: 13705.965 | AI27: 10523.929 | AJ27: 12545.662 | AK27: -5019.823 | AL27: 1398.41
W29: Net Profit Attributable to Equity Holders | X29: =+X21+X24-X27 -> 4531831.9 | Y29: =+Y21+Y24-Y27 -> 4551157.1 | Z29: =+Z21+Z24-Z27 -> 3999264.4 | AA29: =+AA21+AA24-AA27 -> 6286401.3 | AB29: =+AB21+AB24-AB27 -> 12060238 | AC29: =+AC21+AC24-AC27 -> 23041244 | AD29: =+AD21+AD24-AD27 -> 31354649 | AE29: =+AE21+AE24-AE27 -> 20154847 | ... AM29: =+AM21+AM24-AM27 -> 0
W30: NP Margin | X30: =+X29/X3 -> 0.092202534 | Y30: =+Y29/Y3 -> 0.078628705 | Z30: =+Z29/Z3 -> 0.052961604 | AA30: =+AA29/AA3 -> 0.065666241 | AB30: =+AB29/AB3 -> 0.079645389 | AC30: =+AC29/AC3 -> 0.11242147 | AD30: =+AD29/AD3 -> 0.12953977 | AE30: =+AE29/AE3 -> 0.085698985 | ... AM30: =+AM29/AM3 -> #DIV/0!
W32: EPS | X32: =+X29/X47 -> 2.3181734 | Y32: =+Y29/Y47 -> 2.3280588 | Z32: =+Z29/Z47 -> 2.0457485 | AA32: =+AA29/AA47 -> 3.2156903 | AB32: =+AB29/AB47 -> 6.1691878 | AC32: =+AC29/AC47 -> 11.786315 | AD32: =+AD29/AD47 -> 16.038881 | AE32: =+AE29/AE47 -> 10.309833 | ... AM32: =+AM29/AM47 -> 0
W33: YoY% | AB33: =+AB32/X32-1 -> 1.661228 | AC33: =+AC32/Y32-1 -> 4.0627221 | AD33: =+AD32/Z32-1 -> 6.840104 | AE33: =+AE32/AA32-1 -> 2.2061025 | AF33: =+AF32/AB32-1 -> -0.25551019 | AG33: =+AG32/AC32-1 -> -0.87024662 | AH33: =+AH32/AD32-1 -> -1.0377971 | AI33: =+AI32/AE32-1 -> -1.2826185 | ... AM33: =+AM32/AI32-1 -> -1 | AO33: =+AVERAGE(X36:AK36) -> 0.50793182 | AP33: RoE
W34: QoQ% | Y34: =+Y32/X32-1 -> 0.0042643268 | Z34: =+Z32/Y32-1 -> -0.12126427 | AA34: =+AA32/Z32-1 -> 0.57188939 | AB34: =+AB32/AA32-1 -> 0.91846452 | AC34: =+AC32/AB32-1 -> 0.91051321 | AD34: =+AD32/AC32-1 -> 0.3608054 | AE34: =+AE32/AD32-1 -> -0.3571975 | AF34: =+AF32/AE32-1 -> -0.5545129 | ... AM34: =+AM32/AL32-1 -> -1 | AO34: =AVERAGE(X36:AK36)*AK49 -> 33.545587 | AP34: Normalized EPS
AO35: =X1/AO34 -> 4.5013373 | AP35: P/E
W36: RoE | X36: =+X29*4/X41 -> 0.96034786 | Y36: =+Y29*4/Y41 -> 0.80901868 | Z36: =+Z29*4/Z41 -> 0.58922851 | AA36: =+AA29*4/AA41 -> 0.80772709 | AB36: =+AB29*4/AB41 -> 1.1142445 | AC36: =+AC29*4/AC41 -> 1.3789737 | AD36: =+AD29*4/AD41 -> 1.0119967 | AE36: =+AE29*4/AE41 -> 0.54351211 | ... AM36: =+AM29*4/AM41 -> #DIV/0!
W38: Debt | X38: =4834292.395+10669745.872 -> 15504038 | Y38: =5300601.835+11896395.524 -> 17196997 | Z38: =12854627.585+5532778.654 -> 18387406 | AA38: =7288170.543+29031205.111 -> 36319376 | AB38: =8892918.246+58885493.746 -> 67778412 | AC38: =9197090.199+90248896.979 -> 99445987 | AD38: =15134573.848+76996999.199+96861.771 -> 92228435 | AE38: =18581540.748+67245255.056 -> 85826796 | AF38: =19568416.723+22779208.04+174866.528 -> 42522491 | AG38: =7200946.876+17980166.793+201899.335 -> 25383013 | AH38: =16794614.339+15062191.672+114360.757 -> 31971167 | AI38: =18625734.655+14932414.64+197783.608 -> 33755933 | AJ38: =18539800.07+12463689.073+66589.164 -> 31070078 | AK38: =23817319.48+11136957.095+49790.463 -> 35004067 | AL38: =16794614.339+15062191.673+114360.757 -> 31971167
W39: Cash | X39: =4827101.378+151307.756 -> 4978409.1 | Y39: =7118845.382+174332.828 -> 7293178.2 | Z39: =7610756.231+342756.064 -> 7953512.3 | AA39: =12144928.727+231830.751 -> 12376759 | AB39: =13172736.113+238770.131 -> 13411506 | AC39: =28980207.971+186186.376 -> 29166394 | AD39: =43192921.348+225982.529 -> 43418904 | AE39: =81151564.27+270657.218 -> 81422221 | AF39: =59198914.125+764138.723 -> 59963053 | AG39: =74575931.248+820388.689 -> 75396320 | AH39: =77781817.84+336469.506 -> 78118287 | AI39: =73008960.741+451406.145 -> 73460367 | AJ39: =58764251.133+1456193.918 -> 60220445 | AK39: =58403289.477+1523090.161 -> 59926380 | AL39: =671016.186+49887864.121 -> 50558880 | AN39: =+AI45/AE45-1 -> -0.13126589
W40: Net Debt | X40: =+X38-X39 -> 10525629 | Y40: =+Y38-Y39 -> 9903819.1 | Z40: =+Z38-Z39 -> 10433894 | AA40: =+AA38-AA39 -> 23942616 | AB40: =+AB38-AB39 -> 54366906 | AC40: =+AC38-AC39 -> 70279593 | AD40: =+AD38-AD39 -> 48809531 | AE40: =+AE38-AE39 -> 4404574.3 | ... AM40: =+AM38-AM39 -> 0
W41: Equity | X41: 18875793 | Y41: 22502111 | Z41: 27149157 | AA41: 31131313 | AB41: 43294764 | AC41: 66835921 | AD41: 1.2393182e+08 | AE41: 1.4833043e+08 | AF41: 1.5793316e+08 | AG41: 1.6170685e+08 | AH41: 1.4893559e+08 | AI41: 1.3550596e+08 | AJ41: 1.3315808e+08 | AK41: 1.291094e+08 | AL41: 1.1264503e+08
W43: Debt/Equity | X43: =+X38/X41 -> 0.82137149 | Y43: =+Y38/Y41 -> 0.76423928 | Z43: =+Z38/Z41 -> 0.67727355 | AA43: =+AA38/AA41 -> 1.1666509 | AB43: =+AB38/AB41 -> 1.5655106 | AC43: =+AC38/AC41 -> 1.4879123 | AD43: =+AD38/AD41 -> 0.74418686 | AE43: =+AE38/AE41 -> 0.57861893 | ... AM43: =+AM38/AM41 -> #DIV/0!
W45: Average Exchange rate (income Statement) | X45: =+MGT!X42 -> 187.87665 | Y45: =+MGT!Y42 -> 187.90336 | Z45: =+MGT!Z42 -> 197.89852 | AA45: =+MGT!AA42 -> 201.88667 | AB45: =+MGT!AB42 -> 202.93333 | AC45: =+MGT!AC42 -> 203.00001 | AD45: =+MGT!AD42 -> 233.47823 | AE45: =+MGT!AE42 -> 364.27332 | ... AK45: =+MGT!AK42 -> 334.23664
W47: Number of shares | X47: 1954915 | Y47: 1954915 | Z47: 1954915 | AA47: 1954915 | AB47: 1954915 | AC47: 1954915 | AD47: 1954915 | AE47: 1954915 | AF47: 1954915 | AG47: 1954915 | AH47: 1954915 | AI47: 1954915 | AJ47: 1954915 | AK47: 1954915 | AL47: 1954915 | AM47: 1954915
W49: Net Asset Value per share | X49: =+X41/X47 -> 9.6555569 | Y49: =+Y41/Y47 -> 11.510532 | Z49: =+Z41/Z47 -> 13.887641 | AA49: =+AA41/AA47 -> 15.924638 | AB49: =+AB41/AB47 -> 22.146622 | AC49: =+AC41/AC47 -> 34.188658 | AD49: =+AD41/AD47 -> 63.394994 | AE49: =+AE41/AE47 -> 75.875642 | ... AM49: =+AM41/AM47 -> 0
W51: Cashflow from operations (in LKR 000') | Y51: =+Y55-X55 -> 2193498.2 | Z51: =+Z55-Y55 -> 2240121.3 | AA51: =+AA55 -> -12715487 | AB51: =+AB55-AA55 -> -24397844 | AC51: =+AC55-AB55 -> -13769364 | AD51: =+AD55-AC55 -> 41581632 | AE51: =+AE55 -> 57266707 | AF51: =+AF55-AE55 -> 40887832 | AG51: =+AG55-AF55 -> 34734556 | AH51: =+AH55-AG55 -> 37063009 | AI51: =+AI55 -> 3648231.8 | AJ51: =+AJ55-AI55 -> -338403.42 | AK51: =+AK55-AJ55 -> 2395095.5 | AL51: =+AL55-AK55 -> -5704923.8 | AM51: =+AM55-AL55 -> 0
W52: Capex | Y52: =+Y56-X56 -> -46984.068 | Z52: =+Z56-Y56 -> -181685.63 | AA52: =+AA56 -> -73744.504 | AB52: =+AB56-AA56 -> -3741081.4 | AC52: =+AC56-AB56 -> 2882475.8 | AD52: =+AD56-AC56 -> -1025564.7 | AE52: =+AE56 -> -1083062.5 | AF52: =+AF56-AE56 -> -1439689.6 | AG52: =+AG56-AF56 -> -1956719.9 | AH52: =+AH56-AG56 -> -32300015 | AI52: =+AI56 -> -738416.4 | AJ52: =+AJ56-AI56 -> -653390.34 | AK52: =+AK56-AJ56 -> -931063.77 | AL52: =+AL56-AK56 -> 2322870.5 | AM52: =+AM56-AL56 -> 0
W53: FCF (in LKR 000') | Y53: =+Y51+Y52 -> 2146514.1 | Z53: =+Z51+Z52 -> 2058435.7 | AA53: =+AA51+AA52 -> -12789232 | AB53: =+AB51+AB52 -> -28138926 | AC53: =+AC51+AC52 -> -10886888 | AD53: =+AD51+AD52 -> 40556068 | AE53: =+AE51+AE52 -> 56183645 | AF53: =+AF51+AF52 -> 39448142 | ... AM53: =+AM51+AM52 -> 0
W55: Cashflow from operations (in LKR 000') | X55: -4711756.8 | Y55: -2518258.6 | Z55: -278137.28 | AA55: -12715487 | AB55: -37113332 | AC55: -50882695 | AD55: -9301063.1 | AE55: 57266707 | AF55: 98154539 | AG55: 1.3288909e+08 | AH55: 1.699521e+08 | AI55: 3648231.8 | AJ55: 3309828.3 | AK55: 5704923.8
W56: Capex | X56: -197884.04 | Y56: -244868.1 | Z56: -426553.73 | AA56: -73744.504 | AB56: =-375051.442-3439774.481 -> -3814825.9 | AC56: -932350.11 | AD56: -1957914.8 | AE56: -1083062.5 | AF56: =-1793983.471-728768.612 -> -2522752.1 | AG56: =-3755216.328-724255.605 -> -4479471.9 | AH56: =-5093733.01-31685753.735 -> -36779487 | AI56: -738416.4 | AJ56: -1391806.7 | AK56: -2322870.5
W57: FCF (in LKR 000') | X57: =+X55+X56 -> -4909640.8 | Y57: =+Y55+Y56 -> -2763126.7 | Z57: =+Z55+Z56 -> -704691.02 | AA57: =+AA55+AA56 -> -12789232 | AB57: =+AB55+AB56 -> -40928158 | AC57: =+AC55+AC56 -> -51815045 | AD57: =+AD55+AD56 -> -11258978 | AE57: =+AE55+AE56 -> 56183645 | ... AM57: =+AM55+AM56 -> 0
W60: Freight data
W61: FBX 00 (Global Freight Index - 40ft Container) | X61: =+FBX!D189 -> 1932.9231 | Y61: =+FBX!D176 -> 2472.2308 | Z61: =+FBX!D163 -> 4277.8462 | AA61: =+FBX!D150 -> 5468.9231 | AB61: =+FBX!D137 -> 9656.1538 | AC61: =+FBX!D124 -> 9831.6923 | AD61: =+FBX!D111 -> 9595.8462 | AE61: =+FBX!D98 -> 8311.4615 | AF61: =+FBX!D85 -> 5738.9231 | AG61: =+FBX!D72 -> 3042.2308 | AH61: =+FBX!D59 -> 1953.7692 | AI61: =+FBX!D46 -> 1444.7692 | AJ61: =+FBX!D33 -> 1390.6154 | AK61: =+FBX!D19 -> 1185.49 | AL61: =+FBX!E19 -> 0 | AM61: =+FBX!F19 -> 0 | AN61: =+FBX!D8 -> 3130.4364
W62: YoY% | AB62: =+AB61/X61-1 -> 3.9956224 | AC62: =+AC61/Y61-1 -> 2.9768506 | AD62: =+AD61/Z61-1 -> 1.243149 | AE62: =+AE61/AA61-1 -> 0.51976201 | AF62: =+AF61/AB61-1 -> -0.40567195 | AG62: =+AG61/AC61-1 -> -0.69056896 | AH62: =+AH61/AD61-1 -> -0.79639427 | AI62: =+AI61/AE61-1 -> -0.82617146 | ... AM62: =+AM61/AI61-1 -> -1 | AN62: =+AN61/AH61-1 -> 0.60225492
W63: QoQ% | Y63: =+Y61/X61-1 -> 0.27901146 | Z63: =+Z61/Y61-1 -> 0.73035875 | AA63: =+AA61/Z61-1 -> 0.27842912 | AB63: =+AB61/AA61-1 -> 0.76564082 | AC63: =+AC61/AB61-1 -> 0.018178921 | AD63: =+AD61/AC61-1 -> -0.023988358 | AE63: =+AE61/AD61-1 -> -0.13384798 | AF63: =+AF61/AE61-1 -> -0.30951698 | ... AM63: =+AM61/AL61-1 -> #DIV/0! | AN63: =+AN61/AK61-1 -> 1.6406265
W65: Volume data
W66: Ocean (TEU) | X66: 48000 | Y66: 55000 | Z66: 59000 | AA66: =51000+38200 -> 89200 | AB66: =145000-AA66 -> 55800 | AC66: =211000-AB66-AA66 -> 66000 | AD66: =281000-AC66-AB66-AA66 -> 70000 | AE66: 78700 | AF66: =129700-AE66 -> 51000 | AG66: =167200-AF66-AE66 -> 37500 | AH66: =202900-AG66-AF66-AE66 -> 35700 | AI66: 40000 | AJ66: 46000 | AK66: 29000 | AL66: 29000 | AM66: 29000
W67: YoY% | AB67: =+AB66/X66-1 -> 0.1625 | AC67: =+AC66/Y66-1 -> 0.2 | AD67: =+AD66/Z66-1 -> 0.18644068 | AE67: =+AE66/AA66-1 -> -0.117713 | AF67: =+AF66/AB66-1 -> -0.086021505 | AG67: =+AG66/AC66-1 -> -0.43181818 | AH67: =+AH66/AD66-1 -> -0.49 | AI67: =+AI66/AE66-1 -> -0.49174079 | ... AM67: =+AM66/AI66-1 -> -0.275
W68: QoQ% | Y68: =+Y66/X66-1 -> 0.14583333 | Z68: =+Z66/Y66-1 -> 0.072727273 | AA68: =+AA66/Z66-1 -> 0.51186441 | AB68: =+AB66/AA66-1 -> -0.37443946 | AC68: =+AC66/AB66-1 -> 0.1827957 | AD68: =+AD66/AC66-1 -> 0.060606061 | AE68: =+AE66/AD66-1 -> 0.12428571 | AF68: =+AF66/AE66-1 -> -0.3519695 | ... AM68: =+AM66/AL66-1 -> 0
W70: Air (mn KG) | X70: 38 | Y70: 41 | Z70: 31 | AA70: =34.3+22.8 -> 57.1 | AB70: =100.5-AA70 -> 43.4 | AC70: =161-AB70-AA70 -> 60.5 | AD70: =198-AC70-AB70-AA70 -> 37 | AE70: 32.9 | AF70: =62.5-AE70 -> 29.6 | AG70: =87.5-AF70-AE70 -> 25 | AH70: =105.1-AG70-AF70-AE70 -> 17.6 | AI70: 21 | AJ70: 25 | AK70: 25 | AL70: 25 | AM70: 25 | AO70: https://www.expolanka.com/uploads/Presentation/IR_Presentation_Q4-2022.pdf
W71: YoY% | AB71: =+AB70/X70-1 -> 0.14210526 | AC71: =+AC70/Y70-1 -> 0.47560976 | AD71: =+AD70/Z70-1 -> 0.19354839 | AE71: =+AE70/AA70-1 -> -0.42381786 | AF71: =+AF70/AB70-1 -> -0.31797235 | AG71: =+AG70/AC70-1 -> -0.58677686 | AH71: =+AH70/AD70-1 -> -0.52432432 | AI71: =+AI70/AE70-1 -> -0.36170213 | ... AM71: =+AM70/AI70-1 -> 0.19047619 | AO71: 40mn Air
W72: QoQ% | Y72: =+Y70/X70-1 -> 0.078947368 | Z72: =+Z70/Y70-1 -> -0.24390244 | AA72: =+AA70/Z70-1 -> 0.84193548 | AB72: =+AB70/AA70-1 -> -0.23992995 | AC72: =+AC70/AB70-1 -> 0.39400922 | AD72: =+AD70/AC70-1 -> -0.38842975 | AE72: =+AE70/AD70-1 -> -0.11081081 | AF72: =+AF70/AE70-1 -> -0.10030395 | ... AM72: =+AM70/AL70-1 -> 0 | AO72: 45k Ocean
W74: Ocean:Air Revenue Split | AD74: 42/58 | AH74: 56/44 | AI74: 54/46
W76: Correlation between Rev and Freight rates | AI76: =+CORREL(X7:AI7,X61:AI61) -> 0.95343273 | AJ76: =+CORREL(X7:AJ7,X61:AJ61) -> 0.95638506

Sheet GLAS
W1: Stock Price | X1: =+'Valuation Sheet'!C10 -> 27.7
B2: TJL - Rs mn | C2: FY16 | D2: FY17 | E2: FY18 | F2: FY19 | G2: FY20 | H2: FY21 | I2: FY22 | J2: CAGR/AVG | M2: MPS | N2: ='[1]LT Portfolio'!I294 -> SELL | P2: AVG | Q2: =J14*J21 -> #DIV/0! | W2: GLAS | X2: 2Q21 | Y2: 3Q21 | Z2: 4Q21 | AA2: 1Q22 | AB2: 2Q22 | AC2: 3Q22 | AD2: 4Q22 | AE2: 1Q23 | AF2: 2Q23 | AG2: 3Q23 | AH2: 4Q23 | AI2: 1Q24 | AJ2: 2Q24 | AK2: 3Q24 | AL2: 4Q24 | AM2: 1Q25 | AP2: =+W2 -> GLAS | AQ2: FY24E | AV2: FY25E
B3: Net Revenue | C3: 17820.179 | M3: P/E | N3: ='[1]LT Portfolio'!W294 -> 0 | W3: Revenue (LKR 000) | X3: 2229746 | Y3: 2400946 | Z3: 2571198 | AA3: 1876183 | AB3: 2264180 | AC3: 2923291 | AD3: 3165357 | AE3: 3884742 | AF3: 4947868 | AG3: 5856865 | AH3: 5377833 | AI3: 4086637 | AJ3: 3699735 | AK3: 4513804 | AL3: 5523333 | AM3: 4117996 | AO3: =AM3-AI3 -> 31359 | AQ3: Revenue | AR3: EBIT | AS3: NP | AT3: EPS | AU3: DPS | AV3: Revenue | AW3: EBIT | AX3: NP | AY3: EPS | AZ3: DPS
B4: Revenue Growth | D4: =(D3/C3-1)*100 -> -100 | E4: =(E3/D3-1)*100 -> #DIV/0! | F4: =(F3/E3-1)*100 -> #DIV/0! | G4: =(G3/F3-1)*100 -> #DIV/0! | H4: =(H3/G3-1)*100 -> #DIV/0! | I4: =(I3/H3-1)*100 -> #DIV/0! | J4: =((I3/D3)^(1/5)-1)*100 -> #DIV/0! | W4: YoY% | AB4: =+AB3/X3-1 -> 0.015443015 | AC4: =+AC3/Y3-1 -> 0.217558 | AD4: =+AD3/Z3-1 -> 0.23108255 | AE4: =+AE3/AA3-1 -> 1.070556 | AF4: =+AF3/AB3-1 -> 1.1852803 | AG4: =+AG3/AC3-1 -> 1.0035176 | AH4: =+AH3/AD3-1 -> 0.69896571 | AI4: =+AI3/AE3-1 -> 0.051971276 | ... AM4: =+AM3/AI3-1 -> 0.0076735467 | AO4: =AL3-AM3 -> 1405337 | AP4: CT CLSA
B5: Gross Profit | C5: 2994.862 | M5: 2Q21 | N5: =202.575/415.481776 -> 0.48756651 | W5: QoQ% | Y5: =+Y3/X3-1 -> 0.076780046 | Z5: =+Z3/Y3-1 -> 0.070910383 | AA5: =+AA3/Z3-1 -> -0.27030785 | AB5: =+AB3/AA3-1 -> 0.20680126 | AC5: =+AC3/AB3-1 -> 0.29110362 | AD5: =+AD3/AC3-1 -> 0.082805988 | AE5: =+AE3/AD3-1 -> 0.2272682 | AF5: =+AF3/AE3-1 -> 0.27366708 | ... AM5: =+AM3/AL3-1 -> -0.25443641 | AP5: Capital Alliance
B6: GPM | C6: =C5/C$3*100 -> 16.806015 | D6: =D5/D$3*100 -> #DIV/0! | E6: =E5/E$3*100 -> #DIV/0! | F6: =F5/F$3*100 -> #DIV/0! | G6: =G5/G$3*100 -> #DIV/0! | H6: =H5/H$3*100 -> #DIV/0! | I6: =I5/I$3*100 -> #DIV/0! | J6: =AVERAGE(D6:I6) -> #DIV/0! | M6: 3Q21 | N6: =261.001/415.481776 -> 0.6281888 | AP6: Asia Securities | AQ6: 17866 | AR6: 3849 | AS6: 2814 | AT6: 2.96 | AU6: 1.5 | AV6: 22199 | AW6: 4759 | AX6: 3492 | AY6: 3.68 | AZ6: 1.9
B7: EBIT | C7: 2167.608 | M7: 4Q21 | N7: ='[1]LT Portfolio'!P294 -> 0 | W7: Revenue (in USD) | AP7: First Capital
B8: EBIT Margin | C8: =C7/C$3*100 -> 12.163784 | D8: =D7/D$3*100 -> #DIV/0! | E8: =E7/E$3*100 -> #DIV/0! | F8: =F7/F$3*100 -> #DIV/0! | G8: =G7/G$3*100 -> #DIV/0! | H8: =H7/H$3*100 -> #DIV/0! | I8: =I7/I$3*100 -> #DIV/0! | J8: =AVERAGE(D8:I8) -> #DIV/0! | M8: 1Q22 | N8: ='[1]LT Portfolio'!Q294 -> 0 | W8: YoY% | AB8: =+AB7/X7-1 -> #DIV/0! | AC8: =+AC7/Y7-1 -> #DIV/0! | AD8: =+AD7/Z7-1 -> #DIV/0! | AE8: =+AE7/AA7-1 -> #DIV/0! | AF8: =+AF7/AB7-1 -> #DIV/0! | AG8: =+AG7/AC7-1 -> #DIV/0! | AH8: =+AH7/AD7-1 -> #DIV/0! | AI8: =+AI7/AE7-1 -> #DIV/0! | ... AM8: =+AM7/AI7-1 -> #DIV/0! | AP8: Bartleet
B9: PBT | C9: 2228.947 | M9: 2Q22 | N9: ='[1]LT Portfolio'!R294 -> 0 | O9: =N9/N5-1 -> -1 | W9: QoQ% | Y9: =+Y7/X7-1 -> #DIV/0! | Z9: =+Z7/Y7-1 -> #DIV/0! | AA9: =+AA7/Z7-1 -> #DIV/0! | AB9: =+AB7/AA7-1 -> #DIV/0! | AC9: =+AC7/AB7-1 -> #DIV/0! | AD9: =+AD7/AC7-1 -> #DIV/0! | AE9: =+AE7/AD7-1 -> #DIV/0! | AF9: =+AF7/AE7-1 -> #DIV/0! | ... AM9: =+AM7/AL7-1 -> #DIV/0! | AP9: Asia Capital
B10: Net Profit | C10: 2170.667 | J10: =((I10/D10)^(1/5)-1)*100 -> #DIV/0! | M10: 3Q22 | N10: ='[1]LT Portfolio'!S294 -> 0 | O10: =N10/N6-1 -> -1 | AP10: JKSB
B11: NP Margin | C11: =C10/C$3*100 -> 12.180949 | D11: =D10/D$3*100 -> #DIV/0! | E11: =E10/E$3*100 -> #DIV/0! | F11: =F10/F$3*100 -> #DIV/0! | G11: =G10/G$3*100 -> #DIV/0! | H11: =H10/H$3*100 -> #DIV/0! | I11: =I10/I$3*100 -> #DIV/0! | J11: =AVERAGE(D11:I11) -> #DIV/0! | M11: 4Q22 | N11: ='[1]LT Portfolio'!T294 -> 0 | O11: =N11/N7-1 -> #DIV/0! | W11: Gross Profit | X11: 527887 | Y11: 650516 | Z11: 623686 | AA11: 444020 | AB11: 597807 | AC11: 837673 | AD11: 925944 | AE11: 925630 | AF11: 1269567 | AG11: 1815083 | AH11: 1544199 | AI11: 992141 | AJ11: 1250516 | AK11: 1445467 | AL11: 1586988 | AM11: 1097794 | AP11: Consensus | AQ11: =+AVERAGE(AQ4:AQ10) -> 17866 | AR11: =+AVERAGE(AR4:AR10) -> 3849 | AS11: =+AVERAGE(AS4:AS10) -> 2814 | AT11: =+AVERAGE(AT4:AT10) -> 2.96 | AU11: =+AVERAGE(AU4:AU10) -> 1.5 | AV11: =+AVERAGE(AV4:AV10) -> 22199 | AW11: =+AVERAGE(AW4:AW10) -> 4759 | AX11: =+AVERAGE(AX4:AX10) -> 3492 | ... AZ11: =+AVERAGE(AZ4:AZ10) -> 1.9
B12: NP Growth | D12: =(D10/C10-1)*100 -> -100 | E12: =(E10/D10-1)*100 -> #DIV/0! | F12: =(F10/E10-1)*100 -> #DIV/0! | G12: =(G10/F10-1)*100 -> #DIV/0! | H12: =(H10/G10-1)*100 -> #DIV/0! | I12: =(I10/H10-1)*100 -> #DIV/0! | J12: =AVERAGE(D12:I12) -> #DIV/0! | S12: 1Q22 | T12: 2Q22 | W12: GPM% | X12: =+X11/X3 -> 0.23674759 | Y12: =+Y11/Y3 -> 0.27094154 | Z12: =+Z11/Z3 -> 0.24256631 | AA12: =+AA11/AA3 -> 0.23666135 | AB12: =+AB11/AB3 -> 0.26402804 | AC12: =+AC11/AC3 -> 0.28655136 | AD12: =+AD11/AD3 -> 0.29252435 | AE12: =+AE11/AE3 -> 0.23827322 | ... AM12: =+AM11/AM3 -> 0.26658452 | AU12: DY | AZ12: DY
M13: TTM | N13: =SUM(N8:N11) -> 0 | Q13: =N13*J21 -> #DIV/0! | S13: 19.109574 | T13: 18.873653 | AP13: Leading P/E | AT13: =+$X$1/AT11 -> 9.3581081 | AU13: =+AU11/$X$1 -> 0.054151625 | AY13: =+$X$1/AY11 -> 7.5271739 | AZ13: =+AZ11/$X$1 -> 0.068592058
B14: EPS | C14: 3.24 | J14: =AVERAGE(D14:I14) -> #DIV/0! | M14: P/E | N14: =N2/N13 -> #VALUE! | Q14: =Q13/N2-1 -> #DIV/0! | S14: =S13/N2-1 -> #VALUE! | T14: =T13/N2-1 -> #VALUE! | W14: EBIT | X14: =+X20-X17 -> 390298 | Y14: =+Y20-Y17 -> 508282 | Z14: =+Z20-Z17 -> 526550 | AA14: =+AA20-AA17 -> 326893 | AB14: =+AB20-AB17 -> 486831 | AC14: =+AC20-AC17 -> 689480 | AD14: =+AD20-AD17 -> 991574 | AE14: =+AE20-AE17 -> 874703 | ... AI14: =+AI20-AI17 -> 583993 | AJ14: 1046568 | AK14: =+AK20-AK17 -> 1143361 | AL14: =+AL20-AL17 -> 1161229 | AM14: =+AM20-AM17 -> 838373
B15: DPS | C15: =1+0.6 -> 1.6 | W15: EBIT margin % | X15: =+X14/X3 -> 0.17504146 | Y15: =+Y14/Y3 -> 0.21170072 | Z15: =+Z14/Z3 -> 0.20478781 | AA15: =+AA14/AA3 -> 0.174233 | AB15: =+AB14/AB3 -> 0.21501427 | AC15: =+AC14/AC3 -> 0.23585746 | AD15: =+AD14/AD3 -> 0.31325819 | AE15: =+AE14/AE3 -> 0.22516373 | ... AM15: =+AM14/AM3 -> 0.20358762
B16: MPS | C16: 31.7 | J16: =((I16/D16)^(1/5)-1)*100 -> #DIV/0!
B17: BVPS | C17: 14.6 | J17: =((I17/D17)^(1/6)-1)*100 -> #DIV/0! | W17: Net Finance Income/Cost | X17: =-75910+63 -> -75847 | Y17: =-66841+123 -> -66718 | Z17: =-42521+59 -> -42462 | AA17: =-39584+100 -> -39484 | AB17: =-39857+42 -> -39815 | AC17: =-42332+50 -> -42282 | AD17: =-37478+232 -> -37246 | AE17: =-49380+89 -> -49291 | AF17: =-115337+245 -> -115092 | AG17: =-100365+336 -> -100029 | AH17: =-65440+366 -> -65074 | AI17: =-20170+181 -> -19989 | AJ17: =-27893+923 -> -26970 | AK17: =-34938+514 -> -34424 | AL17: =-14573+717 -> -13856 | AM17: =-1040+13404 -> 12364
B18: ROE | C18: =C14/AVERAGE(B17:C17)*100 -> 22.191781 | D18: =D14/AVERAGE(C17:D17)*100 -> 0 | E18: =E14/AVERAGE(D17:E17)*100 -> #DIV/0! | F18: =F14/AVERAGE(E17:F17)*100 -> #DIV/0! | G18: =G14/AVERAGE(F17:G17)*100 -> #DIV/0! | H18: =H14/AVERAGE(G17:H17)*100 -> #DIV/0! | I18: =I14/AVERAGE(H17:I17)*100 -> #DIV/0! | J18: =AVERAGE(D18:I18) -> #DIV/0! | M18: MGT | W18: As a % of EBIT | X18: =+X17/X14 -> -0.194331 | Y18: =+Y17/Y14 -> -0.13126178 | Z18: =+Z17/Z14 -> -0.080641914 | AA18: =+AA17/AA14 -> -0.1207857 | AB18: =+AB17/AB14 -> -0.081784028 | AC18: =+AC17/AC14 -> -0.061324476 | AD18: =+AD17/AD14 -> -0.037562502 | AE18: =+AE17/AE14 -> -0.056351699 | ... AM18: =+AM17/AM14 -> 0.014747612
B19: DY | C19: =C15/C16*100 -> 5.0473186 | D19: =D15/D16*100 -> #DIV/0! | E19: =E15/E16*100 -> #DIV/0! | F19: =F15/F16*100 -> #DIV/0! | G19: =G15/G16*100 -> #DIV/0! | H19: =H15/H16*100 -> #DIV/0! | I19: =I15/I16*100 -> #DIV/0! | J19: =AVERAGE(D19:I19) -> #DIV/0!
B20: Dividend Payout | C20: =C15/C14*100 -> 49.382716 | D20: =D15/D14*100 -> #DIV/0! | E20: =E15/E14*100 -> #DIV/0! | F20: =F15/F14*100 -> #DIV/0! | G20: =G15/G14*100 -> #DIV/0! | H20: =H15/H14*100 -> #DIV/0! | I20: =I15/I14*100 -> #DIV/0! | J20: =AVERAGE(D20:I20) -> #DIV/0! | M20: YoY Growth | N20: =N13/H14-1 -> #DIV/0! | W20: PBT | X20: 314451 | Y20: 441564 | Z20: 484088 | AA20: 287409 | AB20: 447016 | AC20: 647198 | AD20: 954328 | AE20: 825412 | AF20: 875642 | AG20: 1332223 | AH20: 927039 | AI20: 564004 | AJ20: 1019598 | AK20: 1108937 | AL20: 1147373 | AM20: 850737
B21: P/E | C21: =C16/C14 -> 9.7839506 | D21: =D16/D14 -> #DIV/0! | E21: =E16/E14 -> #DIV/0! | F21: =F16/F14 -> #DIV/0! | G21: =G16/G14 -> #DIV/0! | H21: =H16/H14 -> #DIV/0! | I21: =I16/I14 -> #DIV/0! | J21: =AVERAGE(D21:I21) -> #DIV/0! | W21: PBT Margin% | X21: =+X20/X3 -> 0.14102548 | Y21: =+Y20/Y3 -> 0.18391251 | Z21: =+Z20/Z3 -> 0.18827333 | AA21: =+AA20/AA3 -> 0.15318815 | AB21: =+AB20/AB3 -> 0.19742953 | AC21: =+AC20/AC3 -> 0.22139363 | AD21: =+AD20/AD3 -> 0.30149143 | AE21: =+AE20/AE3 -> 0.21247537 | ... AM21: =+AM20/AM3 -> 0.20659005
B22: P/B | C22: =C16/C17 -> 2.1712329 | D22: =D16/D17 -> #DIV/0! | E22: =E16/E17 -> #DIV/0! | F22: =F16/F17 -> #DIV/0! | G22: =G16/G17 -> #DIV/0! | H22: =H16/H17 -> #DIV/0! | I22: =I16/I17 -> #DIV/0! | J22: =AVERAGE(D22:I22) -> #DIV/0!
W23: Taxes | X23: 45528 | Y23: -63277 | Z23: -82411 | AA23: -51969 | AB23: -139425 | AC23: -112398 | AD23: -117614 | AE23: -165300 | AF23: -147120 | AG23: -446150 | AH23: -21446 | AI23: -142973 | AJ23: -260210 | AK23: -256382 | AL23: -241517 | AM23: -162432
G24: 701.95658 | H24: 709.32254 | I24: 716.73997 | W24: ETR% | X24: =+X23/X20 -> 0.14478567 | Y24: =+Y23/Y20 -> -0.14330199 | Z24: =+Z23/Z20 -> -0.17023971 | AA24: =+AA23/AA20 -> -0.18081897 | AB24: =+AB23/AB20 -> -0.31190159 | AC24: =+AC23/AC20 -> -0.17366865 | AD24: =+AD23/AD20 -> -0.12324274 | AE24: =+AE23/AE20 -> -0.20026363 | ... AM24: =+AM23/AM20 -> -0.19093092
G25: =+G10/G24 -> 0 | H25: =+H10/H24 -> 0 | I25: =+I10/I24 -> 0
W26: Net Profit Attributable to Equity Holders | X26: =+X20+X23 -> 359979 | Y26: =+Y20+Y23 -> 378287 | Z26: =+Z20+Z23 -> 401677 | AA26: =+AA20+AA23 -> 235440 | AB26: =+AB20+AB23 -> 307591 | AC26: =+AC20+AC23 -> 534800 | AD26: =+AD20+AD23 -> 836714 | AE26: =+AE20+AE23 -> 660112 | ... AM26: =+AM20+AM23 -> 688305
W27: NP Margin | X27: =+X26/X3 -> 0.16144395 | Y27: =+Y26/Y3 -> 0.15755748 | Z27: =+Z26/Z3 -> 0.15622173 | AA27: =+AA26/AA3 -> 0.12548882 | AB27: =+AB26/AB3 -> 0.13585095 | AC27: =+AC26/AC3 -> 0.1829445 | AD27: =+AD26/AD3 -> 0.2643348 | AE27: =+AE26/AE3 -> 0.16992428 | ... AM27: =+AM26/AM3 -> 0.16714562
W29: EPS | X29: =+X26/X44 -> 0.37889093 | Y29: =+Y26/Y44 -> 0.39816076 | Z29: =+Z26/Z44 -> 0.42277959 | AA29: =+AA26/AA44 -> 0.24780912 | AB29: =+AB26/AB44 -> 0.32375066 | AC29: =+AC26/AC44 -> 0.56289636 | AD29: =+AD26/AD44 -> 0.88067178 | AE29: =+AE26/AE44 -> 0.69479178 | ... AM29: =+AM26/AM44 -> 0.72446593
W30: YoY% | AB30: =+AB29/X29-1 -> -0.14553071 | AC30: =+AC29/Y29-1 -> 0.41374142 | AD30: =+AD29/Z29-1 -> 1.0830518 | AE30: =+AE29/AA29-1 -> 1.8037377 | AF30: =+AF29/AB29-1 -> 1.3684763 | AG30: =+AG29/AC29-1 -> 0.65683059 | AH30: =+AH29/AD29-1 -> 0.082320841 | AI30: =+AI29/AE29-1 -> -0.36218248 | ... AM30: =+AM29/AI29-1 -> 0.63480836
W31: QoQ% | Y31: =+Y29/X29-1 -> 0.050858522 | Z31: =+Z29/Y29-1 -> 0.061831361 | AA31: =+AA29/Z29-1 -> -0.4138574 | AB31: =+AB29/AA29-1 -> 0.30645175 | AC31: =+AC29/AB29-1 -> 0.73867246 | AD31: =+AD29/AC29-1 -> 0.56453628 | AE31: =+AE29/AD29-1 -> -0.21106615 | AF31: =+AF29/AE29-1 -> 0.10363393 | ... AM31: =+AM29/AL29-1 -> -0.24016069
W33: RoE | X33: =+X26*4/X38 -> 0.30021179 | Y33: =+Y26*4/Y38 -> 0.29199367 | Z33: =+Z26*4/Z38 -> 0.28852878 | AA33: =+AA26*4/AA38 -> 0.16225822 | AB33: =+AB26*4/AB38 -> 0.22106555 | AC33: =+AC26*4/AC38 -> 0.3645724 | AD33: =+AD26*4/AD38 -> 0.51251827 | AE33: =+AE26*4/AE38 -> 0.36724798 | ... AM33: =+AM26*4/AM38 -> 0.23418163 | AO33: =+AVERAGE(X33:AM33) -> 0.31506446 | AP33: RoE
AO34: =AVERAGE(X33:AM33)*AM46 -> 3.8987426 | AP34: Normalized EPS
W35: Debt | X35: =23302+1406667+10354+1809204+11944 -> 3261471 | Y35: =23917+1164917+9518+1720345+10560 -> 2929257 | Z35: =24677+923167+8531+1364540+128820 -> 2449735 | AA35: =21612+681417+7479+1058529+90968 -> 1860005 | AB35: =22356+439667+6804+1814310+39871 -> 2323008 | AC35: =23104+275917+6633+1756614+49418 -> 2111686 | AD35: =23872+165167+6611+1261202+145365 -> 1602217 | AE35: =19937+99667+6619+1419036+362001 -> 1907260 | AF35: =20678+34167+6567+1678685+394969 -> 2135066 | AG35: =6167+21408+6544+1010953+554954 -> 1600026 | AH35: =22156+6521+623016+5399 -> 657092 | AI35: =14314+6496+322599+255976 -> 599385 | AJ35: =14980+6496+1552696+5431 -> 1579603 | AK35: =15664+6496+959702+17348 -> 999210 | AL35: =16366+6496+33618 -> 56480 | AM35: =10033+5804+17613 -> 33450 | AO35: =X1/AO34 -> 7.1048548 | AP35: P/E
W36: Cash | X36: 88998 | Y36: =186415 -> 186415 | Z36: 125663 | AA36: 137755 | AB36: 194057 | AC36: 141181 | AD36: 182733 | AE36: 51418 | AF36: 397454 | AG36: 477098 | AH36: 183032 | AI36: 125687 | AJ36: 151227 | AK36: 233157 | AL36: 86631 | AM36: 1429245
W37: Net Debt | X37: =+X35-X36 -> 3172473 | Y37: =+Y35-Y36 -> 2742842 | Z37: =+Z35-Z36 -> 2324072 | AA37: =+AA35-AA36 -> 1722250 | AB37: =+AB35-AB36 -> 2128951 | AC37: =+AC35-AC36 -> 1970505 | AD37: =+AD35-AD36 -> 1419484 | AE37: =+AE35-AE36 -> 1855842 | ... AM37: =+AM35-AM36 -> -1395795 | AO37: Dividend Payout
W38: Equity | X38: 4796334 | Y38: 5182126 | Z38: 5568623 | AA38: 5804082 | AB38: 5565607 | AC38: 5867696 | AD38: 6530218 | AE38: 7189823 | AF38: 7918373 | AG38: 8808581 | AH38: 9709121 | AI38: 10130265 | AJ38: 9314171 | AK38: 10172343 | AL38: 11068392 | AM38: 11756772 | AO38: =1.55/3.09 -> 0.50161812
W40: Debt/Equity | X40: =+X35/X38 -> 0.67999247 | Y40: =+Y35/Y38 -> 0.56526163 | Z40: =+Z35/Z38 -> 0.43991755 | AA40: =+AA35/AA38 -> 0.32046498 | AB40: =+AB35/AB38 -> 0.41738628 | AC40: =+AC35/AC38 -> 0.35988333 | AD40: =+AD35/AD38 -> 0.24535429 | AE40: =+AE35/AE38 -> 0.26527218 | ... AM40: =+AM35/AM38 -> 0.0028451687
W42: Average Exchange rate (income Statement) | X42: =+(X3*1000)/X7 -> #DIV/0! | Y42: =+(Y3*1000)/Y7 -> #DIV/0! | Z42: =+(Z3*1000)/Z7 -> #DIV/0! | AA42: =+(AA3*1000)/AA7 -> #DIV/0! | AB42: =+(AB3*1000)/AB7 -> #DIV/0! | AC42: =+(AC3*1000)/AC7 -> #DIV/0! | AD42: =+(AD3*1000)/AD7 -> #DIV/0! | AE42: =+(AE3*1000)/AE7 -> #DIV/0! | ... AM42: =+(AM3*1000)/AM7 -> #DIV/0!
W44: Number of shares | X44: 950086.08 | Y44: 950086.08 | Z44: 950086.08 | AA44: 950086.08 | AB44: 950086.08 | AC44: 950086.08 | AD44: 950086.08 | AE44: 950086.08 | AF44: 950086.08 | AG44: 950086.08 | AH44: 950086.08 | AI44: 950086.08 | AJ44: 950086.08 | AK44: 950086.08 | AL44: 950086.08 | AM44: 950086.08
W46: Net Asset Value per share | X46: =+X38/X44 -> 5.0483152 | Y46: =+Y38/Y44 -> 5.4543752 | Z46: =+Z38/Z44 -> 5.8611773 | AA46: =+AA38/AA44 -> 6.1090065 | AB46: =+AB38/AB44 -> 5.8580029 | AC46: =+AC38/AC44 -> 6.1759625 | AD46: =+AD38/AD44 -> 6.8732909 | AE46: =+AE38/AE44 -> 7.567549 | ... AM46: =+AM38/AM44 -> 12.374428
W48: Cashflow from operations (in LKR 000') | Y48: =+Y52-X52 -> 535184 | Z48: =+Z52-Y52 -> 580815 | AA48: =+AA52 -> 653464 | AB48: =+AB52-AA52 -> 206281 | AC48: =+AC52-AB52 -> 444964 | AD48: =+AD52-AC52 -> 887863 | AE48: =+AE52 -> -369952 | AF48: =+AF52-AE52 -> 217391 | AG48: =+AG52-AF52 -> 676583 | AH48: =+AH52-AG52 -> 732676 | AI48: =+AI52 -> 64561 | AJ48: =+AJ52-AI52 -> 753945 | AK48: =+AK52-AJ52 -> 791353 | AL48: =+AL52-AK52 -> 963148 | AM48: =+AM52 -> 1439541
W49: Capex | Y49: =+Y53-X53 -> -104925 | Z49: =+Z53-Y53 -> -160630 | AA49: =+AA53 -> -51545 | AB49: =+AB53-AA53 -> -81664 | AC49: =+AC53-AB53 -> -52672 | AD49: =+AD53-AC53 -> -93805 | AE49: =+AE53 -> -55917 | AF49: =+AF53-AE53 -> -94160 | AG49: =+AG53-AF53 -> -71284 | AH49: =+AH53-AG53 -> -105530 | AI49: =+AI53 -> -84344 | AJ49: =+AJ53-AI53 -> -165704 | AK49: =+AK53-AJ53 -> -132306 | AL49: =+AL53-AK53 -> -170349 | AM49: =+AM53 -> -85911
W50: FCF (in LKR 000') | Y50: =+Y48+Y49 -> 430259 | Z50: =+Z48+Z49 -> 420185 | AA50: =+AA48+AA49 -> 601919 | AB50: =+AB48+AB49 -> 124617 | AC50: =+AC48+AC49 -> 392292 | AD50: =+AD48+AD49 -> 794058 | AE50: =+AE48+AE49 -> -425869 | AF50: =+AF48+AF49 -> 123231 | ... AM50: =+AM48+AM49 -> 1353630
W52: Cashflow from operations (in LKR 000') | X52: 460244 | Y52: 995428 | Z52: 1576243 | AA52: 653464 | AB52: 859745 | AC52: 1304709 | AD52: 2192572 | AE52: -369952 | AF52: -152561 | AG52: 524022 | AH52: 1256698 | AI52: 64561 | AJ52: 818506 | AK52: 1609859 | AL52: 2573007 | AM52: 1439541
W53: Capex | X53: -113387 | Y53: -218312 | Z53: -378942 | AA53: -51545 | AB53: -133209 | AC53: -185881 | AD53: -279686 | AE53: -55917 | AF53: -150077 | AG53: -221361 | AH53: -326891 | AI53: -84344 | AJ53: -250048 | AK53: -382354 | AL53: -552703 | AM53: -85911
W54: FCF (in LKR 000') | X54: =+X52+X53 -> 346857 | Y54: =+Y52+Y53 -> 777116 | Z54: =+Z52+Z53 -> 1197301 | AA54: =+AA52+AA53 -> 601919 | AB54: =+AB52+AB53 -> 726536 | AC54: =+AC52+AC53 -> 1118828 | AD54: =+AD52+AD53 -> 1912886 | AE54: =+AE52+AE53 -> -425869 | ... AM54: =+AM52+AM53 -> 1353630

Sheet TKYO
W1: Stock Price | X1: =+'Valuation Sheet'!C11 -> 48.8
B2: TJL - Rs mn | C2: FY16 | D2: FY17 | E2: FY18 | F2: FY19 | G2: FY20 | H2: FY21 | I2: FY22 | J2: CAGR/AVG | M2: MPS | N2: ='[1]LT Portfolio'!I294 -> SELL | P2: AVG | Q2: =J14*J21 -> #DIV/0! | W2: TKYO | X2: 2Q21 | Y2: 3Q21 | Z2: 4Q21 | AA2: 1Q22 | AB2: 2Q22 | AC2: 3Q22 | AD2: 4Q22 | AE2: 1Q23 | AF2: 2Q23 | AG2: 3Q23 | AH2: 4Q23 | AI2: 1Q24 | AJ2: 2Q24 | AK2: 3Q24 | AL2: 4Q24 | AM2: 1Q25 | AO2: =+W2 -> TKYO | AP2: FY24E | AU2: FY25E | AZ2: FY26E
B3: Net Revenue | C3: 17820.179 | M3: P/E | N3: ='[1]LT Portfolio'!W294 -> 0 | W3: Revenue (LKR 000) | X3: 11413366 | Y3: 11456233 | Z3: 12372581 | AA3: 10663557 | AB3: 11884766 | AC3: 13771151 | AD3: 16158121 | AE3: 16307249 | AF3: 14010079 | AG3: 12078983 | AH3: 14085368 | AI3: 12019952 | AJ3: 13311060 | AK3: 11347590 | AL3: 13145191 | AM3: 11664753 | AP3: Revenue | AQ3: EBIT | AR3: NP | AS3: EPS | AT3: DPS | AU3: Revenue | AV3: EBIT | AW3: NP | AX3: EPS | AY3: DPS | AZ3: Revenue | BA3: EBIT | BB3: NP | BC3: EPS | BD3: DPS
B4: Revenue Growth | D4: =(D3/C3-1)*100 -> -100 | E4: =(E3/D3-1)*100 -> #DIV/0! | F4: =(F3/E3-1)*100 -> #DIV/0! | G4: =(G3/F3-1)*100 -> #DIV/0! | H4: =(H3/G3-1)*100 -> #DIV/0! | I4: =(I3/H3-1)*100 -> #DIV/0! | J4: =((I3/D3)^(1/5)-1)*100 -> #DIV/0! | W4: YoY% | AB4: =+AB3/X3-1 -> 0.041302452 | AC4: =+AC3/Y3-1 -> 0.20206625 | AD4: =+AD3/Z3-1 -> 0.30596203 | AE4: =+AE3/AA3-1 -> 0.52925042 | AF4: =+AF3/AB3-1 -> 0.17882666 | AG4: =+AG3/AC3-1 -> -0.12287775 | AH4: =+AH3/AD3-1 -> -0.12827933 | AI4: =+AI3/AE3-1 -> -0.26290743 | ... AM4: =+AM3/AI3-1 -> -0.029550784 | AO4: CT CLSA | AP4: 55984 | AR4: 4295 | AS4: 9.7 | AT4: 1.5 | AU4: 60467 | AW4: 4703 | AX4: 10.7 | AY4: 1.6 | AZ4: 68297 | BB4: 5640 | BC4: 12.8 | BD4: 1.9
B5: Gross Profit | C5: 2994.862 | M5: 2Q21 | N5: =202.575/415.481776 -> 0.48756651 | W5: QoQ% | Y5: =+Y3/X3-1 -> 0.0037558596 | Z5: =+Z3/Y3-1 -> 0.079986851 | AA5: =+AA3/Z3-1 -> -0.13812995 | AB5: =+AB3/AA3-1 -> 0.11452173 | AC5: =+AC3/AB3-1 -> 0.15872294 | AD5: =+AD3/AC3-1 -> 0.17333119 | AE5: =+AE3/AD3-1 -> 0.009229291 | AF5: =+AF3/AE3-1 -> -0.14086803 | ... AM5: =+AM3/AL3-1 -> -0.11262202 | AO5: Capital Alliance
B6: GPM | C6: =C5/C$3*100 -> 16.806015 | D6: =D5/D$3*100 -> #DIV/0! | E6: =E5/E$3*100 -> #DIV/0! | F6: =F5/F$3*100 -> #DIV/0! | G6: =G5/G$3*100 -> #DIV/0! | H6: =H5/H$3*100 -> #DIV/0! | I6: =I5/I$3*100 -> #DIV/0! | J6: =AVERAGE(D6:I6) -> #DIV/0! | M6: 3Q21 | N6: =261.001/415.481776 -> 0.6281888 | AO6: Asia Securities | AP6: 54511 | AQ6: 7969 | AR6: 4448 | AS6: 10.09 | AT6: 2.1 | AU6: 53809 | AV6: 5157 | AW6: 2851 | AX6: 6.46 | AY6: 1.3 | AZ6: 62150 | BA6: 6827 | BB6: 3825 | BC6: 8.67 | BD6: 1.4
B7: EBIT | C7: 2167.608 | M7: 4Q21 | N7: ='[1]LT Portfolio'!P294 -> 0 | W7: Revenue (in USD) | AO7: First Capital
B8: EBIT Margin | C8: =C7/C$3*100 -> 12.163784 | D8: =D7/D$3*100 -> #DIV/0! | E8: =E7/E$3*100 -> #DIV/0! | F8: =F7/F$3*100 -> #DIV/0! | G8: =G7/G$3*100 -> #DIV/0! | H8: =H7/H$3*100 -> #DIV/0! | I8: =I7/I$3*100 -> #DIV/0! | J8: =AVERAGE(D8:I8) -> #DIV/0! | M8: 1Q22 | N8: ='[1]LT Portfolio'!Q294 -> 0 | W8: YoY% | AB8: =+AB7/X7-1 -> #DIV/0! | AC8: =+AC7/Y7-1 -> #DIV/0! | AD8: =+AD7/Z7-1 -> #DIV/0! | AE8: =+AE7/AA7-1 -> #DIV/0! | AF8: =+AF7/AB7-1 -> #DIV/0! | AG8: =+AG7/AC7-1 -> #DIV/0! | AH8: =+AH7/AD7-1 -> #DIV/0! | AI8: =+AI7/AE7-1 -> #DIV/0! | ... AM8: =+AM7/AI7-1 -> #DIV/0! | AO8: Bartleet
B9: PBT | C9: 2228.947 | M9: 2Q22 | N9: ='[1]LT Portfolio'!R294 -> 0 | O9: =N9/N5-1 -> -1 | W9: QoQ% | Y9: =+Y7/X7-1 -> #DIV/0! | Z9: =+Z7/Y7-1 -> #DIV/0! | AA9: =+AA7/Z7-1 -> #DIV/0! | AB9: =+AB7/AA7-1 -> #DIV/0! | AC9: =+AC7/AB7-1 -> #DIV/0! | AD9: =+AD7/AC7-1 -> #DIV/0! | AE9: =+AE7/AD7-1 -> #DIV/0! | AF9: =+AF7/AE7-1 -> #DIV/0! | ... AM9: =+AM7/AL7-1 -> #DIV/0! | AO9: Asia Capital | AU9: 57218.62 | AW9: 3191.42 | AX9: 7.24
B10: Net Profit | C10: 2170.667 | J10: =((I10/D10)^(1/5)-1)*100 -> #DIV/0! | M10: 3Q22 | N10: ='[1]LT Portfolio'!S294 -> 0 | O10: =N10/N6-1 -> -1 | AO10: Almas
B11: NP Margin | C11: =C10/C$3*100 -> 12.180949 | D11: =D10/D$3*100 -> #DIV/0! | E11: =E10/E$3*100 -> #DIV/0! | F11: =F10/F$3*100 -> #DIV/0! | G11: =G10/G$3*100 -> #DIV/0! | H11: =H10/H$3*100 -> #DIV/0! | I11: =I10/I$3*100 -> #DIV/0! | J11: =AVERAGE(D11:I11) -> #DIV/0! | M11: 4Q22 | N11: ='[1]LT Portfolio'!T294 -> 0 | O11: =N11/N7-1 -> #DIV/0! | W11: Gross Profit | X11: 3983921 | Y11: 3399147 | Z11: 3024456 | AA11: 2038610 | AB11: 2059131 | AC11: 3476644 | AD11: 3836586 | AE11: 5623498 | AF11: 6090669 | AG11: 4212485 | AH11: 4590972 | AI11: 3932996 | AJ11: 3905306 | AK11: 3595424 | AL11: 4128785 | AM11: 4062181 | AO11: Consensus | AP11: =+AVERAGE(AP4:AP10) -> 55247.5 | AQ11: =+AVERAGE(AQ4:AQ10) -> 7969 | AR11: =+AVERAGE(AR4:AR10) -> 4371.5 | AS11: =+AVERAGE(AS4:AS10) -> 9.895 | AT11: =+AVERAGE(AT4:AT10) -> 1.8 | AU11: =+AVERAGE(AU4:AU10) -> 57164.873 | AV11: =+AVERAGE(AV4:AV10) -> 5157 | AW11: =+AVERAGE(AW4:AW10) -> 3581.8067 | ... BD11: =+AVERAGE(BD4:BD10) -> 1.65
B12: NP Growth | D12: =(D10/C10-1)*100 -> -100 | E12: =(E10/D10-1)*100 -> #DIV/0! | F12: =(F10/E10-1)*100 -> #DIV/0! | G12: =(G10/F10-1)*100 -> #DIV/0! | H12: =(H10/G10-1)*100 -> #DIV/0! | I12: =(I10/H10-1)*100 -> #DIV/0! | J12: =AVERAGE(D12:I12) -> #DIV/0! | S12: 1Q22 | T12: 2Q22 | W12: GPM% | X12: =+X11/X3 -> 0.3490575 | Y12: =+Y11/Y3 -> 0.29670722 | Z12: =+Z11/Z3 -> 0.24444827 | AA12: =+AA11/AA3 -> 0.19117542 | AB12: =+AB11/AB3 -> 0.17325802 | AC12: =+AC11/AC3 -> 0.25245849 | AD12: =+AD11/AD3 -> 0.23744011 | AE12: =+AE11/AE3 -> 0.34484652 | ... AM12: =+AM11/AM3 -> 0.34824406 | AT12: DY | AY12: DY | BD12: DY
M13: TTM | N13: =SUM(N8:N11) -> 0 | Q13: =N13*J21 -> #DIV/0! | S13: 19.109574 | T13: 18.873653 | AO13: Leading P/E | AS13: =+$X$1/AS11 -> 4.9317837 | AT13: =+AT11/$X$1 -> 0.036885246 | AX13: =+$X$1/AX11 -> 6 | AY13: =+AY11/$X$1 -> 0.029713115 | BC13: =+$X$1/BC11 -> 4.545878 | BD13: =+BD11/$X$1 -> 0.033811475
B14: EPS | C14: 3.24 | J14: =AVERAGE(D14:I14) -> #DIV/0! | M14: P/E | N14: =N2/N13 -> #VALUE! | Q14: =Q13/N2-1 -> #DIV/0! | S14: =S13/N2-1 -> #VALUE! | T14: =T13/N2-1 -> #VALUE! | W14: EBIT | X14: 2572300 | Y14: 1639318 | Z14: 904063 | AA14: =74768+473020 -> 547788 | AB14: 312644 | AC14: 2093162 | AD14: 2278067 | AE14: 4007711 | AF14: 4390962 | AG14: 1765455 | AH14: 1638571 | AI14: 1712763 | AJ14: 1297646 | AK14: 540819 | AL14: 1335999 | AM14: 1286843
B15: DPS | C15: =1+0.6 -> 1.6 | W15: EBIT margin % | X15: =+X14/X3 -> 0.22537611 | Y15: =+Y14/Y3 -> 0.14309398 | Z15: =+Z14/Z3 -> 0.073069879 | AA15: =+AA14/AA3 -> 0.051370101 | AB15: =+AB14/AB3 -> 0.026306282 | AC15: =+AC14/AC3 -> 0.15199615 | AD15: =+AD14/AD3 -> 0.14098589 | AE15: =+AE14/AE3 -> 0.24576254 | ... AM15: =+AM14/AM3 -> 0.11031892
B16: MPS | C16: 31.7 | J16: =((I16/D16)^(1/5)-1)*100 -> #DIV/0!
B17: BVPS | C17: 14.6 | J17: =((I17/D17)^(1/6)-1)*100 -> #DIV/0! | W17: Net Finance Income/Cost | X17: =1272-296626 -> -295354 | Y17: =10357-207951 -> -197594 | Z17: =12992-171626 -> -158634 | AA17: =10229-149391 -> -139162 | AB17: =8656-148602 -> -139946 | AC17: =21735-129041 -> -107306 | AD17: =41984-5176724 -> -5134740 | AE17: =77094-3406735 -> -3329641 | AF17: =94452-792621 -> -698169 | AG17: =8234-644814 -> -636580 | AH17: =5029-376675 -> -371646 | AI17: =31491-548845 -> -517354 | AJ17: =103095-429938 -> -326843 | AK17: =92033-325242 -> -233209 | AL17: =-65530-295858 -> -361388 | AM17: =109177-226650 -> -117473
B18: ROE | C18: =C14/AVERAGE(B17:C17)*100 -> 22.191781 | D18: =D14/AVERAGE(C17:D17)*100 -> 0 | E18: =E14/AVERAGE(D17:E17)*100 -> #DIV/0! | F18: =F14/AVERAGE(E17:F17)*100 -> #DIV/0! | G18: =G14/AVERAGE(F17:G17)*100 -> #DIV/0! | H18: =H14/AVERAGE(G17:H17)*100 -> #DIV/0! | I18: =I14/AVERAGE(H17:I17)*100 -> #DIV/0! | J18: =AVERAGE(D18:I18) -> #DIV/0! | M18: MGT | W18: As a % of EBIT | X18: =+X17/X14 -> -0.11482098 | Y18: =+Y17/Y14 -> -0.12053427 | Z18: =+Z17/Z14 -> -0.17546786 | AA18: =+AA17/AA14 -> -0.25404354 | AB18: =+AB17/AB14 -> -0.44762094 | AC18: =+AC17/AC14 -> -0.051265024 | AD18: =+AD17/AD14 -> -2.2539899 | AE18: =+AE17/AE14 -> -0.83080866 | ... AM18: =+AM17/AM14 -> -0.091287748
B19: DY | C19: =C15/C16*100 -> 5.0473186 | D19: =D15/D16*100 -> #DIV/0! | E19: =E15/E16*100 -> #DIV/0! | F19: =F15/F16*100 -> #DIV/0! | G19: =G15/G16*100 -> #DIV/0! | H19: =H15/H16*100 -> #DIV/0! | I19: =I15/I16*100 -> #DIV/0! | J19: =AVERAGE(D19:I19) -> #DIV/0!
B20: Dividend Payout | C20: =C15/C14*100 -> 49.382716 | D20: =D15/D14*100 -> #DIV/0! | E20: =E15/E14*100 -> #DIV/0! | F20: =F15/F14*100 -> #DIV/0! | G20: =G15/G14*100 -> #DIV/0! | H20: =H15/H14*100 -> #DIV/0! | I20: =I15/I14*100 -> #DIV/0! | J20: =AVERAGE(D20:I20) -> #DIV/0! | M20: YoY Growth | N20: =N13/H14-1 -> #DIV/0! | W20: PBT | X20: =+X14+X17 -> 2276946 | Y20: =+Y14+Y17 -> 1441724 | Z20: =+Z14+Z17 -> 745429 | AA20: =+AA14+AA17 -> 408626 | AB20: =+AB14+AB17 -> 172698 | AC20: =+AC14+AC17 -> 1985856 | AD20: =+AD14+AD17 -> -2856673 | AE20: =+AE14+AE17 -> 678070 | ... AM20: =+AM14+AM17 -> 1169370
B21: P/E | C21: =C16/C14 -> 9.7839506 | D21: =D16/D14 -> #DIV/0! | E21: =E16/E14 -> #DIV/0! | F21: =F16/F14 -> #DIV/0! | G21: =G16/G14 -> #DIV/0! | H21: =H16/H14 -> #DIV/0! | I21: =I16/I14 -> #DIV/0! | J21: =AVERAGE(D21:I21) -> #DIV/0! | W21: PBT Margin% | X21: =+X20/X3 -> 0.1994982 | Y21: =+Y20/Y3 -> 0.12584625 | Z21: =+Z20/Z3 -> 0.060248464 | AA21: =+AA20/AA3 -> 0.038319859 | AB21: =+AB20/AB3 -> 0.014531039 | AC21: =+AC20/AC3 -> 0.14420407 | AD21: =+AD20/AD3 -> -0.17679488 | AE21: =+AE20/AE3 -> 0.041580894 | ... AM21: =+AM20/AM3 -> 0.10024816
B22: P/B | C22: =C16/C17 -> 2.1712329 | D22: =D16/D17 -> #DIV/0! | E22: =E16/E17 -> #DIV/0! | F22: =F16/F17 -> #DIV/0! | G22: =G16/G17 -> #DIV/0! | H22: =H16/H17 -> #DIV/0! | I22: =I16/I17 -> #DIV/0! | J22: =AVERAGE(D22:I22) -> #DIV/0!
W23: Taxes | X23: -173198 | Y23: -138517 | Z23: 587891 | AA23: -110827 | AB23: -41147 | AC23: -337236 | AD23: 420923 | AE23: -143274 | AF23: -517000 | AG23: -569874 | AH23: -543597 | AI23: -330309 | AJ23: -328779 | AK23: -114379 | AL23: -252396 | AM23: -462643
G24: 701.95658 | H24: 709.32254 | I24: 716.73997 | W24: ETR% | X24: =+X23/X20 -> -0.076065923 | Y24: =+Y23/Y20 -> -0.096077335 | Z24: =+Z23/Z20 -> 0.78866129 | AA24: =+AA23/AA20 -> -0.27121867 | AB24: =+AB23/AB20 -> -0.23825985 | AC24: =+AC23/AC20 -> -0.16981896 | AD24: =+AD23/AD20 -> -0.14734728 | AE24: =+AE23/AE20 -> -0.21129677 | ... AM24: =+AM23/AM20 -> -0.3956344
G25: =+G10/G24 -> 0 | H25: =+H10/H24 -> 0 | I25: =+I10/I24 -> 0
W26: NCI | X26: -2228 | Y26: -7494 | Z26: -8595 | AA26: 1066 | AB26: 4506 | AC26: 8722 | AD26: 5574 | AE26: 604 | AF26: 1741 | AG26: 2634 | AH26: 5027 | AI26: 1546 | AJ26: 2219 | AK26: -2412 | AL26: 2492 | AM26: 379
W28: Net Profit Attributable to Equity Holders | X28: =+X20+X23-X26 -> 2105976 | Y28: =+Y20+Y23-Y26 -> 1310701 | Z28: =+Z20+Z23-Z26 -> 1341915 | AA28: =+AA20+AA23-AA26 -> 296733 | AB28: =+AB20+AB23-AB26 -> 127045 | AC28: =+AC20+AC23-AC26 -> 1639898 | AD28: =+AD20+AD23-AD26 -> -2441324 | AE28: =+AE20+AE23-AE26 -> 534192 | ... AM28: =+AM20+AM23-AM26 -> 706348
W29: NP Margin | X29: =+X28/X3 -> 0.1845184 | Y29: =+Y28/Y3 -> 0.11440942 | Z29: =+Z28/Z3 -> 0.10845878 | AA29: =+AA28/AA3 -> 0.027826831 | AB29: =+AB28/AB3 -> 0.010689735 | AC29: =+AC28/AC3 -> 0.11908213 | AD29: =+AD28/AD3 -> -0.1510896 | AE29: =+AE28/AE3 -> 0.032757947 | ... AM29: =+AM28/AM3 -> 0.060554047
W31: EPS | X31: =+X28/X47 -> 4.7749685 | Y31: =+Y28/Y47 -> 2.9718079 | Z31: =+Z28/Z47 -> 3.0425807 | AA31: =+AA28/AA47 -> 0.67279529 | AB31: =+AB28/AB47 -> 0.28805451 | AC31: =+AC28/AC47 -> 3.7182102 | AD31: =+AD28/AD47 -> -5.5353173 | AE31: =+AE28/AE47 -> 1.2111961 | ... AM31: =+AM28/AM47 -> 1.6015327
W32: YoY% | AB32: =+AB31/X31-1 -> -0.93967405 | AC32: =+AC31/Y31-1 -> 0.25116102 | AD32: =+AD31/Z31-1 -> -2.8192836 | AE32: =+AE31/AA31-1 -> 0.80024466 | AF32: =+AF31/AB31-1 -> 23.983683 | AG32: =+AG31/AC31-1 -> -0.66073073 | AH32: =+AH31/AD31-1 -> -1.294226 | AI32: =+AI31/AE31-1 -> 0.61656109 | ... AM32: =+AM31/AI31-1 -> -0.18204536
W33: QoQ% | Y33: =+Y31/X31-1 -> -0.37762776 | Z33: =+Z31/Y31-1 -> 0.023814737 | AA33: =+AA31/Z31-1 -> -0.77887348 | AB33: =+AB31/AA31-1 -> -0.57185416 | AC33: =+AC31/AB31-1 -> 11.908009 | AD33: =+AD31/AC31-1 -> -2.4887048 | AE33: =+AE31/AD31-1 -> -1.2188124 | AF33: =+AF31/AE31-1 -> 4.9417812 | ... AM33: =+AM31/AL31-1 -> -0.018583538
W35: RoE | X35: =+X28*4/X40 -> 0.42214139 | Y35: =+Y28*4/Y40 -> 0.2537113 | Z35: =+Z28*4/Z40 -> 0.24417115 | AA35: =+AA28*4/AA40 -> 0.054337433 | AB35: =+AB28*4/AB40 -> 0.023565068 | AC35: =+AC28*4/AC40 -> 0.28268171 | AD35: =+AD28*4/AD40 -> -0.46678387 | AE35: =+AE28*4/AE40 -> 0.099988882 | ... AM35: =+AM28*4/AM40 -> 0.10010613 | AN35: =+AVERAGE(X35:AL35) -> 0.13288721 | AO35: RoE
AN36: =AVERAGE(X35:AL35)*AL49 -> 8.29108 | AO36: Normalized EPS
W37: Debt | X37: =5495389+269907+5552244+43518+431984 -> 11793042 | Y37: =4535678+251136+5278781+43201+536653 -> 10645449 | Z37: =3962571+425726+4212808+94559+436668 -> 9132332 | AA37: =3467745+402854+4308463+85070+937091 -> 9201223 | AB37: =3001972+368847+4129063+83754+541808 -> 8125444 | AC37: =2107624+352041+3082206+84155+770311 -> 6396337 | AD37: =1349873+333956+4187143+86149+982473 -> 6939594 | AE37: =1587549+318363+4693797+1201001+83774 -> 7884484 | AF37: =1201135+307620+6019307+59225+1450602 -> 9037889 | AG37: =890546+296818+9065455+56704+1245913 -> 11555436 | AH37: =1162434+284114+10646498+53808+689961 -> 12836815 | AI37: =1399044+276099+9202801+39978+724831 -> 11642753 | AJ37: =3189970+407014+53483+1233179+6843083 -> 11726729 | AK37: =4069810+409945+9199801+63575+737565 -> 14480696 | AL37: =4600166+429231+8325042+69459+380063 -> 13803961 | AM37: =4405066+410290+8232780+67885+686267 -> 13802288 | AN37: =X1/AN36 -> 5.8858436 | AO37: P/E
W38: Cash | X38: =1763985+7925 -> 1771910 | Y38: =1758369+7903 -> 1766272 | Z38: =7988+1489031 -> 1497019 | AA38: =1454052+8073 -> 1462125 | AB38: =8163+949259 -> 957422 | AC38: =8269+3356363 -> 3364632 | AD38: =8387+6349580 -> 6357967 | AE38: =8606+3446066 -> 3454672 | AF38: =8877+869880 -> 878757 | AG38: =9169+434297 -> 443466 | AH38: =1673752+9519 -> 1683271 | AI38: =1050439+9818 -> 1060257 | AJ38: =749684+10086 -> 759770 | AK38: =1479290+10341 -> 1489631 | AL38: =2221584+10561 -> 2232145 | AM38: =10757+3011007 -> 3021764
W39: Net Debt | X39: =+X37-X38 -> 10021132 | Y39: =+Y37-Y38 -> 8879177 | Z39: =+Z37-Z38 -> 7635313 | AA39: =+AA37-AA38 -> 7739098 | AB39: =+AB37-AB38 -> 7168022 | AC39: =+AC37-AC38 -> 3031705 | AD39: =+AD37-AD38 -> 581627 | AE39: =+AE37-AE38 -> 4429812 | ... AM39: =+AM37-AM38 -> 10780524
W40: Equity | X40: 19955172 | Y40: 20664448 | Z40: 21983187 | AA40: 21843726 | AB40: 21564971 | AC40: 23204869 | AD40: 20920380 | AE40: 21370056 | AF40: 24544108 | AG40: 25100475 | AH40: 25793557 | AI40: 26055685 | AJ40: 26695489 | AK40: 26891132 | AL40: 27517617 | AM40: 28223966
W41: Inventory | X41: 2489349 | Y41: 2639271 | Z41: 3239785 | AA41: 3404981 | AB41: 3541658 | AC41: 4260580 | AD41: 5459542 | AE41: 2900404 | AF41: 5914021 | AG41: 7304513 | AH41: 8352187 | AI41: 6130666 | AJ41: 5129951 | AK41: 6196230 | AL41: 5685180 | AM41: 5915862
W43: Debt/Equity | X43: =+X37/X40 -> 0.59097672 | Y43: =+Y37/Y40 -> 0.51515768 | Z43: =+Z37/Z40 -> 0.41542348 | AA43: =+AA37/AA40 -> 0.42122956 | AB43: =+AB37/AB40 -> 0.37678901 | AC43: =+AC37/AC40 -> 0.27564633 | AD43: =+AD37/AD40 -> 0.33171453 | AE43: =+AE37/AE40 -> 0.36895009 | ... AM43: =+AM37/AM40 -> 0.48902723
W45: Average Exchange rate (income Statement) | X45: =+(X3*1000)/X7 -> #DIV/0! | Y45: =+(Y3*1000)/Y7 -> #DIV/0! | Z45: =+(Z3*1000)/Z7 -> #DIV/0! | AA45: =+(AA3*1000)/AA7 -> #DIV/0! | AB45: =+(AB3*1000)/AB7 -> #DIV/0! | AC45: =+(AC3*1000)/AC7 -> #DIV/0! | AD45: =+(AD3*1000)/AD7 -> #DIV/0! | AE45: =+(AE3*1000)/AE7 -> #DIV/0! | ... AM45: =+(AM3*1000)/AM7 -> #DIV/0!
W47: Number of shares | X47: =Y47 -> 441045 | Y47: =Z47 -> 441045 | Z47: =AA47 -> 441045 | AA47: =AB47 -> 441045 | AB47: =AC47 -> 441045 | AC47: =AD47 -> 441045 | AD47: =AE47 -> 441045 | AE47: =AF47 -> 441045 | ... AI47: =AJ47 -> 441045 | AJ47: =294030+147015 -> 441045 | AK47: =294030+147015 -> 441045 | AL47: =294030+147015 -> 441045 | AM47: =294030+147015 -> 441045
W49: Net Asset Value per share | X49: =+X40/X47 -> 45.245206 | Y49: =+Y40/Y47 -> 46.853378 | Z49: =+Z40/Z47 -> 49.843411 | AA49: =+AA40/AA47 -> 49.527205 | AB49: =+AB40/AB47 -> 48.895172 | AC49: =+AC40/AC47 -> 52.613382 | AD49: =+AD40/AD47 -> 47.433663 | AE49: =+AE40/AE47 -> 48.453233 | ... AM49: =+AM40/AM47 -> 63.993393
W51: Cashflow from operations (in LKR 000') | Y51: =+Y55-X55 -> 2280833 | Z51: =+Z55-Y55 -> 2573658 | AA51: =+AA55 -> 112504 | AB51: =+AB55-AA55 -> 1473197 | AC51: =+AC55-AB55 -> 4691536 | AD51: =+AD55-AC55 -> 2861335 | AE51: =+AE55 -> -3359752 | AF51: =+AF55-AE55 -> -2980740 | AG51: =+AG55-AF55 -> -1880281 | AH51: =+AH55-AG55 -> 746335 | AI51: =+AI55 -> 1869707 | AJ51: =+AJ55-AI55 -> 2698598 | AK51: =+AK55-AJ55 -> -1437034 | AL51: =+AL55-AK55 -> 2430346 | AM51: =+AM55-AL55 -> -4090349
W52: Capex | Y52: =+Y56-X56 -> -538861 | Z52: =+Z56-Y56 -> -1108439 | AA52: =+AA56 -> -291652 | AB52: =+AB56-AA56 -> -570043 | AC52: =+AC56-AB56 -> -551755 | AD52: =+AD56-AC56 -> -448964 | AE52: =+AE56 -> -556178 | AF52: =+AF56-AE56 -> -836419 | AG52: =+AG56-AF56 -> -1067170 | AH52: =+AH56-AG56 -> -789709 | AI52: =+AI56 -> -784435 | AJ52: =+AJ56-AI56 -> -3122233 | AK52: =+AK56-AJ56 -> -490675 | AL52: =+AL56-AK56 -> -999180 | AM52: =+AM56-AL56 -> 6096358
W53: FCF (in LKR 000') | Y53: =+Y51+Y52 -> 1741972 | Z53: =+Z51+Z52 -> 1465219 | AA53: =+AA51+AA52 -> -179148 | AB53: =+AB51+AB52 -> 903154 | AC53: =+AC51+AC52 -> 4139781 | AD53: =+AD51+AD52 -> 2412371 | AE53: =+AE51+AE52 -> -3915930 | AF53: =+AF51+AF52 -> -3817159 | ... AM53: =+AM51+AM52 -> 2006009
W55: Cashflow from operations (in LKR 000') | X55: 5234775 | Y55: 7515608 | Z55: 10089266 | AA55: 112504 | AB55: 1585701 | AC55: 6277237 | AD55: 9138572 | AE55: -3359752 | AF55: -6340492 | AG55: -8220773 | AH55: -7474438 | AI55: 1869707 | AJ55: 4568305 | AK55: 3131271 | AL55: 5561617 | AM55: 1471268
W56: Capex | X56: -459608 | Y56: -998469 | Z56: -2106908 | AA56: -291652 | AB56: -861695 | AC56: -1413450 | AD56: -1862414 | AE56: -556178 | AF56: -1392597 | AG56: -2459767 | AH56: -3249476 | AI56: -784435 | AJ56: -3906668 | AK56: -4397343 | AL56: -5396523 | AM56: 699835
W57: FCF (in LKR 000') | X57: =+X55+X56 -> 4775167 | Y57: =+Y55+Y56 -> 6517139 | Z57: =+Z55+Z56 -> 7982358 | AA57: =+AA55+AA56 -> -179148 | AB57: =+AB55+AB56 -> 724006 | AC57: =+AC55+AC56 -> 4863787 | AD57: =+AD55+AD56 -> 7276158 | AE57: =+AE55+AE56 -> -3915930 | ... AM57: =+AM55+AM56 -> 2171103
W59: Segments
W60: Brushware
W61: Revenue
W62: YoY% | AD62: =+AD61/Z61-1 -> #DIV/0! | AE62: =+AE61/AA61-1 -> #DIV/0! | AF62: =+AF61/AB61-1 -> #DIV/0! | AG62: =+AG61/AC61-1 -> #DIV/0! | AH62: =+AH61/AD61-1 -> #DIV/0! | AI62: =+AI61/AE61-1 -> #DIV/0! | AJ62: =+AJ61/AF61-1 -> #DIV/0! | AK62: =+AK61/AG61-1 -> #DIV/0! | ... AM62: =+AM61/AI61-1 -> #DIV/0!
W63: QoQ% | AA63: =+AA61/Z61-1 -> #DIV/0! | AB63: =+AB61/AA61-1 -> #DIV/0! | AC63: =+AC61/AB61-1 -> #DIV/0! | AD63: =+AD61/AC61-1 -> #DIV/0! | AE63: =+AE61/AD61-1 -> #DIV/0! | AF63: =+AF61/AE61-1 -> #DIV/0! | AG63: =+AG61/AF61-1 -> #DIV/0! | AH63: =+AH61/AG61-1 -> #DIV/0! | ... AM63: =+AM61/AL61-1 -> #DIV/0!
W64: Gross profit
W65: margin% | Z65: =+Z64/Z61 -> #DIV/0! | AA65: =+AA64/AA61 -> #DIV/0! | AB65: =+AB64/AB61 -> #DIV/0! | AC65: =+AC64/AC61 -> #DIV/0! | AD65: =+AD64/AD61 -> #DIV/0! | AE65: =+AE64/AE61 -> #DIV/0! | AF65: =+AF64/AF61 -> #DIV/0! | AG65: =+AG64/AG61 -> #DIV/0! | ... AM65: =+AM64/AM61 -> #DIV/0!
W66: PBT
W67: margin% | Z67: =+Z66/Z61 -> #DIV/0! | AA67: =+AA66/AA61 -> #DIV/0! | AB67: =+AB66/AB61 -> #DIV/0! | AC67: =+AC66/AC61 -> #DIV/0! | AD67: =+AD66/AD61 -> #DIV/0! | AE67: =+AE66/AE61 -> #DIV/0! | AF67: =+AF66/AF61 -> #DIV/0! | AG67: =+AG66/AG61 -> #DIV/0! | ... AM67: =+AM66/AM61 -> #DIV/0!
W69: Filament and Yarn
W70: Revenue
W71: YoY% | AD71: =+AD70/Z70-1 -> #DIV/0! | AE71: =+AE70/AA70-1 -> #DIV/0! | AF71: =+AF70/AB70-1 -> #DIV/0! | AG71: =+AG70/AC70-1 -> #DIV/0! | AH71: =+AH70/AD70-1 -> #DIV/0! | AI71: =+AI70/AE70-1 -> #DIV/0! | AJ71: =+AJ70/AF70-1 -> #DIV/0! | AK71: =+AK70/AG70-1 -> #DIV/0! | ... AM71: =+AM70/AI70-1 -> #DIV/0!
W72: QoQ% | AA72: =+AA70/Z70-1 -> #DIV/0! | AB72: =+AB70/AA70-1 -> #DIV/0! | AC72: =+AC70/AB70-1 -> #DIV/0! | AD72: =+AD70/AC70-1 -> #DIV/0! | AE72: =+AE70/AD70-1 -> #DIV/0! | AF72: =+AF70/AE70-1 -> #DIV/0! | AG72: =+AG70/AF70-1 -> #DIV/0! | AH72: =+AH70/AG70-1 -> #DIV/0! | ... AM72: =+AM70/AL70-1 -> #DIV/0!
W73: Gross profit
W74: margin% | Z74: =+Z73/Z70 -> #DIV/0! | AA74: =+AA73/AA70 -> #DIV/0! | AB74: =+AB73/AB70 -> #DIV/0! | AC74: =+AC73/AC70 -> #DIV/0! | AD74: =+AD73/AD70 -> #DIV/0! | AE74: =+AE73/AE70 -> #DIV/0! | AF74: =+AF73/AF70 -> #DIV/0! | AG74: =+AG73/AG70 -> #DIV/0! | ... AM74: =+AM73/AM70 -> #DIV/0!
W75: PBT
W76: margin% | Z76: =+Z75/Z70 -> #DIV/0! | AA76: =+AA75/AA70 -> #DIV/0! | AB76: =+AB75/AB70 -> #DIV/0! | AC76: =+AC75/AC70 -> #DIV/0! | AD76: =+AD75/AD70 -> #DIV/0! | AE76: =+AE75/AE70 -> #DIV/0! | AF76: =+AF75/AF70 -> #DIV/0! | AG76: =+AG75/AG70 -> #DIV/0! | ... AM76: =+AM75/AM70 -> #DIV/0!

Sheet TILE
W1: Stock Price | X1: =+'Valuation Sheet'!C12 -> 48.9
B2: TJL - Rs mn | C2: FY16 | D2: FY17 | E2: FY18 | F2: FY19 | G2: FY20 | H2: FY21 | I2: FY22 | J2: CAGR/AVG | M2: MPS | N2: ='[1]LT Portfolio'!I294 -> SELL | P2: AVG | Q2: =J14*J21 -> #DIV/0! | W2: TILE | X2: 2Q21 | Y2: 3Q21 | Z2: 4Q21 | AA2: 1Q22 | AB2: 2Q22 | AC2: 3Q22 | AD2: 4Q22 | AE2: 1Q23 | AF2: 2Q23 | AG2: 3Q23 | AH2: 4Q23 | AI2: 1Q24 | AJ2: 2Q24 | AK2: 3Q24 | AL2: 4Q24 | AM2: 1Q25 | AO2: =+W2 -> TILE | AP2: FY24E | AU2: FY25E
B3: Net Revenue | C3: 17820.179 | M3: P/E | N3: ='[1]LT Portfolio'!W294 -> 0 | W3: Revenue (LKR 000) | AD3: 4063882 | AE3: 4120322 | AF3: 5456099 | AG3: 4646839 | AH3: 5065672 | AI3: 3453359 | AJ3: 4399270 | AK3: 5669179 | AL3: 2609728 | AM3: 2428970 | AP3: Revenue | AQ3: EBIT | AR3: NP | AS3: EPS | AT3: DPS | AU3: Revenue | AV3: EBIT | AW3: NP | AX3: EPS | AY3: DPS
B4: Revenue Growth | D4: =(D3/C3-1)*100 -> -100 | E4: =(E3/D3-1)*100 -> #DIV/0! | F4: =(F3/E3-1)*100 -> #DIV/0! | G4: =(G3/F3-1)*100 -> #DIV/0! | H4: =(H3/G3-1)*100 -> #DIV/0! | I4: =(I3/H3-1)*100 -> #DIV/0! | J4: =((I3/D3)^(1/5)-1)*100 -> #DIV/0! | W4: YoY% | AB4: =+AB3/X3-1 -> #DIV/0! | AC4: =+AC3/Y3-1 -> #DIV/0! | AD4: =+AD3/Z3-1 -> #DIV/0! | AE4: =+AE3/AA3-1 -> #DIV/0! | AF4: =+AF3/AB3-1 -> #DIV/0! | AG4: =+AG3/AC3-1 -> #DIV/0! | AH4: =+AH3/AD3-1 -> 0.2465106 | AI4: =+AI3/AE3-1 -> -0.16187157 | ... AM4: =+AM3/AI3-1 -> -0.29663554 | AO4: CT CLSA
B5: Gross Profit | C5: 2994.862 | M5: 2Q21 | N5: =202.575/415.481776 -> 0.48756651 | W5: QoQ% | Y5: =+Y3/X3-1 -> #DIV/0! | Z5: =+Z3/Y3-1 -> #DIV/0! | AA5: =+AA3/Z3-1 -> #DIV/0! | AB5: =+AB3/AA3-1 -> #DIV/0! | AC5: =+AC3/AB3-1 -> #DIV/0! | AD5: =+AD3/AC3-1 -> #DIV/0! | AE5: =+AE3/AD3-1 -> 0.013888199 | AF5: =+AF3/AE3-1 -> 0.32419238 | ... AM5: =+AM3/AL3-1 -> -0.069263157 | AO5: Capital Alliance
B6: GPM | C6: =C5/C$3*100 -> 16.806015 | D6: =D5/D$3*100 -> #DIV/0! | E6: =E5/E$3*100 -> #DIV/0! | F6: =F5/F$3*100 -> #DIV/0! | G6: =G5/G$3*100 -> #DIV/0! | H6: =H5/H$3*100 -> #DIV/0! | I6: =I5/I$3*100 -> #DIV/0! | J6: =AVERAGE(D6:I6) -> #DIV/0! | M6: 3Q21 | N6: =261.001/415.481776 -> 0.6281888 | AO6: Asia Securities
B7: EBIT | C7: 2167.608 | M7: 4Q21 | N7: ='[1]LT Portfolio'!P294 -> 0 | W7: Revenue (in USD) | AO7: First Capital
B8: EBIT Margin | C8: =C7/C$3*100 -> 12.163784 | D8: =D7/D$3*100 -> #DIV/0! | E8: =E7/E$3*100 -> #DIV/0! | F8: =F7/F$3*100 -> #DIV/0! | G8: =G7/G$3*100 -> #DIV/0! | H8: =H7/H$3*100 -> #DIV/0! | I8: =I7/I$3*100 -> #DIV/0! | J8: =AVERAGE(D8:I8) -> #DIV/0! | M8: 1Q22 | N8: ='[1]LT Portfolio'!Q294 -> 0 | W8: YoY% | AB8: =+AB7/X7-1 -> #DIV/0! | AC8: =+AC7/Y7-1 -> #DIV/0! | AD8: =+AD7/Z7-1 -> #DIV/0! | AE8: =+AE7/AA7-1 -> #DIV/0! | AF8: =+AF7/AB7-1 -> #DIV/0! | AG8: =+AG7/AC7-1 -> #DIV/0! | AH8: =+AH7/AD7-1 -> #DIV/0! | AI8: =+AI7/AE7-1 -> #DIV/0! | ... AM8: =+AM7/AI7-1 -> #DIV/0! | AO8: Softlogic
B9: PBT | C9: 2228.947 | M9: 2Q22 | N9: ='[1]LT Portfolio'!R294 -> 0 | O9: =N9/N5-1 -> -1 | W9: QoQ% | Y9: =+Y7/X7-1 -> #DIV/0! | Z9: =+Z7/Y7-1 -> #DIV/0! | AA9: =+AA7/Z7-1 -> #DIV/0! | AB9: =+AB7/AA7-1 -> #DIV/0! | AC9: =+AC7/AB7-1 -> #DIV/0! | AD9: =+AD7/AC7-1 -> #DIV/0! | AE9: =+AE7/AD7-1 -> #DIV/0! | AF9: =+AF7/AE7-1 -> #DIV/0! | ... AM9: =+AM7/AL7-1 -> #DIV/0! | AO9: Consensus | AP9: =+AVERAGE(AP4:AP8) -> #DIV/0! | AQ9: =+AVERAGE(AQ4:AQ8) -> #DIV/0! | AR9: =+AVERAGE(AR4:AR8) -> #DIV/0! | AS9: =+AVERAGE(AS4:AS8) -> #DIV/0! | AT9: =+AVERAGE(AT4:AT8) -> #DIV/0! | AU9: =+AVERAGE(AU4:AU8) -> #DIV/0! | AV9: =+AVERAGE(AV4:AV8) -> #DIV/0! | AW9: =+AVERAGE(AW4:AW8) -> #DIV/0! | ... AY9: =+AVERAGE(AY4:AY8) -> #DIV/0!
B10: Net Profit | C10: 2170.667 | J10: =((I10/D10)^(1/5)-1)*100 -> #DIV/0! | M10: 3Q22 | N10: ='[1]LT Portfolio'!S294 -> 0 | O10: =N10/N6-1 -> -1
B11: NP Margin | C11: =C10/C$3*100 -> 12.180949 | D11: =D10/D$3*100 -> #DIV/0! | E11: =E10/E$3*100 -> #DIV/0! | F11: =F10/F$3*100 -> #DIV/0! | G11: =G10/G$3*100 -> #DIV/0! | H11: =H10/H$3*100 -> #DIV/0! | I11: =I10/I$3*100 -> #DIV/0! | J11: =AVERAGE(D11:I11) -> #DIV/0! | M11: 4Q22 | N11: ='[1]LT Portfolio'!T294 -> 0 | O11: =N11/N7-1 -> #DIV/0! | W11: Gross Profit | AD11: 1865229 | AE11: 2086638 | AF11: 2164184 | AG11: 1970325 | AH11: 2206499 | AI11: 1439662 | AJ11: 2097597 | AK11: 2660721 | AL11: 1264154 | AM11: 834543 | AO11: Leading P/E | AS11: =+$X$1/AS9 -> #DIV/0! | AT11: =+AT9/$X$1 -> #DIV/0! | AX11: =+$X$1/AX9 -> #DIV/0! | AY11: =+AY9/$X$1 -> #DIV/0!
B12: NP Growth | D12: =(D10/C10-1)*100 -> -100 | E12: =(E10/D10-1)*100 -> #DIV/0! | F12: =(F10/E10-1)*100 -> #DIV/0! | G12: =(G10/F10-1)*100 -> #DIV/0! | H12: =(H10/G10-1)*100 -> #DIV/0! | I12: =(I10/H10-1)*100 -> #DIV/0! | J12: =AVERAGE(D12:I12) -> #DIV/0! | S12: 1Q22 | T12: 2Q22 | W12: GPM% | X12: =+X11/X3 -> #DIV/0! | Y12: =+Y11/Y3 -> #DIV/0! | Z12: =+Z11/Z3 -> #DIV/0! | AA12: =+AA11/AA3 -> #DIV/0! | AB12: =+AB11/AB3 -> #DIV/0! | AC12: =+AC11/AC3 -> #DIV/0! | AD12: =+AD11/AD3 -> 0.45897716 | AE12: =+AE11/AE3 -> 0.50642595 | ... AM12: =+AM11/AM3 -> 0.34357897
M13: TTM | N13: =SUM(N8:N11) -> 0 | Q13: =N13*J21 -> #DIV/0! | S13: 19.109574 | T13: 18.873653
B14: EPS | C14: 3.24 | J14: =AVERAGE(D14:I14) -> #DIV/0! | M14: P/E | N14: =N2/N13 -> #VALUE! | Q14: =Q13/N2-1 -> #DIV/0! | S14: =S13/N2-1 -> #VALUE! | T14: =T13/N2-1 -> #VALUE! | W14: EBIT | AD14: 1407693 | AE14: 1434675 | AF14: 1402727 | AG14: 1211950 | AH14: 1248187 | AI14: 732739 | AJ14: 1241470 | AK14: 1599741 | AL14: 548427 | AM14: 224012
B15: DPS | C15: =1+0.6 -> 1.6 | W15: EBIT margin % | X15: =+X14/X3 -> #DIV/0! | Y15: =+Y14/Y3 -> #DIV/0! | Z15: =+Z14/Z3 -> #DIV/0! | AA15: =+AA14/AA3 -> #DIV/0! | AB15: =+AB14/AB3 -> #DIV/0! | AC15: =+AC14/AC3 -> #DIV/0! | AD15: =+AD14/AD3 -> 0.34639121 | AE15: =+AE14/AE3 -> 0.34819487 | ... AM15: =+AM14/AM3 -> 0.0922251
B16: MPS | C16: 31.7 | J16: =((I16/D16)^(1/5)-1)*100 -> #DIV/0!
B17: BVPS | C17: 14.6 | J17: =((I17/D17)^(1/6)-1)*100 -> #DIV/0! | W17: Net Finance Income/Cost | AD17: =58593+122854 -> 181447 | AE17: 104306 | AF17: 96950 | AG17: 80304 | AH17: =-27749-87928 -> -115677 | AI17: -92966 | AJ17: -27723 | AK17: 12363 | AL17: 125200 | AM17: 5884
B18: ROE | C18: =C14/AVERAGE(B17:C17)*100 -> 22.191781 | D18: =D14/AVERAGE(C17:D17)*100 -> 0 | E18: =E14/AVERAGE(D17:E17)*100 -> #DIV/0! | F18: =F14/AVERAGE(E17:F17)*100 -> #DIV/0! | G18: =G14/AVERAGE(F17:G17)*100 -> #DIV/0! | H18: =H14/AVERAGE(G17:H17)*100 -> #DIV/0! | I18: =I14/AVERAGE(H17:I17)*100 -> #DIV/0! | J18: =AVERAGE(D18:I18) -> #DIV/0! | M18: MGT | W18: As a % of EBIT | X18: =+X17/X14 -> #DIV/0! | Y18: =+Y17/Y14 -> #DIV/0! | Z18: =+Z17/Z14 -> #DIV/0! | AA18: =+AA17/AA14 -> #DIV/0! | AB18: =+AB17/AB14 -> #DIV/0! | AC18: =+AC17/AC14 -> #DIV/0! | AD18: =+AD17/AD14 -> 0.12889671 | AE18: =+AE17/AE14 -> 0.072703574 | ... AM18: =+AM17/AM14 -> 0.02626645
B19: DY | C19: =C15/C16*100 -> 5.0473186 | D19: =D15/D16*100 -> #DIV/0! | E19: =E15/E16*100 -> #DIV/0! | F19: =F15/F16*100 -> #DIV/0! | G19: =G15/G16*100 -> #DIV/0! | H19: =H15/H16*100 -> #DIV/0! | I19: =I15/I16*100 -> #DIV/0! | J19: =AVERAGE(D19:I19) -> #DIV/0!
B20: Dividend Payout | C20: =C15/C14*100 -> 49.382716 | D20: =D15/D14*100 -> #DIV/0! | E20: =E15/E14*100 -> #DIV/0! | F20: =F15/F14*100 -> #DIV/0! | G20: =G15/G14*100 -> #DIV/0! | H20: =H15/H14*100 -> #DIV/0! | I20: =I15/I14*100 -> #DIV/0! | J20: =AVERAGE(D20:I20) -> #DIV/0! | M20: YoY Growth | N20: =N13/H14-1 -> #DIV/0! | W20: PBT | AD20: 1589140 | AE20: 1521235 | AF20: 1514319 | AG20: 1116821 | AH20: 1132510 | AI20: 564095 | AJ20: 1185169 | AK20: 1592451 | AL20: 767020 | AM20: 267967
B21: P/E | C21: =C16/C14 -> 9.7839506 | D21: =D16/D14 -> #DIV/0! | E21: =E16/E14 -> #DIV/0! | F21: =F16/F14 -> #DIV/0! | G21: =G16/G14 -> #DIV/0! | H21: =H16/H14 -> #DIV/0! | I21: =I16/I14 -> #DIV/0! | J21: =AVERAGE(D21:I21) -> #DIV/0! | W21: PBT Margin% | X21: =+X20/X3 -> #DIV/0! | Y21: =+Y20/Y3 -> #DIV/0! | Z21: =+Z20/Z3 -> #DIV/0! | AA21: =+AA20/AA3 -> #DIV/0! | AB21: =+AB20/AB3 -> #DIV/0! | AC21: =+AC20/AC3 -> #DIV/0! | AD21: =+AD20/AD3 -> 0.3910399 | AE21: =+AE20/AE3 -> 0.36920294 | ... AM21: =+AM20/AM3 -> 0.11032125
B22: P/B | C22: =C16/C17 -> 2.1712329 | D22: =D16/D17 -> #DIV/0! | E22: =E16/E17 -> #DIV/0! | F22: =F16/F17 -> #DIV/0! | G22: =G16/G17 -> #DIV/0! | H22: =H16/H17 -> #DIV/0! | I22: =I16/I17 -> #DIV/0! | J22: =AVERAGE(D22:I22) -> #DIV/0!
W23: Taxes | AD23: -313499 | AE23: -365649 | AF23: -278416 | AG23: -672519 | AH23: -280499 | AI23: -177034 | AJ23: -375631 | AK23: -509106 | AL23: -140092 | AM23: -60810
G24: 701.95658 | H24: 709.32254 | I24: 716.73997 | W24: ETR% | X24: =+X23/X20 -> #DIV/0! | Y24: =+Y23/Y20 -> #DIV/0! | Z24: =+Z23/Z20 -> #DIV/0! | AA24: =+AA23/AA20 -> #DIV/0! | AB24: =+AB23/AB20 -> #DIV/0! | AC24: =+AC23/AC20 -> #DIV/0! | AD24: =+AD23/AD20 -> -0.19727589 | AE24: =+AE23/AE20 -> -0.24036326 | ... AM24: =+AM23/AM20 -> -0.22693093
G25: =+G10/G24 -> 0 | H25: =+H10/H24 -> 0 | I25: =+I10/I24 -> 0
W26: NCI | AD26: 56 | AE26: 25 | AF26: 109 | AG26: -2 | AH26: 83 | AI26: 59 | AJ26: -694 | AK26: -994 | AL26: -3777 | AM26: -4651
W28: Net Profit Attributable to Equity Holders | X28: =+X20+X23-X26 -> 0 | Y28: =+Y20+Y23-Y26 -> 0 | Z28: =+Z20+Z23-Z26 -> 0 | AA28: =+AA20+AA23-AA26 -> 0 | AB28: =+AB20+AB23-AB26 -> 0 | AC28: =+AC20+AC23-AC26 -> 0 | AD28: =+AD20+AD23-AD26 -> 1275585 | AE28: =+AE20+AE23-AE26 -> 1155561 | ... AL28: =+AL20+AL23-AL26 -> 630705 | AM28: 211808
W29: NP Margin | X29: =+X28/X3 -> #DIV/0! | Y29: =+Y28/Y3 -> #DIV/0! | Z29: =+Z28/Z3 -> #DIV/0! | AA29: =+AA28/AA3 -> #DIV/0! | AB29: =+AB28/AB3 -> #DIV/0! | AC29: =+AC28/AC3 -> #DIV/0! | AD29: =+AD28/AD3 -> 0.31388338 | AE29: =+AE28/AE3 -> 0.28045405 | ... AM29: =+AM28/AM3 -> 0.087200748
W31: EPS | X31: =+X28/X47 -> 0 | Y31: =+Y28/Y47 -> 0 | Z31: =+Z28/Z47 -> 0 | AA31: =+AA28/AA47 -> 0 | AB31: =+AB28/AB47 -> 0 | AC31: =+AC28/AC47 -> 0 | AD31: =+AD28/AD47 -> 4.8089544 | AE31: =+AE28/AE47 -> 4.356464 | ... AM31: =+AM28/AM47 -> 0.79851598
W32: YoY% | AB32: =+AB31/X31-1 -> #DIV/0! | AC32: =+AC31/Y31-1 -> #DIV/0! | AD32: =+AD31/Z31-1 -> #DIV/0! | AE32: =+AE31/AA31-1 -> #DIV/0! | AF32: =+AF31/AB31-1 -> #DIV/0! | AG32: =+AG31/AC31-1 -> #DIV/0! | AH32: =+AH31/AD31-1 -> -0.33212761 | AI32: =+AI31/AE31-1 -> -0.665096 | ... AM32: =+AM31/AI31-1 -> -0.45269533
W33: QoQ% | Y33: =+Y31/X31-1 -> #DIV/0! | Z33: =+Z31/Y31-1 -> #DIV/0! | AA33: =+AA31/Z31-1 -> #DIV/0! | AB33: =+AB31/AA31-1 -> #DIV/0! | AC33: =+AC31/AB31-1 -> #DIV/0! | AD33: =+AD31/AC31-1 -> #DIV/0! | AE33: =+AE31/AD31-1 -> -0.094093298 | AF33: =+AF31/AE31-1 -> 0.069432077 | ... AM33: =+AM31/AL31-1 -> -0.66417263
W35: RoE | X35: =+X28*4/X40 -> #DIV/0! | Y35: =+Y28*4/Y40 -> #DIV/0! | Z35: =+Z28*4/Z40 -> #DIV/0! | AA35: =+AA28*4/AA40 -> #DIV/0! | AB35: =+AB28*4/AB40 -> #DIV/0! | AC35: =+AC28*4/AC40 -> 0 | AD35: =+AD28*4/AD40 -> #DIV/0! | AE35: =+AE28*4/AE40 -> #DIV/0! | ... AM35: =+AM28*4/AM40 -> 0.056622834 | AN35: =+AVERAGE(AH35:AL35) -> 0.21536605 | AO35: RoE
AN36: =AVERAGE(AH35:AL35)*AL49 -> 12.126384 | AO36: Normalized EPS
W37: Debt | AC37: =38753+666667+36753+232352+250000+475639 -> 1700164 | AH37: =17738+416667+20788+750000+545095 -> 1750288 | AI37: =375000+28672+163862+525000+470543 -> 1563077 | AJ37: =40871+291667+44678+260115+350000+102310 -> 1089641 | AK37: =33033+250000+39638+438921+229167+50770 -> 1041529 | AL37: =21623+166667+35712+132188+651623+277630 -> 1285443 | AM37: =8796+145833+34496+227956+1438213+574521 -> 2429815 | AN37: =X1/AN36 -> 4.0325293 | AO37: P/E
W38: Cash | AC38: 4936501 | AH38: 810691 | AI38: 558116 | AJ38: 243130 | AK38: 1803802 | AL38: =306811+895532 -> 1202343 | AM38: =477566+788050 -> 1265616
W39: Net Debt | X39: =+X37-X38 -> 0 | Y39: =+Y37-Y38 -> 0 | Z39: =+Z37-Z38 -> 0 | AA39: =+AA37-AA38 -> 0 | AB39: =+AB37-AB38 -> 0 | AC39: =+AC37-AC38 -> -3236337 | AD39: =+AD37-AD38 -> 0 | AE39: =+AE37-AE38 -> 0 | ... AM39: =+AM37-AM38 -> 1164199
W40: Equity | AC40: 12219323 | AH40: 12922261 | AI40: 13016611 | AJ40: 13827436 | AK40: 14910378 | AL40: 14935262 | AM40: 14962727
W41: Inventory | AC41: 2473794 | AH41: 5036886 | AI41: 5388356 | AJ41: 6034080 | AK41: 6106452 | AL41: 7414063 | AM41: 7414063
W43: Debt/Equity | X43: =+X37/X40 -> #DIV/0! | Y43: =+Y37/Y40 -> #DIV/0! | Z43: =+Z37/Z40 -> #DIV/0! | AA43: =+AA37/AA40 -> #DIV/0! | AB43: =+AB37/AB40 -> #DIV/0! | AC43: =+AC37/AC40 -> 0.13913733 | AD43: =+AD37/AD40 -> #DIV/0! | AE43: =+AE37/AE40 -> #DIV/0! | ... AM43: =+AM37/AM40 -> 0.16239119
W45: Average Exchange rate (income Statement) | X45: =+(X3*1000)/X7 -> #DIV/0! | Y45: =+(Y3*1000)/Y7 -> #DIV/0! | Z45: =+(Z3*1000)/Z7 -> #DIV/0! | AA45: =+(AA3*1000)/AA7 -> #DIV/0! | AB45: =+(AB3*1000)/AB7 -> #DIV/0! | AC45: =+(AC3*1000)/AC7 -> #DIV/0! | AD45: =+(AD3*1000)/AD7 -> #DIV/0! | AE45: =+(AE3*1000)/AE7 -> #DIV/0! | ... AM45: =+(AM3*1000)/AM7 -> #DIV/0!
W47: Number of shares | X47: =Y47 -> 265252.05 | Y47: =Z47 -> 265252.05 | Z47: =AA47 -> 265252.05 | AA47: =AB47 -> 265252.05 | AB47: =AC47 -> 265252.05 | AC47: =AD47 -> 265252.05 | AD47: =AE47 -> 265252.05 | AE47: =AF47 -> 265252.05 | ... AI47: =AJ47 -> 265252.05 | AJ47: 265252.05 | AK47: 265252.05 | AL47: 265252.05 | AM47: 265252.05
W49: Net Asset Value per share | X49: =+X40/X47 -> 0 | Y49: =+Y40/Y47 -> 0 | Z49: =+Z40/Z47 -> 0 | AA49: =+AA40/AA47 -> 0 | AB49: =+AB40/AB47 -> 0 | AC49: =+AC40/AC47 -> 46.066837 | AD49: =+AD40/AD47 -> 0 | AE49: =+AE40/AE47 -> 0 | ... AM49: =+AM40/AM47 -> 56.409468
W51: Cashflow from operations (in LKR 000') | Y51: =+Y55-X55 -> 0 | Z51: =+Z55-Y55 -> 0 | AA51: =+AA55 -> 0 | AB51: =+AB55-AA55 -> 0 | AC51: =+AC55-AB55 -> 0 | AD51: =+AD55-AC55 -> 4802042 | AE51: =+AE55 -> -496516 | AF51: =+AF55-AE55 -> -852487 | AG51: =+AG55-AF55 -> -706728 | AH51: =+AH55-AG55 -> 833055 | AI51: =+AI55 -> 277961 | AJ51: =+AJ55-AI55 -> 850328 | AK51: =+AK55-AJ55 -> 2182931 | AL51: =+AL55-AK55 -> -582468 | AM51: =+AM55-AL55 -> -3441551
W52: Capex | Y52: =+Y56-X56 -> 0 | Z52: =+Z56-Y56 -> 0 | AA52: =+AA56 -> 0 | AB52: =+AB56-AA56 -> 0 | AC52: =+AC56-AB56 -> 0 | AD52: =+AD56-AC56 -> -700196 | AE52: =+AE56 -> -66708 | AF52: =+AF56-AE56 -> -87482 | AG52: =+AG56-AF56 -> -179647 | AH52: =+AH56-AG56 -> -651776 | AI52: =+AI56 -> -175678 | AJ52: =+AJ56-AI56 -> -249334 | AK52: =+AK56-AJ56 -> -447538 | AL52: =+AL56-AK56 -> -157921 | AM52: =+AM56-AL56 -> 866681
W53: FCF (in LKR 000') | Y53: =+Y51+Y52 -> 0 | Z53: =+Z51+Z52 -> 0 | AA53: =+AA51+AA52 -> 0 | AB53: =+AB51+AB52 -> 0 | AC53: =+AC51+AC52 -> 0 | AD53: =+AD51+AD52 -> 4101846 | AE53: =+AE51+AE52 -> -563224 | AF53: =+AF51+AF52 -> -939969 | ... AM53: =+AM51+AM52 -> -2574870
W55: Cashflow from operations (in LKR 000') | AD55: 4802042 | AE55: -496516 | AF55: -1349003 | AG55: -2055731 | AH55: -1222676 | AI55: 277961 | AJ55: 1128289 | AK55: 3311220 | AL55: 2728752 | AM55: -712799
W56: Capex | AD56: -700196 | AE56: -66708 | AF56: -154190 | AG56: -333837 | AH56: -985613 | AI56: -175678 | AJ56: -425012 | AK56: -872550 | AL56: -1030471 | AM56: -163790
W57: FCF (in LKR 000') | X57: =+X55+X56 -> 0 | Y57: =+Y55+Y56 -> 0 | Z57: =+Z55+Z56 -> 0 | AA57: =+AA55+AA56 -> 0 | AB57: =+AB55+AB56 -> 0 | AC57: =+AC55+AC56 -> 0 | AD57: =+AD55+AD56 -> 4101846 | AE57: =+AE55+AE56 -> -563224 | ... AM57: =+AM55+AM56 -> -876589
W59: Local Sales
W60: Revenue | AD60: 4266833 | AE60: 4357355 | AF60: 5277908 | AG60: 4558365 | AH60: 5706476 | AI60: 3794176 | AJ60: 4907125 | AK60: 5585637 | AL60: 2482485 | AM60: 2287889
W61: YoY% | AD61: =+AD60/Z60-1 -> #DIV/0! | AE61: =+AE60/AA60-1 -> #DIV/0! | AF61: =+AF60/AB60-1 -> #DIV/0! | AG61: =+AG60/AC60-1 -> #DIV/0! | AH61: =+AH60/AD60-1 -> 0.33740317 | AI61: =+AI60/AE60-1 -> -0.1292479 | AJ61: =+AJ60/AF60-1 -> -0.070251888 | AK61: =+AK60/AG60-1 -> 0.22535975 | ... AM61: =+AM60/AI60-1 -> -0.39699977
W62: QoQ% | AA62: =+AA60/Z60-1 -> #DIV/0! | AB62: =+AB60/AA60-1 -> #DIV/0! | AC62: =+AC60/AB60-1 -> #DIV/0! | AD62: =+AD60/AC60-1 -> #DIV/0! | AE62: =+AE60/AD60-1 -> 0.021215267 | AF62: =+AF60/AE60-1 -> 0.21126417 | AG62: =+AG60/AF60-1 -> -0.1363311 | AH62: =+AH60/AG60-1 -> 0.25186904 | ... AM62: =+AM60/AL60-1 -> -0.078387583
W64: Exports
W65: Revenue | AD65: 115789 | AE65: 155315 | AF65: 178191 | AG65: 88474 | AH65: 103518 | AI65: 154075 | AJ65: 132206 | AK65: 83542 | AL65: 127243 | AM65: 141082
W66: YoY% | AD66: =+AD65/Z65-1 -> #DIV/0! | AE66: =+AE65/AA65-1 -> #DIV/0! | AF66: =+AF65/AB65-1 -> #DIV/0! | AG66: =+AG65/AC65-1 -> #DIV/0! | AH66: =+AH65/AD65-1 -> -0.10597725 | AI66: =+AI65/AE65-1 -> -0.0079837749 | AJ66: =+AJ65/AF65-1 -> -0.25806578 | AK66: =+AK65/AG65-1 -> -0.055745191 | ... AM66: =+AM65/AI65-1 -> -0.084329061
W67: QoQ% | AA67: =+AA65/Z65-1 -> #DIV/0! | AB67: =+AB65/AA65-1 -> #DIV/0! | AC67: =+AC65/AB65-1 -> #DIV/0! | AD67: =+AD65/AC65-1 -> #DIV/0! | AE67: =+AE65/AD65-1 -> 0.34136231 | AF67: =+AF65/AE65-1 -> 0.14728777 | AG67: =+AG65/AF65-1 -> -0.50348783 | AH67: =+AH65/AG65-1 -> 0.17003866 | ... AM67: =+AM65/AL65-1 -> 0.1087604
W68: As a % of Total | AD68: =+AD65/(AD65+AD60) -> 0.026420029 | AE68: =+AE65/(AE65+AE60) -> 0.03441754 | AF68: =+AF65/(AF65+AF60) -> 0.032659048 | AG68: =+AG65/(AG65+AG60) -> 0.01903961 | AH68: =+AH65/(AH65+AH60) -> 0.01781723 | AI68: =+AI65/(AI65+AI60) -> 0.039023608 | AJ68: =+AJ65/(AJ65+AJ60) -> 0.026234832 | AK68: =+AK65/(AK65+AK60) -> 0.014736173 | ... AM68: =+AM65/(AM65+AM60) -> 0.058083032

Sheet JAT
W1: Stock Price | X1: =+'Valuation Sheet'!C13 -> 17.9
B2: TJL - Rs mn | C2: FY16 | D2: FY17 | E2: FY18 | F2: FY19 | G2: FY20 | H2: FY21 | I2: FY22 | J2: CAGR/AVG | M2: MPS | N2: ='[1]LT Portfolio'!I294 -> SELL | P2: AVG | Q2: =J14*J21 -> #DIV/0! | W2: JAT | X2: 2Q21 | Y2: 3Q21 | Z2: 4Q21 | AA2: 1Q22 | AB2: 2Q22 | AC2: 3Q22 | AD2: 4Q22 | AE2: 1Q23 | AF2: 2Q23 | AG2: 3Q23 | AH2: 4Q23 | AI2: 1Q24 | AJ2: 2Q24 | AK2: 3Q24 | AL2: 4Q24 | AO2: =+W2 -> JAT | AP2: FY24E | AU2: FY25E
B3: Net Revenue | C3: 17820.179 | M3: P/E | N3: ='[1]LT Portfolio'!W294 -> 0 | W3: Revenue (LKR 000) | AC3: 2302721.9 | AD3: 3465047.1 | AE3: 1935037.4 | AF3: 2456773.8 | AG3: 2552879.4 | AH3: 3222636.3 | AI3: 2137381.5 | AJ3: 2740546.3 | AK3: 3009495.4 | AL3: 3673053.1 | AP3: Revenue | AQ3: EBIT | AR3: NP | AS3: EPS | AT3: DPS | AU3: Revenue | AV3: EBIT | AW3: NP | AX3: EPS | AY3: DPS
B4: Revenue Growth | D4: =(D3/C3-1)*100 -> -100 | E4: =(E3/D3-1)*100 -> #DIV/0! | F4: =(F3/E3-1)*100 -> #DIV/0! | G4: =(G3/F3-1)*100 -> #DIV/0! | H4: =(H3/G3-1)*100 -> #DIV/0! | I4: =(I3/H3-1)*100 -> #DIV/0! | J4: =((I3/D3)^(1/5)-1)*100 -> #DIV/0! | W4: YoY% | AB4: =+AB3/X3-1 -> #DIV/0! | AC4: =+AC3/Y3-1 -> #DIV/0! | AD4: =+AD3/Z3-1 -> #DIV/0! | AE4: =+AE3/AA3-1 -> #DIV/0! | AF4: =+AF3/AB3-1 -> #DIV/0! | AG4: =+AG3/AC3-1 -> 0.10863554 | AH4: =+AH3/AD3-1 -> -0.069958874 | AI4: =+AI3/AE3-1 -> 0.10456861 | ... AL4: =+AL3/AH3-1 -> 0.13976655 | AO4: CT CLSA
B5: Gross Profit | C5: 2994.862 | M5: 2Q21 | N5: =202.575/415.481776 -> 0.48756651 | W5: QoQ% | Y5: =+Y3/X3-1 -> #DIV/0! | Z5: =+Z3/Y3-1 -> #DIV/0! | AA5: =+AA3/Z3-1 -> #DIV/0! | AB5: =+AB3/AA3-1 -> #DIV/0! | AC5: =+AC3/AB3-1 -> #DIV/0! | AD5: =+AD3/AC3-1 -> 0.50476141 | AE5: =+AE3/AD3-1 -> -0.44155525 | AF5: =+AF3/AE3-1 -> 0.26962604 | ... AL5: =+AL3/AK3-1 -> 0.22048803 | AO5: Capital Alliance
B6: GPM | C6: =C5/C$3*100 -> 16.806015 | D6: =D5/D$3*100 -> #DIV/0! | E6: =E5/E$3*100 -> #DIV/0! | F6: =F5/F$3*100 -> #DIV/0! | G6: =G5/G$3*100 -> #DIV/0! | H6: =H5/H$3*100 -> #DIV/0! | I6: =I5/I$3*100 -> #DIV/0! | J6: =AVERAGE(D6:I6) -> #DIV/0! | M6: 3Q21 | N6: =261.001/415.481776 -> 0.6281888 | AO6: Asia Securities
B7: EBIT | C7: 2167.608 | M7: 4Q21 | N7: ='[1]LT Portfolio'!P294 -> 0 | W7: Revenue (in USD) | AO7: First Capital
B8: EBIT Margin | C8: =C7/C$3*100 -> 12.163784 | D8: =D7/D$3*100 -> #DIV/0! | E8: =E7/E$3*100 -> #DIV/0! | F8: =F7/F$3*100 -> #DIV/0! | G8: =G7/G$3*100 -> #DIV/0! | H8: =H7/H$3*100 -> #DIV/0! | I8: =I7/I$3*100 -> #DIV/0! | J8: =AVERAGE(D8:I8) -> #DIV/0! | M8: 1Q22 | N8: ='[1]LT Portfolio'!Q294 -> 0 | W8: YoY% | AB8: =+AB7/X7-1 -> #DIV/0! | AC8: =+AC7/Y7-1 -> #DIV/0! | AD8: =+AD7/Z7-1 -> #DIV/0! | AE8: =+AE7/AA7-1 -> #DIV/0! | AF8: =+AF7/AB7-1 -> #DIV/0! | AG8: =+AG7/AC7-1 -> #DIV/0! | AH8: =+AH7/AD7-1 -> #DIV/0! | AI8: =+AI7/AE7-1 -> #DIV/0! | ... AL8: =+AL7/AH7-1 -> #DIV/0! | AO8: Bartleet
B9: PBT | C9: 2228.947 | M9: 2Q22 | N9: ='[1]LT Portfolio'!R294 -> 0 | O9: =N9/N5-1 -> -1 | W9: QoQ% | Y9: =+Y7/X7-1 -> #DIV/0! | Z9: =+Z7/Y7-1 -> #DIV/0! | AA9: =+AA7/Z7-1 -> #DIV/0! | AB9: =+AB7/AA7-1 -> #DIV/0! | AC9: =+AC7/AB7-1 -> #DIV/0! | AD9: =+AD7/AC7-1 -> #DIV/0! | AE9: =+AE7/AD7-1 -> #DIV/0! | AF9: =+AF7/AE7-1 -> #DIV/0! | ... AL9: =+AL7/AK7-1 -> #DIV/0! | AO9: Asia Capital
B10: Net Profit | C10: 2170.667 | J10: =((I10/D10)^(1/5)-1)*100 -> #DIV/0! | M10: 3Q22 | N10: ='[1]LT Portfolio'!S294 -> 0 | O10: =N10/N6-1 -> -1 | AO10: Almas
